Workbook

Sheet department
A1: Name | B1: Parent
A2: Medical Record
A3: Registration and billing
A4: Respiratory medicine
A5: Medicine
A6: Paediatrics
A7: Endocrinology
A8: Pulmonary and Critical Care Medicine
A9: Radiation Oncology
A10: Obstetrics and Gynaecology
A11: Otorhinolaryngology (ENT)
A12: Ophthalmology (EYE)
A13: Surgery
... A31: Anatomy

Sheet location
A1: Building | B1: type | C1: description | D1: floor | E1: type | F1: description | G1: Room | H1: type | I1: description | J1: Bed | K1: type | L1: description | M1: department
A2: Dental | B2: building
A3: Academic Block | B3: building | C3: Academic Building | D3: First Floor | E3: level | F3: First floor in Academic Building | G3: Department of Biochemistry | H3: wing | M3: Biochemistry
A4: Academic Block | B4: building | C4: Academic Building | D4: Ground Floor | E4: level | F4: Ground floor in Academic Building | G4: Department of Microbiology | H4: wing | M4: Microbiology
A5: Academic Block | B5: building | C5: Academic Building | D5: Ground Floor | E5: level | F5: Ground floor in Academic Building | G5: Department of Pathology | H5: wing | M5: Pathology
A6: Medicine Block | B6: building | C6: New IPD building | D6: Fourth Floor | E6: level | F6: Fourth floor in Medicine Block New IPD building | G6: Hematology ward | H6: ward | I6: Hematology Ward in New IPD Building | M6: Medicine
A7: Medicine Block | B7: building | C7: New IPD building | D7: Fourth Floor | E7: level | F7: Fourth floor in Medicine Block New IPD building | G7: Hematology ward | H7: ward | I7: Hematology Ward in New IPD Building | J7: BED 1 | K7: bed
A8: Medicine Block | B8: building | C8: New IPD building | D8: Fourth Floor | E8: level | F8: Fourth floor in Medicine Block New IPD building | G8: Hematology ward | H8: ward | I8: Hematology Ward in New IPD Building | J8: BED 2 | K8: bed
A9: Medicine Block | B9: building | C9: New IPD building | D9: Fourth Floor | E9: level | F9: Fourth floor in Medicine Block New IPD building | G9: Hematology ward | H9: ward | I9: Hematology Ward in New IPD Building | J9: BED 3 | K9: bed
A10: Medicine Block | B10: building | C10: New IPD building | D10: Fourth Floor | E10: level | F10: Fourth floor in Medicine Block New IPD building | G10: Hematology ward | H10: ward | I10: Hematology Ward in New IPD Building | J10: BED 4 | K10: bed
A11: Medicine Block | B11: building | C11: New IPD building | D11: Fourth Floor | E11: level | F11: Fourth floor in Medicine Block New IPD building | G11: Female Nephrology Ward | H11: ward | I11: Female Nephrology Ward in New IPD Building | M11: Medicine
A12: Medicine Block | B12: building | C12: New IPD building | D12: Fourth Floor | E12: level | F12: Fourth floor in Medicine Block New IPD building | G12: Female Nephrology Ward | H12: ward | I12: Female Nephrology Ward in New IPD Building | J12: Bed 30 | K12: bed
A13: Medicine Block | B13: building | C13: New IPD building | D13: Fourth Floor | E13: level | F13: Fourth floor in Medicine Block New IPD building | G13: Female Nephrology Ward | H13: ward | I13: Female Nephrology Ward in New IPD Building | J13: Bed 29 | K13: bed
A14: Medicine Block | B14: building | C14: New IPD building | D14: Fourth Floor | E14: level | F14: Fourth floor in Medicine Block New IPD building | G14: Female Nephrology Ward | H14: ward | I14: Female Nephrology Ward in New IPD Building | J14: Bed 28 | K14: bed
A15: Medicine Block | B15: building | C15: New IPD building | D15: Fourth Floor | E15: level | F15: Fourth floor in Medicine Block New IPD building | G15: Female Nephrology Ward | H15: ward | I15: Female Nephrology Ward in New IPD Building | J15: Bed 27 | K15: bed
A16: Medicine Block | B16: building | C16: New IPD building | D16: Fourth Floor | E16: level | F16: Fourth floor in Medicine Block New IPD building | G16: Female Nephrology Ward | H16: ward | I16: Female Nephrology Ward in New IPD Building | J16: Bed 26 | K16: bed
A17: Medicine Block | B17: building | C17: New IPD building | D17: Fourth Floor | E17: level | F17: Fourth floor in Medicine Block New IPD building | G17: Female Nephrology Ward | H17: ward | I17: Female Nephrology Ward in New IPD Building | J17: Bed 25 | K17: bed
A18: Medicine Block | B18: building | C18: New IPD building | D18: Fourth Floor | E18: level | F18: Fourth floor in Medicine Block New IPD building | G18: Female Medicine Ward unit 4 | H18: ward | I18: Female Medicine Ward (unit 3,4) in New IPD Building | J18: Bed 24 | K18: bed
A19: Medicine Block | B19: building | C19: New IPD building | D19: Fourth Floor | E19: level | F19: Fourth floor in Medicine Block New IPD building | G19: Female Medicine Ward unit 4 | H19: ward | I19: Female Medicine Ward (unit 3,4) in New IPD Building | J19: Bed 23 | K19: bed
A20: Medicine Block | B20: building | C20: New IPD building | D20: Fourth Floor | E20: level | F20: Fourth floor in Medicine Block New IPD building | G20: Female Medicine Ward unit 4 | H20: ward | I20: Female Medicine Ward (unit 3,4) in New IPD Building | J20: Bed 22 | K20: bed
A21: Medicine Block | B21: building | C21: New IPD building | D21: Fourth Floor | E21: level | F21: Fourth floor in Medicine Block New IPD building | G21: Female Medicine Ward unit 4 | H21: ward | I21: Female Medicine Ward (unit 3,4) in New IPD Building | J21: Bed 21 | K21: bed
A22: Medicine Block | B22: building | C22: New IPD building | D22: Fourth Floor | E22: level | F22: Fourth floor in Medicine Block New IPD building | G22: Female Medicine Ward unit 4 | H22: ward | I22: Female Medicine Ward (unit 3,4) in New IPD Building | J22: Bed 20 | K22: bed
A23: Medicine Block | B23: building | C23: New IPD building | D23: Fourth Floor | E23: level | F23: Fourth floor in Medicine Block New IPD building | G23: Female Medicine Ward unit 4 | H23: ward | I23: Female Medicine Ward (unit 3,4) in New IPD Building | J23: Bed 19 | K23: bed
... A41: Medicine Block | B41: building | C41: New IPD building | D41: Fourth Floor | E41: level | F41: Fourth floor in Medicine Block New IPD building | G41: Female Medicine Ward unit 3 | H41: ward | I41: Female Medicine Ward (unit 3,4) in New IPD Building | J41: Bed 1 | K41: bed
A42: Medicine Block | B42: building | C42: New IPD building | D42: Third Floor | E42: level | F42: Third floor in Medicine Block New IPD building | G42: Hemato Oncology Ward | H42: ward | I42: Hemato Oncology Ward in New IPD Building | M42: Medicine
A43: Medicine Block | B43: building | C43: New IPD building | D43: Third Floor | E43: level | F43: Third floor in Medicine Block New IPD building | G43: Hemato Oncology Ward | H43: ward | I43: Hemato Oncology Ward in New IPD Building | J43: Bed 8 | K43: bed
A44: Medicine Block | B44: building | C44: New IPD building | D44: Third Floor | E44: level | F44: Third floor in Medicine Block New IPD building | G44: Hemato Oncology Ward | H44: ward | I44: Hemato Oncology Ward in New IPD Building | J44: Bed 7 | K44: bed
A45: Medicine Block | B45: building | C45: New IPD building | D45: Third Floor | E45: level | F45: Third floor in Medicine Block New IPD building | G45: Hemato Oncology Ward | H45: ward | I45: Hemato Oncology Ward in New IPD Building | J45: Bed 6 | K45: bed
A46: Medicine Block | B46: building | C46: New IPD building | D46: Third Floor | E46: level | F46: Third floor in Medicine Block New IPD building | G46: Hemato Oncology Ward | H46: ward | I46: Hemato Oncology Ward in New IPD Building | J46: Bed 5 | K46: bed
A47: Medicine Block | B47: building | C47: New IPD building | D47: Third Floor | E47: level | F47: Third floor in Medicine Block New IPD building | G47: Hemato Oncology Ward | H47: ward | I47: Hemato Oncology Ward in New IPD Building | J47: Bed 4 | K47: bed
A48: Medicine Block | B48: building | C48: New IPD building | D48: Third Floor | E48: level | F48: Third floor in Medicine Block New IPD building | G48: Hemato Oncology Ward | H48: ward | I48: Hemato Oncology Ward in New IPD Building | J48: Bed 3 | K48: bed
A49: Medicine Block | B49: building | C49: New IPD building | D49: Third Floor | E49: level | F49: Third floor in Medicine Block New IPD building | G49: Hemato Oncology Ward | H49: ward | I49: Hemato Oncology Ward in New IPD Building | J49: Bed 2 | K49: bed
A50: Medicine Block | B50: building | C50: New IPD building | D50: Third Floor | E50: level | F50: Third floor in Medicine Block New IPD building | G50: Hemato Oncology Ward | H50: ward | I50: Hemato Oncology Ward in New IPD Building | J50: Bed 1 | K50: bed
A51: Medicine Block | B51: building | C51: New IPD building | D51: Third Floor | E51: level | F51: Third floor in Medicine Block New IPD building | G51: Female Endocrinology Ward | H51: ward | I51: Third Floor in Medicine Block New IPD Building | M51: Endocrinology
A52: Medicine Block | B52: building | C52: New IPD building | D52: Third Floor | E52: level | F52: Third floor in Medicine Block New IPD building | G52: Female Endocrinology Ward | H52: ward | I52: Third Floor in Medicine Block New IPD Building | J52: Bed 30 | K52: bed
A53: Medicine Block | B53: building | C53: New IPD building | D53: Third Floor | E53: level | F53: Third floor in Medicine Block New IPD building | G53: Female Endocrinology Ward | H53: ward | I53: Third Floor in Medicine Block New IPD Building | J53: Bed 29 | K53: bed
A54: Medicine Block | B54: building | C54: New IPD building | D54: Third Floor | E54: level | F54: Third floor in Medicine Block New IPD building | G54: Female Endocrinology Ward | H54: ward | I54: Third Floor in Medicine Block New IPD Building | J54: Bed 28 | K54: bed
A55: Medicine Block | B55: building | C55: New IPD building | D55: Third Floor | E55: level | F55: Third floor in Medicine Block New IPD building | G55: Female Endocrinology Ward | H55: ward | I55: Third Floor in Medicine Block New IPD Building | J55: Bed 27 | K55: bed
A56: Medicine Block | B56: building | C56: New IPD building | D56: Third Floor | E56: level | F56: Third floor in Medicine Block New IPD building | G56: Female Endocrinology Ward | H56: ward | I56: Third Floor in Medicine Block New IPD Building | J56: Bed 26 | K56: bed
A57: Medicine Block | B57: building | C57: New IPD building | D57: Third Floor | E57: level | F57: Third floor in Medicine Block New IPD building | G57: Female Endocrinology Ward | H57: ward | I57: Third Floor in Medicine Block New IPD Building | J57: Bed 25 | K57: bed
A58: Medicine Block | B58: building | C58: New IPD building | D58: Third Floor | E58: level | F58: Third floor in Medicine Block New IPD building | G58: Female Medicine Ward unit 2 | H58: ward | I58: Third Floor in Medicine Block New IPD Building | M58: Medicine
A59: Medicine Block | B59: building | C59: New IPD building | D59: Third Floor | E59: level | F59: Third floor in Medicine Block New IPD building | G59: Female Medicine Ward unit 2 | H59: ward | I59: Third Floor in Medicine Block New IPD Building | J59: Bed 24 | K59: bed
A60: Medicine Block | B60: building | C60: New IPD building | D60: Third Floor | E60: level | F60: Third floor in Medicine Block New IPD building | G60: Female Medicine Ward unit 2 | H60: ward | I60: Third Floor in Medicine Block New IPD Building | J60: Bed 23 | K60: bed
A61: Medicine Block | B61: building | C61: New IPD building | D61: Third Floor | E61: level | F61: Third floor in Medicine Block New IPD building | G61: Female Medicine Ward unit 2 | H61: ward | I61: Third Floor in Medicine Block New IPD Building | J61: Bed 22 | K61: bed
A62: Medicine Block | B62: building | C62: New IPD building | D62: Third Floor | E62: level | F62: Third floor in Medicine Block New IPD building | G62: Female Medicine Ward unit 2 | H62: ward | I62: Third Floor in Medicine Block New IPD Building | J62: Bed 21 | K62: bed
A63: Medicine Block | B63: building | C63: New IPD building | D63: Third Floor | E63: level | F63: Third floor in Medicine Block New IPD building | G63: Female Medicine Ward unit 2 | H63: ward | I63: Third Floor in Medicine Block New IPD Building | J63: Bed 20 | K63: bed
A64: Medicine Block | B64: building | C64: New IPD building | D64: Third Floor | E64: level | F64: Third floor in Medicine Block New IPD building | G64: Female Medicine Ward unit 2 | H64: ward | I64: Third Floor in Medicine Block New IPD Building | J64: Bed 19 | K64: bed
A65: Medicine Block | B65: building | C65: New IPD building | D65: Third Floor | E65: level | F65: Third floor in Medicine Block New IPD building | G65: Female Medicine Ward unit 2 | H65: ward | I65: Third Floor in Medicine Block New IPD Building | J65: Bed 18 | K65: bed
A66: Medicine Block | B66: building | C66: New IPD building | D66: Third Floor | E66: level | F66: Third floor in Medicine Block New IPD building | G66: Female Medicine Ward unit 2 | H66: ward | I66: Third Floor in Medicine Block New IPD Building | J66: Bed 17 | K66: bed
A67: Medicine Block | B67: building | C67: New IPD building | D67: Third Floor | E67: level | F67: Third floor in Medicine Block New IPD building | G67: Female Medicine Ward unit 2 | H67: ward | I67: Third Floor in Medicine Block New IPD Building | J67: Bed 16 | K67: bed
A68: Medicine Block | B68: building | C68: New IPD building | D68: Third Floor | E68: level | F68: Third floor in Medicine Block New IPD building | G68: Female Medicine Ward unit 1 | H68: ward | I68: Third Floor in Medicine Block New IPD Building | J68: Bed 15 | K68: bed
A69: Medicine Block | B69: building | C69: New IPD building | D69: Third Floor | E69: level | F69: Third floor in Medicine Block New IPD building | G69: Female Medicine Ward unit 1 | H69: ward | I69: Third Floor in Medicine Block New IPD Building | J69: Bed 14 | K69: bed
A70: Medicine Block | B70: building | C70: New IPD building | D70: Third Floor | E70: level | F70: Third floor in Medicine Block New IPD building | G70: Female Medicine Ward unit 1 | H70: ward | I70: Third Floor in Medicine Block New IPD Building | J70: Bed 12 b | K70: bed
... A76: Medicine Block | B76: building | C76: New IPD building | D76: Third Floor | E76: level | F76: Third floor in Medicine Block New IPD building | G76: Female Medicine Ward unit 1 | H76: ward | I76: Third Floor in Medicine Block New IPD Building | J76: Bed 7 | K76: bed
A77: Medicine Block | B77: building | C77: New IPD building | D77: Third Floor | E77: level | F77: Third floor in Medicine Block New IPD building | G77: Female Pulmonary and Critical Care Medicine Ward | H77: ward | I77: Third Floor in Medicine Block New IPD Building | M77: Pulmonary and Critical Care Medicine
A78: Medicine Block | B78: building | C78: New IPD building | D78: Third Floor | E78: level | F78: Third floor in Medicine Block New IPD building | G78: Female Pulmonary and Critical Care Medicine Ward | H78: ward | I78: Third Floor in Medicine Block New IPD Building | J78: Bed 6 | K78: bed
A79: Medicine Block | B79: building | C79: New IPD building | D79: Third Floor | E79: level | F79: Third floor in Medicine Block New IPD building | G79: Female Pulmonary and Critical Care Medicine Ward | H79: ward | I79: Third Floor in Medicine Block New IPD Building | J79: Bed 5 | K79: bed
A80: Medicine Block | B80: building | C80: New IPD building | D80: Third Floor | E80: level | F80: Third floor in Medicine Block New IPD building | G80: Female Pulmonary and Critical Care Medicine Ward | H80: ward | I80: Third Floor in Medicine Block New IPD Building | J80: Bed 4 | K80: bed
A81: Medicine Block | B81: building | C81: New IPD building | D81: Third Floor | E81: level | F81: Third floor in Medicine Block New IPD building | G81: Female Pulmonary and Critical Care Medicine Ward | H81: ward | I81: Third Floor in Medicine Block New IPD Building | J81: Bed 3 | K81: bed
A82: Medicine Block | B82: building | C82: New IPD building | D82: Third Floor | E82: level | F82: Third floor in Medicine Block New IPD building | G82: Female Pulmonary and Critical Care Medicine Ward | H82: ward | I82: Third Floor in Medicine Block New IPD Building | J82: Bed 2 | K82: bed
A83: Medicine Block | B83: building | C83: New IPD building | D83: Third Floor | E83: level | F83: Third floor in Medicine Block New IPD building | G83: Female Pulmonary and Critical Care Medicine Ward | H83: ward | I83: Third Floor in Medicine Block New IPD Building | J83: Bed 1 | K83: bed
A84: Medicine Block | B84: building | C84: New IPD building | D84: Second Floor | E84: level | F84: Second floor in Medicine Block New IPD building | G84: Male Nephrology Ward | H84: ward | I84: Second Floor in Medicine Block New IPD Building | M84: Medicine
A85: Medicine Block | B85: building | C85: New IPD building | D85: Second Floor | E85: level | F85: Second floor in Medicine Block New IPD building | G85: Male Nephrology Ward | H85: ward | I85: Second Floor in Medicine Block New IPD Building | J85: Bed 30 | K85: bed
A86: Medicine Block | B86: building | C86: New IPD building | D86: Second Floor | E86: level | F86: Second floor in Medicine Block New IPD building | G86: Male Nephrology Ward | H86: ward | I86: Second Floor in Medicine Block New IPD Building | J86: Bed 29 | K86: bed
A87: Medicine Block | B87: building | C87: New IPD building | D87: Second Floor | E87: level | F87: Second floor in Medicine Block New IPD building | G87: Male Nephrology Ward | H87: ward | I87: Second Floor in Medicine Block New IPD Building | J87: Bed 28 | K87: bed
A88: Medicine Block | B88: building | C88: New IPD building | D88: Second Floor | E88: level | F88: Second floor in Medicine Block New IPD building | G88: Male Nephrology Ward | H88: ward | I88: Second Floor in Medicine Block New IPD Building | J88: Bed 27 | K88: bed
A89: Medicine Block | B89: building | C89: New IPD building | D89: Second Floor | E89: level | F89: Second floor in Medicine Block New IPD building | G89: Male Nephrology Ward | H89: ward | I89: Second Floor in Medicine Block New IPD Building | J89: Bed 26 | K89: bed
A90: Medicine Block | B90: building | C90: New IPD building | D90: Second Floor | E90: level | F90: Second floor in Medicine Block New IPD building | G90: Male Nephrology Ward | H90: ward | I90: Second Floor in Medicine Block New IPD Building | J90: Bed 25 | K90: bed
A91: Medicine Block | B91: building | C91: New IPD building | D91: Second Floor | E91: level | F91: Second floor in Medicine Block New IPD building | G91: Male Medicine Ward unit 4 | H91: ward | I91: Second Floor in Medicine Block New IPD Building | J91: Bed 24 | K91: bed
A92: Medicine Block | B92: building | C92: New IPD building | D92: Second Floor | E92: level | F92: Second floor in Medicine Block New IPD building | G92: Male Medicine Ward unit 4 | H92: ward | I92: Second Floor in Medicine Block New IPD Building | J92: Bed 23 | K92: bed
A93: Medicine Block | B93: building | C93: New IPD building | D93: Second Floor | E93: level | F93: Second floor in Medicine Block New IPD building | G93: Male Medicine Ward unit 4 | H93: ward | I93: Second Floor in Medicine Block New IPD Building | J93: Bed 22 | K93: bed
A94: Medicine Block | B94: building | C94: New IPD building | D94: Second Floor | E94: level | F94: Second floor in Medicine Block New IPD building | G94: Male Medicine Ward unit 4 | H94: ward | I94: Second Floor in Medicine Block New IPD Building | J94: Bed 21 | K94: bed
A95: Medicine Block | B95: building | C95: New IPD building | D95: Second Floor | E95: level | F95: Second floor in Medicine Block New IPD building | G95: Male Medicine Ward unit 4 | H95: ward | I95: Second Floor in Medicine Block New IPD Building | J95: Bed 20 | K95: bed
A96: Medicine Block | B96: building | C96: New IPD building | D96: Second Floor | E96: level | F96: Second floor in Medicine Block New IPD building | G96: Male Medicine Ward unit 4 | H96: ward | I96: Second Floor in Medicine Block New IPD Building | J96: Bed 19 | K96: bed
... A114: Medicine Block | B114: building | C114: New IPD building | D114: Second Floor | E114: level | F114: Second floor in Medicine Block New IPD building | G114: Male Medicine Ward unit 3 | H114: ward | I114: Second Floor in Medicine Block New IPD Building | J114: Bed 1 | K114: bed
A115: Medicine Block | B115: building | C115: New IPD building | D115: First Floor | E115: level | F115: First floor in Medicine Block New IPD building | G115: Male Endocrinology Ward | H115: ward | I115: Endocrinology in New IPD Building | M115: Endocrinology
A116: Medicine Block | B116: building | C116: New IPD building | D116: First Floor | E116: level | F116: First floor in Medicine Block New IPD building | G116: Male Endocrinology Ward | H116: ward | I116: Endocrinology in New IPD Building | J116: Bed 30 | K116: bed
A117: Medicine Block | B117: building | C117: New IPD building | D117: First Floor | E117: level | F117: First floor in Medicine Block New IPD building | G117: Male Endocrinology Ward | H117: ward | I117: Endocrinology in New IPD Building | J117: Bed 29 | K117: bed
A118: Medicine Block | B118: building | C118: New IPD building | D118: First Floor | E118: level | F118: First floor in Medicine Block New IPD building | G118: Male Endocrinology Ward | H118: ward | I118: Endocrinology in New IPD Building | J118: Bed 28 | K118: bed
A119: Medicine Block | B119: building | C119: New IPD building | D119: First Floor | E119: level | F119: First floor in Medicine Block New IPD building | G119: Male Endocrinology Ward | H119: ward | I119: Endocrinology in New IPD Building | J119: Bed 27 | K119: bed
A120: Medicine Block | B120: building | C120: New IPD building | D120: First Floor | E120: level | F120: First floor in Medicine Block New IPD building | G120: Male Endocrinology Ward | H120: ward | I120: Endocrinology in New IPD Building | J120: Bed 26 | K120: bed
A121: Medicine Block | B121: building | C121: New IPD building | D121: First Floor | E121: level | F121: First floor in Medicine Block New IPD building | G121: Male Endocrinology Ward | H121: ward | I121: Endocrinology in New IPD Building | J121: Bed 25 | K121: bed
A122: Medicine Block | B122: building | C122: New IPD building | D122: First Floor | E122: level | F122: First floor in Medicine Block New IPD building | G122: Male Medicine Ward unit 2 | H122: ward | I122: Male Medicine Ward(unit 1 & 2) in New IPD Building | M122: Medicine
A123: Medicine Block | B123: building | C123: New IPD building | D123: First Floor | E123: level | F123: First floor in Medicine Block New IPD building | G123: Male Medicine Ward unit 2 | H123: ward | I123: Male Medicine Ward(unit 1 & 2) in New IPD Building | J123: Bed 24 | K123: bed
A124: Medicine Block | B124: building | C124: New IPD building | D124: First Floor | E124: level | F124: First floor in Medicine Block New IPD building | G124: Male Medicine Ward unit 2 | H124: ward | I124: Male Medicine Ward(unit 1 & 2) in New IPD Building | J124: Bed 23 | K124: bed
A125: Medicine Block | B125: building | C125: New IPD building | D125: First Floor | E125: level | F125: First floor in Medicine Block New IPD building | G125: Male Medicine Ward unit 2 | H125: ward | I125: Male Medicine Ward(unit 1 & 2) in New IPD Building | J125: Bed 22 | K125: bed
A126: Medicine Block | B126: building | C126: New IPD building | D126: First Floor | E126: level | F126: First floor in Medicine Block New IPD building | G126: Male Medicine Ward unit 2 | H126: ward | I126: Male Medicine Ward(unit 1 & 2) in New IPD Building | J126: Bed 21 | K126: bed
A127: Medicine Block | B127: building | C127: New IPD building | D127: First Floor | E127: level | F127: First floor in Medicine Block New IPD building | G127: Male Medicine Ward unit 2 | H127: ward | I127: Male Medicine Ward(unit 1 & 2) in New IPD Building | J127: Bed 20 | K127: bed
A128: Medicine Block | B128: building | C128: New IPD building | D128: First Floor | E128: level | F128: First floor in Medicine Block New IPD building | G128: Male Medicine Ward unit 2 | H128: ward | I128: Male Medicine Ward(unit 1 & 2) in New IPD Building | J128: Bed 19 | K128: bed
A129: Medicine Block | B129: building | C129: New IPD building | D129: First Floor | E129: level | F129: First floor in Medicine Block New IPD building | G129: Male Medicine Ward unit 2 | H129: ward | I129: Male Medicine Ward(unit 1 & 2) in New IPD Building | J129: Bed 18 | K129: bed
A130: Medicine Block | B130: building | C130: New IPD building | D130: First Floor | E130: level | F130: First floor in Medicine Block New IPD building | G130: Male Medicine Ward unit 2 | H130: ward | I130: Male Medicine Ward(unit 1 & 2) in New IPD Building | J130: Bed 17 | K130: bed
A131: Medicine Block | B131: building | C131: New IPD building | D131: First Floor | E131: level | F131: First floor in Medicine Block New IPD building | G131: Male Medicine Ward unit 2 | H131: ward | I131: Male Medicine Ward(unit 1 & 2) in New IPD Building | J131: Bed 16 | K131: bed
A132: Medicine Block | B132: building | C132: New IPD building | D132: First Floor | E132: level | F132: First floor in Medicine Block New IPD building | G132: Male Medicine Ward unit 1 | H132: ward | I132: Male Medicine Ward(unit 1 & 2) in New IPD Building | J132: Bed 15 | K132: bed
A133: Medicine Block | B133: building | C133: New IPD building | D133: First Floor | E133: level | F133: First floor in Medicine Block New IPD building | G133: Male Medicine Ward unit 1 | H133: ward | I133: Male Medicine Ward(unit 1 & 2) in New IPD Building | J133: Bed 14 | K133: bed
A134: Medicine Block | B134: building | C134: New IPD building | D134: First Floor | E134: level | F134: First floor in Medicine Block New IPD building | G134: Male Medicine Ward unit 1 | H134: ward | I134: Male Medicine Ward(unit 1 & 2) in New IPD Building | J134: Bed 12 b | K134: bed
... A140: Medicine Block | B140: building | C140: New IPD building | D140: First Floor | E140: level | F140: First floor in Medicine Block New IPD building | G140: Male Medicine Ward unit 1 | H140: ward | I140: Male Medicine Ward(unit 1 & 2) in New IPD Building | J140: Bed 7 | K140: bed
A141: Medicine Block | B141: building | C141: New IPD building | D141: First Floor | E141: level | F141: First floor in Medicine Block New IPD building | G141: Male Medicine Ward(unit 1 & 2) | H141: ward | I141: Male Medicine Ward(unit 1 & 2) in New IPD Building | M141: Pulmonary and Critical Care Medicine
A142: Medicine Block | B142: building | C142: New IPD building | D142: First Floor | E142: level | F142: First floor in Medicine Block New IPD building | G142: Male Medicine Ward(unit 1 & 2) | H142: ward | I142: Male Medicine Ward(unit 1 & 2) in New IPD Building | J142: Bed 6 | K142: bed
A143: Medicine Block | B143: building | C143: New IPD building | D143: First Floor | E143: level | F143: First floor in Medicine Block New IPD building | G143: Male Medicine Ward(unit 1 & 2) | H143: ward | I143: Male Medicine Ward(unit 1 & 2) in New IPD Building | J143: Bed 5 | K143: bed
A144: Medicine Block | B144: building | C144: New IPD building | D144: First Floor | E144: level | F144: First floor in Medicine Block New IPD building | G144: Male Medicine Ward(unit 1 & 2) | H144: ward | I144: Male Medicine Ward(unit 1 & 2) in New IPD Building | J144: Bed 4 | K144: bed
...

Sheet specimen_definition
A1: title | B1: slug_value | C1: description | D1: derived_from_uri | E1: type_collected_system | F1: type_collected_code | G1: type_collected_display | H1: collection_system | I1: collection_code | J1: collection_display | K1: is_derived | L1: preference | M1: single_use | N1: requirement | O1: retention_value | P1: retention_unit_system | Q1: retention_unit_code | R1: retention_unit_display | S1: container_description | T1: container_capacity_value | U1: container_capacity_unit_system | V1: container_capacity_unit_code | W1: container_capacity_unit_display | X1: container_minimum_volume_quantity_value | Y1: container_minimum_volume_quantity_unit_system | Z1: container_minimum_volume_quantity_unit_code | AA1: container_minimum_volume_quantity_unit_display | AB1: container_minimum_volume_string | AC1: container_cap_system | AD1: container_cap_code | AE1: container_cap_display | AF1: container_preparation
A2: Whole Blood | B2: whole-blood | C2: Blood specimen containing all cellular and plasma components collected directly from the patient. | E2: http://terminology.hl7.org/CodeSystem/v2-0487 | F2: BLD | G2: Blood | H2: http://snomed.info/sct | I2: 28520004 | J2: Venipuncture for blood test | K2: FALSE | L2: preferred | M2: TRUE | T2: 5 | U2: http://unitsofmeasure.org | V2: mL | W2: milliliter | X2: 2 | Y2: http://unitsofmeasure.org | Z2: mL | AA2: milliliter | AC2: http://terminology.hl7.org/CodeSystem/container-cap | AD2: lavender | AE2: lavender cap
A3: Serum | B3: serum | C3: Liquid portion of blood obtained after coagulation, with clotting factors removed. | E3: http://terminology.hl7.org/CodeSystem/v2-0487 | F3: SER | G3: Serum | H3: http://snomed.info/sct | I3: 22778000 | J3: Venipuncture | K3: FALSE | L3: preferred | M3: TRUE | T3: 5 | U3: http://unitsofmeasure.org | V3: mL | W3: milliliter | X3: 2 | Y3: http://unitsofmeasure.org | Z3: mL | AA3: milliliter | AC3: http://terminology.hl7.org/CodeSystem/container-cap | AD3: red | AE3: red cap
A4: Plasma | B4: plasma | C4: Liquid component of anticoagulated blood containing clotting factors and dissolved proteins | E4: http://terminology.hl7.org/CodeSystem/v2-0487 | F4: PLAS | G4: Plasma | H4: http://snomed.info/sct | I4: 22778000 | J4: Venipuncture | K4: FALSE | L4: preferred | M4: TRUE | T4: 5 | U4: http://unitsofmeasure.org | V4: mL | W4: milliliter | X4: 2 | Y4: http://unitsofmeasure.org | Z4: mL | AA4: milliliter | AC4: http://terminology.hl7.org/CodeSystem/container-cap | AD4: lavender | AE4: lavender cap
A5: Blood Venous | B5: venous-blood | C5: Blood specimen collected from a vein via venipuncture for laboratory analysis. | E5: http://terminology.hl7.org/CodeSystem/v2-0487 | F5: BLDV | G5: Blood venous | H5: http://snomed.info/sct | I5: 28520004 | J5: Venipuncture for blood test | K5: FALSE | L5: preferred | M5: TRUE | T5: 5 | U5: http://unitsofmeasure.org | V5: mL | W5: milliliter | X5: 2 | Y5: http://unitsofmeasure.org | Z5: mL | AA5: milliliter | AC5: http://terminology.hl7.org/CodeSystem/container-cap | AD5: red | AE5: red cap
A6: Sputum | B6: sputum | C6: Respiratory specimen consisting of mucus expectorated from the lower airways for laboratory analysis. | E6: http://terminology.hl7.org/CodeSystem/v2-0487 | F6: SPT | G6: Sputum | H6: http://snomed.info/sct | I6: 386089008 | J6: Collection of coughed sputum | K6: FALSE | L6: preferred | M6: TRUE
A7: Urine | B7: urine | C7: Urine sample collected from a patient for biochemical, microscopic and microbiological examination | E7: http://terminology.hl7.org/CodeSystem/v2-0487 | F7: UR | G7: Urine | H7: http://snomed.info/sct | I7: 73416001 | J7: Urine specimen collection, clean catch, mid stream urine | K7: FALSE | L7: preferred | M7: TRUE
A8: Oral Swab | B8: oral-swab | C8: Specimen collected using a sterile swab from a oral cavity for microbiological or molecular testing. | E8: http://terminology.hl7.org/CodeSystem/v2-0487 | F8: ORH | G8: Other | H8: http://snomed.info/sct | I8: 418622002 | J8: Taking oral swab | K8: FALSE | L8: preferred | M8: TRUE
A9: Stool | B9: stool | C9: Fecal specimen collected for microbiological, parasitological, or biochemical testing | E9: http://terminology.hl7.org/CodeSystem/v2-0487 | F9: STL | G9: Stool | H9: http://snomed.info/sct | I9: 225105004 | J9: Collection of stool specimen | K9: FALSE | L9: preferred | M9: TRUE
A10: Ascitic Fluid | B10: ascitic-fluid | C10: Peritoneal fluid collected from the abdominal cavity for diagnostic laboratory evaluation. | E10: http://terminology.hl7.org/CodeSystem/v2-0487 | F10: FGA | G10: Fluid, Abdomen | H10: http://snomed.info/sct | I10: 89305009 | J10: Abdominal paracentesis | K10: FALSE | L10: preferred | M10: TRUE
A11: Synovial Fluid | B11: synovial-fluid | C11: Joint fluid aspirated from a synovial cavity for analysis of joint disorders | E11: http://terminology.hl7.org/CodeSystem/v2-0487 | F11: SNV | G11: Fluid, synovial (Joint fluid) | H11: http://snomed.info/sct | I11: 90131007 | J11: Arthrocentesis | K11: FALSE | L11: preferred | M11: TRUE
A12: Pleural Fluid | B12: pleural-fluid | C12: Fluid collected from the pleural cavity for laboratory analysis of cells, proteins, microorganisms and biochemical markers to evaluate pleural diseases | E12: http://terminology.hl7.org/CodeSystem/v2-0487 | F12: PLR | G12: Pleural fluid (thoracentesis fluid) | H12: http://snomed.info/sct | I12: 91602002 | J12: Thoracentesis | K12: FALSE | L12: preferred | M12: TRUE
A13: Nasal Swab | B13: nasal-swab | C13: Specimen collected from the nasal cavity using a sterile swab for respiratory pathogen testing | E13: http://terminology.hl7.org/CodeSystem/v2-0487 | F13: NSECR | G13: Secretion, Nasal | H13: http://snomed.info/sct | I13: 312882009 | J13: Taking nasal swab | K13: FALSE | L13: preferred | M13: TRUE
A14: Throat Swab | B14: throat-swab | C14: Specimen collected from the oropharynx using a sterile swab to detect bacterial or viral infections of the throat and upper respiratory tract | E14: http://terminology.hl7.org/CodeSystem/v2-0487 | F14: ORH | G14: Other | H14: http://snomed.info/sct | I14: 312880001 | J14: Taking throat swab | K14: FALSE | L14: preferred | M14: TRUE
A15: Bone marrow | B15: bone-marrow | C15: Bone marrow is a soft, spongy tissue found inside bones, collected as a specimen to evaluate blood cell production and diagnose hematological conditions. | E15: http://terminology.hl7.org/CodeSystem/v2-0487 | F15: MAR | G15: Marrow | H15: http://snomed.info/sct | I15: 49401003 | J15: Bone marrow aspiration procedure | K15: FALSE | L15: preferred | M15: TRUE
A16: Pus | B16: pus-test | C16: Pus is a thick, yellowish or greenish fluid collected from infected tissue, used as a specimen to identify causative organisms and diagnose infections. | E16: http://terminology.hl7.org/CodeSystem/v2-0487 | F16: PUS | G16: Pus | H16: http://snomed.info/sct | I16: 14766002 | J16: Aspiration | K16: FALSE | L16: preferred | M16: TRUE
A17: Skin | B17: skin-test | C17: Skin is the outer protective layer of the body, collected as a specimen (scraping/biopsy) to diagnose infections, dermatological conditions, or other abnormalities. | E17: http://terminology.hl7.org/CodeSystem/v2-0487 | F17: SKN | G17: Skin | H17: http://snomed.info/sct | I17: 386148007 | J17: Slit skin stain method | K17: FALSE | L17: preferred | M17: TRUE
... A48: Pancreatic Fluid | B48: pancreatic-fluid | C48: Secretion from the pancreas, analyzed to assess pancreatic function and detect inflammation or malignancy. | E48: http://terminology.hl7.org/CodeSystem/v2-0487 | F48: PAFL | G48: Pancreatic fluid | H48: http://snomed.info/sct | I48: 788641000 | J48: Fine needle aspiration of lesion of pancreas using endoscopic ultrasonography guidance | K48: FALSE | L48: preferred | M48: TRUE

Sheet Imported_observation
A1: Title | B1: slug_value | C1: description | D1: category | E1: status | F1: code_system | G1: code_value | H1: code_display | I1: permitted_data_type | J1: body_site_system | K1: body_site_code | L1: body_site_display | M1: method_system | N1: method_code | O1: method_display | P1: permitted_unit_system | Q1: permitted_unit_code | R1: permitted_unit_display | S1: derived_from_uri | T1: age_min | U1: age_max | V1: age_op | W1: gender | X1: range_display | Y1: range_min | Z1: range_max
A2: Random Blood Sugar (RBS) | B2: random-blood-sugar-rbs | C2: Measures the level of glucose in the blood | D2: laboratory | E2: active | F2: http://loinc.org | G2: 74774-1 | H2: Glucose [Mass/volume] in Serum, Plasma or Blood | I2: integer | M2: http://snomed.info/sct | N2: 36048009 | O2: Glucose measurement | P2: http://unitsofmeasure.org | Q2: mg/dL | R2: milligram per deciliter | X2: low | Z2: 0
A3: Random Blood Sugar (RBS) | B3: random-blood-sugar-rbs | C3: Measures the level of glucose in the blood | D3: laboratory | E3: active | F3: http://loinc.org | G3: 74774-1 | H3: Glucose [Mass/volume] in Serum, Plasma or Blood | I3: integer | M3: http://snomed.info/sct | N3: 36048009 | O3: Glucose measurement | P3: http://unitsofmeasure.org | Q3: mg/dL | R3: milligram per deciliter | X3: normal | Y3: 0 | Z3: 200
A4: Random Blood Sugar (RBS) | B4: random-blood-sugar-rbs | C4: Measures the level of glucose in the blood | D4: laboratory | E4: active | F4: http://loinc.org | G4: 74774-1 | H4: Glucose [Mass/volume] in Serum, Plasma or Blood | I4: integer | M4: http://snomed.info/sct | N4: 36048009 | O4: Glucose measurement | P4: http://unitsofmeasure.org | Q4: mg/dL | R4: milligram per deciliter | X4: high | Y4: 200
A5: Fasting Blood Sugar (FBS) | B5: fasting-blood-sugar-fbs | C5: Measures the level of glucose in the blood in the fasting state | D5: laboratory | E5: active | F5: http://loinc.org | G5: 1557-8 | H5: Fasting glucose [Mass/volume] in Venous blood | I5: integer | M5: http://snomed.info/sct | N5: 36048009 | O5: Glucose measurement | P5: http://unitsofmeasure.org | Q5: mg/dL | R5: milligram per deciliter | X5: low | Z5: 70
A6: Fasting Blood Sugar (FBS) | B6: fasting-blood-sugar-fbs | C6: Measures the level of glucose in the blood in the fasting state | D6: laboratory | E6: active | F6: http://loinc.org | G6: 1557-8 | H6: Fasting glucose [Mass/volume] in Venous blood | I6: integer | M6: http://snomed.info/sct | N6: 36048009 | O6: Glucose measurement | P6: http://unitsofmeasure.org | Q6: mg/dL | R6: milligram per deciliter | X6: normal | Y6: 70 | Z6: 110
A7: Fasting Blood Sugar (FBS) | B7: fasting-blood-sugar-fbs | C7: Measures the level of glucose in the blood in the fasting state | D7: laboratory | E7: active | F7: http://loinc.org | G7: 1557-8 | H7: Fasting glucose [Mass/volume] in Venous blood | I7: integer | M7: http://snomed.info/sct | N7: 36048009 | O7: Glucose measurement | P7: http://unitsofmeasure.org | Q7: mg/dL | R7: milligram per deciliter | X7: high | Y7: 110
A8: Post Prandial Blood Sugar (PPBS) | B8: post-prandial-blood-sugar | C8: Measures the level of glucose in the blood after a meal, used to assess how the body processes sugar and to monitor diabetes control | D8: laboratory | E8: active | F8: http://loinc.org | G8: 87422-2 | H8: Glucose [Mass/volume] in Blood – Post meal | I8: integer | M8: http://snomed.info/sct | N8: 302788006 | O8: Post-prandial blood glucose measurement | P8: http://unitsofmeasure.org | Q8: mg/dL | R8: milligram per deciliter | X8: low | Z8: 0
A9: Post Prandial Blood Sugar (PPBS) | B9: post-prandial-blood-sugar | C9: Measures the level of glucose in the blood after a meal, used to assess how the body processes sugar and to monitor diabetes control | D9: laboratory | E9: active | F9: http://loinc.org | G9: 87422-2 | H9: Glucose [Mass/volume] in Blood – Post meal | I9: integer | M9: http://snomed.info/sct | N9: 302788006 | O9: Post-prandial blood glucose measurement | P9: http://unitsofmeasure.org | Q9: mg/dL | R9: milligram per deciliter | X9: normal | Y9: 0 | Z9: 200
A10: Post Prandial Blood Sugar (PPBS) | B10: post-prandial-blood-sugar | C10: Measures the level of glucose in the blood after a meal, used to assess how the body processes sugar and to monitor diabetes control | D10: laboratory | E10: active | F10: http://loinc.org | G10: 87422-2 | H10: Glucose [Mass/volume] in Blood – Post meal | I10: integer | M10: http://snomed.info/sct | N10: 302788006 | O10: Post-prandial blood glucose measurement | P10: http://unitsofmeasure.org | Q10: mg/dL | R10: milligram per deciliter | X10: high | Y10: 200
A11: Glucose Tolerance test (GTT) | B11: glucose-tolerance-test-gt | C11: Ordered to assess how the body processes glucose and to help diagnose diabetes or gestational diabetes | D11: laboratory | E11: active | F11: http://loinc.org | G11: 21004-7 | H11: Glucose tolerance [Interpretation] in Serum or Plasma | I11: integer | M11: http://snomed.info/sct | N11: 113076002 | O11: Glucose tolerance test (procedure) | P11: http://unitsofmeasure.org | Q11: mg/dL | R11: milligram per deciliter | X11: low | Z11: 0
A12: Glucose Tolerance test (GTT) | B12: glucose-tolerance-test-gt | C12: Ordered to assess how the body processes glucose and to help diagnose diabetes or gestational diabetes | D12: laboratory | E12: active | F12: http://loinc.org | G12: 21004-7 | H12: Glucose tolerance [Interpretation] in Serum or Plasma | I12: integer | M12: http://snomed.info/sct | N12: 113076002 | O12: Glucose tolerance test (procedure) | P12: http://unitsofmeasure.org | Q12: mg/dL | R12: milligram per deciliter | X12: normal | Y12: 0 | Z12: 100
A13: Glucose Tolerance test (GTT) | B13: glucose-tolerance-test-gt | C13: Ordered to assess how the body processes glucose and to help diagnose diabetes or gestational diabetes | D13: laboratory | E13: active | F13: http://loinc.org | G13: 21004-7 | H13: Glucose tolerance [Interpretation] in Serum or Plasma | I13: integer | M13: http://snomed.info/sct | N13: 113076002 | O13: Glucose tolerance test (procedure) | P13: http://unitsofmeasure.org | Q13: mg/dL | R13: milligram per deciliter | X13: high | Y13: 100
A14: Glucose Tolerance test (GTT)-2hrs | B14: glucose-tolerance-test-th | C14: Ordered to assess how the body processes glucose and to help diagnose diabetes or gestational diabetes | D14: laboratory | E14: active | F14: http://loinc.org | G14: 21004-7 | H14: Glucose tolerance [Interpretation] in Serum or Plasma | I14: integer | M14: http://snomed.info/sct | N14: 113076002 | O14: Glucose tolerance test (procedure) | P14: http://unitsofmeasure.org | Q14: mg/dL | R14: milligram per deciliter | X14: low | Z14: 0
A15: Glucose Tolerance test (GTT)-2hrs | B15: glucose-tolerance-test-th | C15: Ordered to assess how the body processes glucose and to help diagnose diabetes or gestational diabetes | D15: laboratory | E15: active | F15: http://loinc.org | G15: 21004-7 | H15: Glucose tolerance [Interpretation] in Serum or Plasma | I15: integer | M15: http://snomed.info/sct | N15: 113076002 | O15: Glucose tolerance test (procedure) | P15: http://unitsofmeasure.org | Q15: mg/dL | R15: milligram per deciliter | X15: normal | Y15: 0 | Z15: 140
A16: Glucose Tolerance test (GTT)-2hrs | B16: glucose-tolerance-test-th | C16: Ordered to assess how the body processes glucose and to help diagnose diabetes or gestational diabetes | D16: laboratory | E16: active | F16: http://loinc.org | G16: 21004-7 | H16: Glucose tolerance [Interpretation] in Serum or Plasma | I16: integer | M16: http://snomed.info/sct | N16: 113076002 | O16: Glucose tolerance test (procedure) | P16: http://unitsofmeasure.org | Q16: mg/dL | R16: milligram per deciliter | X16: high | Y16: 140
A17: Serum Uric acid | B17: serum-uric-acid | C17: Measures uric acid levels in the blood, reflecting purine metabolism | D17: laboratory | E17: active | F17: http://loinc.org | G17: 3084-1 | H17: Urate [Measurement] in Serum or Plasma | I17: decimal | M17: http://snomed.info/sct | N17: 275740009 | O17: Serum Uric acid measurement | P17: http://unitsofmeasure.org | Q17: mg/dL | R17: milligram per deciliter | X17: low | Z17: 2.5
A18: Serum Uric acid | B18: serum-uric-acid | C18: Measures uric acid levels in the blood, reflecting purine metabolism | D18: laboratory | E18: active | F18: http://loinc.org | G18: 3084-1 | H18: Urate [Measurement] in Serum or Plasma | I18: decimal | M18: http://snomed.info/sct | N18: 275740009 | O18: Serum Uric acid measurement | P18: http://unitsofmeasure.org | Q18: mg/dL | R18: milligram per deciliter | X18: normal | Y18: 2.5 | Z18: 7.5
A19: Serum Uric acid | B19: serum-uric-acid | C19: Measures uric acid levels in the blood, reflecting purine metabolism | D19: laboratory | E19: active | F19: http://loinc.org | G19: 3084-1 | H19: Urate [Measurement] in Serum or Plasma | I19: decimal | M19: http://snomed.info/sct | N19: 275740009 | O19: Serum Uric acid measurement | P19: http://unitsofmeasure.org | Q19: mg/dL | R19: milligram per deciliter | X19: high | Y19: 7.5
A20: Serum Calcium | B20: serum-calcium | C20: Measures total calcium in the blood, essential for bone health, nerve signals, and muscle function | D20: laboratory | E20: active | F20: http://loinc.org | G20: 17861-6 | H20: Calcium [Mass/volume] in Serum or Plasma | I20: decimal | M20: http://snomed.info/sct | N20: 271240001 | O20: Serum Calcium measurement | P20: http://unitsofmeasure.org | Q20: mg/dL | R20: milligram per deciliter | X20: low | Z20: 8.4
A21: Serum Calcium | B21: serum-calcium | C21: Measures total calcium in the blood, essential for bone health, nerve signals, and muscle function | D21: laboratory | E21: active | F21: http://loinc.org | G21: 17861-6 | H21: Calcium [Mass/volume] in Serum or Plasma | I21: decimal | M21: http://snomed.info/sct | N21: 271240001 | O21: Serum Calcium measurement | P21: http://unitsofmeasure.org | Q21: mg/dL | R21: milligram per deciliter | X21: normal | Y21: 8.4 | Z21: 10.2
A22: Serum Calcium | B22: serum-calcium | C22: Measures total calcium in the blood, essential for bone health, nerve signals, and muscle function | D22: laboratory | E22: active | F22: http://loinc.org | G22: 17861-6 | H22: Calcium [Mass/volume] in Serum or Plasma | I22: decimal | M22: http://snomed.info/sct | N22: 271240001 | O22: Serum Calcium measurement | P22: http://unitsofmeasure.org | Q22: mg/dL | R22: milligram per deciliter | X22: high | Y22: 10.2
A23: Serum Amylase | B23: serum-amylase | C23: Measures the level of amylase enzyme in the blood, mainly from the pancreas and salivary glands. | D23: laboratory | E23: active | F23: http://loinc.org | G23: 1798-8 | H23: Amylase [Enzymatic activity/volume] in Serum or Plasma | I23: integer | M23: http://snomed.info/sct | N23: 89659001 | O23: Amylase measurement, serum | P23: http://unitsofmeasure.org | Q23: U/L | R23: enzyme unit per liter | X23: low | Z23: 30
A24: Serum Amylase | B24: serum-amylase | C24: Measures the level of amylase enzyme in the blood, mainly from the pancreas and salivary glands. | D24: laboratory | E24: active | F24: http://loinc.org | G24: 1798-8 | H24: Amylase [Enzymatic activity/volume] in Serum or Plasma | I24: integer | M24: http://snomed.info/sct | N24: 89659001 | O24: Amylase measurement, serum | P24: http://unitsofmeasure.org | Q24: U/L | R24: enzyme unit per liter | X24: normal | Y24: 30 | Z24: 110
A25: Serum Amylase | B25: serum-amylase | C25: Measures the level of amylase enzyme in the blood, mainly from the pancreas and salivary glands. | D25: laboratory | E25: active | F25: http://loinc.org | G25: 1798-8 | H25: Amylase [Enzymatic activity/volume] in Serum or Plasma | I25: integer | M25: http://snomed.info/sct | N25: 89659001 | O25: Amylase measurement, serum | P25: http://unitsofmeasure.org | Q25: U/L | R25: enzyme unit per liter | X25: high | Y25: 110
A26: Serum Lipase | B26: serum-lipase | C26: Measures the level of lipase enzyme in the serum, which is primarily produced by the pancreas to break down fats. | D26: laboratory | E26: active | F26: http://loinc.org | G26: 3040-3 | H26: Lipase [Enzymatic activity/volume] in Serum or Plasma | I26: integer | M26: http://snomed.info/sct | N26: 271232007 | O26: Serum Lipase Measurement | P26: http://unitsofmeasure.org | Q26: U/L | R26: enzyme unit per liter | X26: low | Z26: 10
A27: Serum Lipase | B27: serum-lipase | C27: Measures the level of lipase enzyme in the serum, which is primarily produced by the pancreas to break down fats. | D27: laboratory | E27: active | F27: http://loinc.org | G27: 3040-3 | H27: Lipase [Enzymatic activity/volume] in Serum or Plasma | I27: integer | M27: http://snomed.info/sct | N27: 271232007 | O27: Serum Lipase Measurement | P27: http://unitsofmeasure.org | Q27: U/L | R27: enzyme unit per liter | X27: normal | Y27: 10 | Z27: 140
A28: Serum Lipase | B28: serum-lipase | C28: Measures the level of lipase enzyme in the serum, which is primarily produced by the pancreas to break down fats. | D28: laboratory | E28: active | F28: http://loinc.org | G28: 3040-3 | H28: Lipase [Enzymatic activity/volume] in Serum or Plasma | I28: integer | M28: http://snomed.info/sct | N28: 271232007 | O28: Serum Lipase Measurement | P28: http://unitsofmeasure.org | Q28: U/L | R28: enzyme unit per liter | X28: high | Y28: 140
A29: Serum LDH | B29: serum-ldh | C29: Measures LDH enzyme levels, which increase with tissue damage in many organs. | D29: laboratory | E29: active | F29: http://loinc.org | G29: 14804-9 | H29: Lactate dehydrogenase [Enzymatic activity/volume] in Serum or Plasma by Lactate to pyruvate reaction | I29: integer | M29: http://snomed.info/sct | N29: 313854008 | O29: Serum Lactate dehydrogenase measurement | P29: http://unitsofmeasure.org | Q29: U/L | R29: enzyme unit per liter | X29: low | Z29: 140
A30: Serum LDH | B30: serum-ldh | C30: Measures LDH enzyme levels, which increase with tissue damage in many organs. | D30: laboratory | E30: active | F30: http://loinc.org | G30: 14804-9 | H30: Lactate dehydrogenase [Enzymatic activity/volume] in Serum or Plasma by Lactate to pyruvate reaction | I30: integer | M30: http://snomed.info/sct | N30: 313854008 | O30: Serum Lactate dehydrogenase measurement | P30: http://unitsofmeasure.org | Q30: U/L | R30: enzyme unit per liter | X30: normal | Y30: 140 | Z30: 280
A31: Serum LDH | B31: serum-ldh | C31: Measures LDH enzyme levels, which increase with tissue damage in many organs. | D31: laboratory | E31: active | F31: http://loinc.org | G31: 14804-9 | H31: Lactate dehydrogenase [Enzymatic activity/volume] in Serum or Plasma by Lactate to pyruvate reaction | I31: integer | M31: http://snomed.info/sct | N31: 313854008 | O31: Serum Lactate dehydrogenase measurement | P31: http://unitsofmeasure.org | Q31: U/L | R31: enzyme unit per liter | X31: high | Y31: 280
A32: Serum Phosphorus | B32: serum-phosphorus | C32: Measures the level of phosphorus (phosphate) in the serum, which plays a key role in bone formation, energy production, and maintaining acid–base balance in the body. | D32: laboratory | E32: active | F32: http://loinc.org | G32: 2777-1 | H32: Phosphate [Mass/volume] in Serum or Plasma | I32: decimal | M32: http://snomed.info/sct | N32: 271241002 | O32: Serum inorganic phosphate measurement (procedure) | P32: http://unitsofmeasure.org | Q32: mg/dL | R32: milligram per deciliter | X32: low | Z32: 2.5
A33: Serum Phosphorus | B33: serum-phosphorus | C33: Measures the level of phosphorus (phosphate) in the serum, which plays a key role in bone formation, energy production, and maintaining acid–base balance in the body. | D33: laboratory | E33: active | F33: http://loinc.org | G33: 2777-1 | H33: Phosphate [Mass/volume] in Serum or Plasma | I33: decimal | M33: http://snomed.info/sct | N33: 271241002 | O33: Serum inorganic phosphate measurement (procedure) | P33: http://unitsofmeasure.org | Q33: mg/dL | R33: milligram per deciliter | X33: normal | Y33: 2.5 | Z33: 4.5
A34: Serum Phosphorus | B34: serum-phosphorus | C34: Measures the level of phosphorus (phosphate) in the serum, which plays a key role in bone formation, energy production, and maintaining acid–base balance in the body. | D34: laboratory | E34: active | F34: http://loinc.org | G34: 2777-1 | H34: Phosphate [Mass/volume] in Serum or Plasma | I34: decimal | M34: http://snomed.info/sct | N34: 271241002 | O34: Serum inorganic phosphate measurement (procedure) | P34: http://unitsofmeasure.org | Q34: mg/dL | R34: milligram per deciliter | X34: high | Y34: 4.5
A35: Serum Bicarbonate | B35: serum-bicarbonate | C35: Measures serum bicarbonate level for acid–base balance. | D35: laboratory | E35: active | F35: http://loinc.org | G35: 1963-8 | H35: Bicarbonate [Moles/volume] in Serum or Plasma | I35: integer | M35: http://snomed.info/sct | N35: 271239003 | O35: Serum bicarbonate measurement (procedure) | P35: http://unitsofmeasure.org | Q35: mmol/L | R35: millimole per liter | X35: low | Z35: 20
A36: Serum Bicarbonate | B36: serum-bicarbonate | C36: Measures serum bicarbonate level for acid–base balance. | D36: laboratory | E36: active | F36: http://loinc.org | G36: 1963-8 | H36: Bicarbonate [Moles/volume] in Serum or Plasma | I36: integer | M36: http://snomed.info/sct | N36: 271239003 | O36: Serum bicarbonate measurement (procedure) | P36: http://unitsofmeasure.org | Q36: mmol/L | R36: millimole per liter | X36: normal | Y36: 20 | Z36: 30
A37: Serum Bicarbonate | B37: serum-bicarbonate | C37: Measures serum bicarbonate level for acid–base balance. | D37: laboratory | E37: active | F37: http://loinc.org | G37: 1963-8 | H37: Bicarbonate [Moles/volume] in Serum or Plasma | I37: integer | M37: http://snomed.info/sct | N37: 271239003 | O37: Serum bicarbonate measurement (procedure) | P37: http://unitsofmeasure.org | Q37: mmol/L | R37: millimole per liter | X37: high | Y37: 30
A38: Blood Urea | B38: blood-urea | C38: Helps detect metabolic and kidney disorders. | D38: laboratory | E38: active | F38: http://loinc.org | G38: 20977-5 | H38: Urea [Mass/volume] in Blood | I38: integer | M38: http://snomed.info/sct | N38: 269858003 | O38: Biochemical evaluation of blood urea/renal function | P38: http://unitsofmeasure.org | Q38: mg/dL | R38: milligram per deciliter | X38: low | Z38: 15
A39: Blood Urea | B39: blood-urea | C39: Helps detect metabolic and kidney disorders. | D39: laboratory | E39: active | F39: http://loinc.org | G39: 20977-5 | H39: Urea [Mass/volume] in Blood | I39: integer | M39: http://snomed.info/sct | N39: 269858003 | O39: Biochemical evaluation of blood urea/renal function | P39: http://unitsofmeasure.org | Q39: mg/dL | R39: milligram per deciliter | X39: normal | Y39: 15 | Z39: 45
A40: Blood Urea | B40: blood-urea | C40: Helps detect metabolic and kidney disorders. | D40: laboratory | E40: active | F40: http://loinc.org | G40: 20977-5 | H40: Urea [Mass/volume] in Blood | I40: integer | M40: http://snomed.info/sct | N40: 269858003 | O40: Biochemical evaluation of blood urea/renal function | P40: http://unitsofmeasure.org | Q40: mg/dL | R40: milligram per deciliter | X40: high | Y40: 45
A41: Serum Creatinine | B41: serum-creatinine | C41: Measures the level of creatinine in the blood, an indicator of kidney function. | D41: laboratory | E41: active | F41: http://loinc.org | G41: 2160-0 | H41: Creatinine [Mass/volume] in Serum or Plasma | I41: decimal | M41: http://snomed.info/sct | N41: 113075003 | O41: Serum Creatinine measurement | P41: http://unitsofmeasure.org | Q41: mg/dL | R41: milligram per deciliter | W41: male | X41: low | Z41: 0.6
A42: Serum Creatinine | B42: serum-creatinine | C42: Measures the level of creatinine in the blood, an indicator of kidney function. | D42: laboratory | E42: active | F42: http://loinc.org | G42: 2160-0 | H42: Creatinine [Mass/volume] in Serum or Plasma | I42: decimal | M42: http://snomed.info/sct | N42: 113075003 | O42: Serum Creatinine measurement | P42: http://unitsofmeasure.org | Q42: mg/dL | R42: milligram per deciliter | W42: male | X42: normal | Y42: 0.6 | Z42: 1.2
A43: Serum Creatinine | B43: serum-creatinine | C43: Measures the level of creatinine in the blood, an indicator of kidney function. | D43: laboratory | E43: active | F43: http://loinc.org | G43: 2160-0 | H43: Creatinine [Mass/volume] in Serum or Plasma | I43: decimal | M43: http://snomed.info/sct | N43: 113075003 | O43: Serum Creatinine measurement | P43: http://unitsofmeasure.org | Q43: mg/dL | R43: milligram per deciliter | W43: male | X43: high | Y43: 1.2
A44: Serum Creatinine | B44: serum-creatinine | C44: Measures the level of creatinine in the blood, an indicator of kidney function. | D44: laboratory | E44: active | F44: http://loinc.org | G44: 2160-0 | H44: Creatinine [Mass/volume] in Serum or Plasma | I44: decimal | M44: http://snomed.info/sct | N44: 113075003 | O44: Serum Creatinine measurement | P44: http://unitsofmeasure.org | Q44: mg/dL | R44: milligram per deciliter | W44: female | X44: low | Z44: 0.5
A45: Serum Creatinine | B45: serum-creatinine | C45: Measures the level of creatinine in the blood, an indicator of kidney function. | D45: laboratory | E45: active | F45: http://loinc.org | G45: 2160-0 | H45: Creatinine [Mass/volume] in Serum or Plasma | I45: decimal | M45: http://snomed.info/sct | N45: 113075003 | O45: Serum Creatinine measurement | P45: http://unitsofmeasure.org | Q45: mg/dL | R45: milligram per deciliter | W45: female | X45: normal | Y45: 0.5 | Z45: 0.9
A46: Serum Creatinine | B46: serum-creatinine | C46: Measures the level of creatinine in the blood, an indicator of kidney function. | D46: laboratory | E46: active | F46: http://loinc.org | G46: 2160-0 | H46: Creatinine [Mass/volume] in Serum or Plasma | I46: decimal | M46: http://snomed.info/sct | N46: 113075003 | O46: Serum Creatinine measurement | P46: http://unitsofmeasure.org | Q46: mg/dL | R46: milligram per deciliter | W46: female | X46: high | Y46: 0.9
A47: Serum Total Protein | B47: serum-total-protein | C47: Measures the total amount of proteins in the blood, mainly albumin and globulins. | D47: laboratory | E47: active | F47: http://loinc.org | G47: 2885-2 | H47: Protein [Mass/volume] in Serum or Plasma | I47: decimal | M47: http://snomed.info/sct | N47: 304383000 | O47: Total protein measurement | P47: http://unitsofmeasure.org | Q47: mg/dL | R47: milligram per deciliter | X47: low | Z47: 6.3
A48: Serum Total Protein | B48: serum-total-protein | C48: Measures the total amount of proteins in the blood, mainly albumin and globulins. | D48: laboratory | E48: active | F48: http://loinc.org | G48: 2885-2 | H48: Protein [Mass/volume] in Serum or Plasma | I48: decimal | M48: http://snomed.info/sct | N48: 304383000 | O48: Total protein measurement | P48: http://unitsofmeasure.org | Q48: mg/dL | R48: milligram per deciliter | X48: normal | Y48: 6.3 | Z48: 8.2
A49: Serum Total Protein | B49: serum-total-protein | C49: Measures the total amount of proteins in the blood, mainly albumin and globulins. | D49: laboratory | E49: active | F49: http://loinc.org | G49: 2885-2 | H49: Protein [Mass/volume] in Serum or Plasma | I49: decimal | M49: http://snomed.info/sct | N49: 304383000 | O49: Total protein measurement | P49: http://unitsofmeasure.org | Q49: mg/dL | R49: milligram per deciliter | X49: high | Y49: 8.2
A50: Serum Albumin | B50: serum-albumin | C50: Measures the level of albumin, the main protein in blood plasma produced by the liver | D50: laboratory | E50: active | F50: http://loinc.org | G50: 1751-7 | H50: Albumin [Mass/volume] in Serum or Plasma | I50: decimal | M50: http://snomed.info/sct | N50: 104485008 | O50: Albumin measurement, serum | P50: http://unitsofmeasure.org | Q50: mg/dL | R50: milligram per deciliter | X50: low | Z50: 3.5
A51: Serum Albumin | B51: serum-albumin | C51: Measures the level of albumin, the main protein in blood plasma produced by the liver | D51: laboratory | E51: active | F51: http://loinc.org | G51: 1751-7 | H51: Albumin [Mass/volume] in Serum or Plasma | I51: decimal | M51: http://snomed.info/sct | N51: 104485008 | O51: Albumin measurement, serum | P51: http://unitsofmeasure.org | Q51: mg/dL | R51: milligram per deciliter | X51: normal | Y51: 3.5 | Z51: 5
A52: Serum Albumin | B52: serum-albumin | C52: Measures the level of albumin, the main protein in blood plasma produced by the liver | D52: laboratory | E52: active | F52: http://loinc.org | G52: 1751-7 | H52: Albumin [Mass/volume] in Serum or Plasma | I52: decimal | M52: http://snomed.info/sct | N52: 104485008 | O52: Albumin measurement, serum | P52: http://unitsofmeasure.org | Q52: mg/dL | R52: milligram per deciliter | X52: high | Y52: 5
A53: S.TSH | B53: s-tsh-test | C53: Measures thyroid-stimulating hormone levels in the blood to assess thyroid gland function. | D53: laboratory | E53: active | F53: http://loinc.org | G53: 3016-3 | H53: Thyrotropin [Units/volume] in Serum or Plasma | I53: decimal | M53: http://snomed.info/sct | N53: 313440008 | O53: Measurement of serum thyroid stimulating hormone | P53: http://unitsofmeasure.org | Q53: ug/mL | R53: micrograms per milliliter | X53: low | Z53: 0.2
A54: S.TSH | B54: s-tsh-test | C54: Measures thyroid-stimulating hormone levels in the blood to assess thyroid gland function. | D54: laboratory | E54: active | F54: http://loinc.org | G54: 3016-3 | H54: Thyrotropin [Units/volume] in Serum or Plasma | I54: decimal | M54: http://snomed.info/sct | N54: 313440008 | O54: Measurement of serum thyroid stimulating hormone | P54: http://unitsofmeasure.org | Q54: ug/mL | R54: micrograms per milliliter | X54: normal | Y54: 0.2 | Z54: 4.2
A55: S.TSH | B55: s-tsh-test | C55: Measures thyroid-stimulating hormone levels in the blood to assess thyroid gland function. | D55: laboratory | E55: active | F55: http://loinc.org | G55: 3016-3 | H55: Thyrotropin [Units/volume] in Serum or Plasma | I55: decimal | M55: http://snomed.info/sct | N55: 313440008 | O55: Measurement of serum thyroid stimulating hormone | P55: http://unitsofmeasure.org | Q55: ug/mL | R55: micrograms per milliliter | X55: high | Y55: 4.2
A56: S.T3 | B56: s-trio-sn | C56: Measures total Triiodothyronine (bound + free) in serum to evaluate thyroid hormone production. | D56: laboratory | E56: active | F56: http://loinc.org | G56: 3053-6 | H56: Triiodothyronine (T3) [Mass/volume] in Serum or Plasma | I56: decimal | M56: http://snomed.info/sct | N56: 401105001 | O56: Serum total T3 level (procedure) | P56: http://unitsofmeasure.org | Q56: ng/mL | R56: nanograms per milliliter | X56: low | Z56: 0.75
A57: S.T3 | B57: s-trio-sn | C57: Measures total Triiodothyronine (bound + free) in serum to evaluate thyroid hormone production. | D57: laboratory | E57: active | F57: http://loinc.org | G57: 3053-6 | H57: Triiodothyronine (T3) [Mass/volume] in Serum or Plasma | I57: decimal | M57: http://snomed.info/sct | N57: 401105001 | O57: Serum total T3 level (procedure) | P57: http://unitsofmeasure.org | Q57: ng/mL | R57: nanograms per milliliter | X57: normal | Y57: 0.75 | Z57: 2.1
A58: S.T3 | B58: s-trio-sn | C58: Measures total Triiodothyronine (bound + free) in serum to evaluate thyroid hormone production. | D58: laboratory | E58: active | F58: http://loinc.org | G58: 3053-6 | H58: Triiodothyronine (T3) [Mass/volume] in Serum or Plasma | I58: decimal | M58: http://snomed.info/sct | N58: 401105001 | O58: Serum total T3 level (procedure) | P58: http://unitsofmeasure.org | Q58: ng/mL | R58: nanograms per milliliter | X58: high | Y58: 2.1
A59: S.T4 | B59: s-thy-sn | C59: Measures total Thyroxine (bound + free) in serum to assess overall thyroid hormone status. | D59: laboratory | E59: active | F59: http://loinc.org | G59: 3026-2 | H59: Thyroxine (T4) [Mass/volume] in Serum or Plasma | I59: integer | M59: http://snomed.info/sct | N59: 313862000 | O59: Serum total T4 level (procedure) | P59: http://unitsofmeasure.org | Q59: ug/dL | R59: micrograms per deciliter | X59: low | Z59: 5
A60: S.T4 | B60: s-thy-sn | C60: Measures total Thyroxine (bound + free) in serum to assess overall thyroid hormone status. | D60: laboratory | E60: active | F60: http://loinc.org | G60: 3026-2 | H60: Thyroxine (T4) [Mass/volume] in Serum or Plasma | I60: integer | M60: http://snomed.info/sct | N60: 313862000 | O60: Serum total T4 level (procedure) | P60: http://unitsofmeasure.org | Q60: ug/dL | R60: micrograms per deciliter | X60: normal | Y60: 5 | Z60: 13
A61: S.T4 | B61: s-thy-sn | C61: Measures total Thyroxine (bound + free) in serum to assess overall thyroid hormone status. | D61: laboratory | E61: active | F61: http://loinc.org | G61: 3026-2 | H61: Thyroxine (T4) [Mass/volume] in Serum or Plasma | I61: integer | M61: http://snomed.info/sct | N61: 313862000 | O61: Serum total T4 level (procedure) | P61: http://unitsofmeasure.org | Q61: ug/dL | R61: micrograms per deciliter | X61: high | Y61: 13
A62: Troponin - I | B62: troponin-i | C62: Measures cardiac-specific proteins released into the blood when heart muscle is damaged. | D62: laboratory | E62: active | F62: http://loinc.org | G62: 10839-9 | H62: Troponin I.cardiac [Mass/volume] in Serum or Plasma | I62: decimal | M62: http://snomed.info/sct | N62: 121870001 | O62: Troponin I measurement | P62: http://unitsofmeasure.org | Q62: ng/mL | R62: nanograms per milliliter | X62: low | Z62: 0
A63: Troponin - I | B63: troponin-i | C63: Measures cardiac-specific proteins released into the blood when heart muscle is damaged. | D63: laboratory | E63: active | F63: http://loinc.org | G63: 10839-9 | H63: Troponin I.cardiac [Mass/volume] in Serum or Plasma | I63: decimal | M63: http://snomed.info/sct | N63: 121870001 | O63: Troponin I measurement | P63: http://unitsofmeasure.org | Q63: ng/mL | R63: nanograms per milliliter | X63: normal | Y63: 0 | Z63: 0.3
A64: Troponin - I | B64: troponin-i | C64: Measures cardiac-specific proteins released into the blood when heart muscle is damaged. | D64: laboratory | E64: active | F64: http://loinc.org | G64: 10839-9 | H64: Troponin I.cardiac [Mass/volume] in Serum or Plasma | I64: decimal | M64: http://snomed.info/sct | N64: 121870001 | O64: Troponin I measurement | P64: http://unitsofmeasure.org | Q64: ng/mL | R64: nanograms per milliliter | X64: high | Y64: 0.3
A65: Serum HBsAg | B65: serum-hbsag | C65: Detects the presence of Hepatitis B surface antigen in the blood. | D65: laboratory | E65: active | F65: http://loinc.org | G65: 5195-3 | H65: Hepatitis B virus surface Ag [Presence] in Serum | I65: boolean | M65: http://snomed.info/sct | N65: 47758006 | O65: Hepatitis B surface antigen measurement | P65: http://unitsofmeasure.org
A66: HCV Antibody Test (Anti HCV) | B66: hcv-antibody-test-anti-hc1 | C66: Screens for antibodies produced in response to Hepatitis C virus infection. | D66: laboratory | E66: active | F66: http://loinc.org | G66: 16128-1 | H66: Hepatitis C virus Ab [Presence] in Serum | I66: boolean | M66: http://snomed.info/sct | N66: 64411004 | O66: Hepatitis C antibody measurement | P66: http://unitsofmeasure.org
A67: Hepatitis A virus Ab (HAV)-Rapid | B67: hepatitis-a-virus-ab-hav | C67: Detects IgM antibodies against Hepatitis A virus, indicating recent or acute infection. | D67: laboratory | E67: active | F67: http://loinc.org | G67: 22314-9 | H67: Hepatitis A virus IgM Ab [Presence] in Serum | I67: boolean | M67: http://snomed.info/sct | N67: 88159009 | O67: Hepatitis A virus antibody, immunoglobulin M type | P67: http://unitsofmeasure.org
A68: Hepatitis E Ab (HEV)-Rapid | B68: hepatitis-e-ab-hev-rapid | C68: Detects IgM antibodies to hepatitis E virus (HEV) in blood using a rapid test method. | D68: laboratory | E68: active | F68: http://loinc.org | G68: 14212-5 | H68: Hepatitis E virus IgM Ab [Presence] in Serum | I68: boolean | M68: http://snomed.info/sct | N68: 401242000 | O68: Hepatitis E immunoglobulin M level | P68: http://unitsofmeasure.org
A69: Widal test | B69: widal-test | C69: Indicates recent or acute hepatitis E infection. | D69: laboratory | E69: active | F69: http://loinc.org | G69: 98211-6 | H69: Salmonella species antibody panel- Serum by agglutination | I69: string | M69: http://snomed.info/sct | N69: 165828002 | O69: Widal test (procedure) | P69: http://unitsofmeasure.org
A70: Widal test | B70: widal-test | C70: Indicates recent or acute hepatitis E infection. | D70: laboratory | E70: active | F70: http://loinc.org | G70: 98211-6 | H70: Salmonella species antibody panel- Serum by agglutination | I70: string | M70: http://snomed.info/sct | N70: 165828002 | O70: Widal test (procedure) | P70: http://unitsofmeasure.org
A71: Widal test | B71: widal-test | C71: Indicates recent or acute hepatitis E infection. | D71: laboratory | E71: active | F71: http://loinc.org | G71: 98211-6 | H71: Salmonella species antibody panel- Serum by agglutination | I71: string | M71: http://snomed.info/sct | N71: 165828002 | O71: Widal test (procedure) | P71: http://unitsofmeasure.org
A72: ASO {titer} | B72: aso-titer | C72: Detects antistreptolysin O (ASO) antibodies. | D72: laboratory | E72: active | F72: http://loinc.org | G72: 5370-2 | H72: Streptolysin O Ab [Units/volume] in Serum or Plasma | I72: integer | M72: http://snomed.info/sct | N72: 82703001 | O72: Antistreptolysin O {titer} (procedure) | P72: http://unitsofmeasure.org | Q72: [IU]/mL | R72: international unit per milliliter | X72: low | Z72: 0
A73: ASO {titer} | B73: aso-titer | C73: Detects antistreptolysin O (ASO) antibodies. | D73: laboratory | E73: active | F73: http://loinc.org | G73: 5370-2 | H73: Streptolysin O Ab [Units/volume] in Serum or Plasma | I73: integer | M73: http://snomed.info/sct | N73: 82703001 | O73: Antistreptolysin O {titer} (procedure) | P73: http://unitsofmeasure.org | Q73: [IU]/mL | R73: international unit per milliliter | X73: normal | Y73: 200 | Z73: 400
A74: ASO {titer} | B74: aso-titer | C74: Detects antistreptolysin O (ASO) antibodies. | D74: laboratory | E74: active | F74: http://loinc.org | G74: 5370-2 | H74: Streptolysin O Ab [Units/volume] in Serum or Plasma | I74: integer | M74: http://snomed.info/sct | N74: 82703001 | O74: Antistreptolysin O {titer} (procedure) | P74: http://unitsofmeasure.org | Q74: [IU]/mL | R74: international unit per milliliter | X74: high | Y74: 400
A75: RA factor (Quantitative) | B75: ra-factor-quantitative | C75: Indicates recent streptococcal infection. | D75: laboratory | E75: active | F75: http://loinc.org | G75: 11572-5 | H75: Rheumatoid factor [Units/volume] in Serum or Plasma | I75: integer | M75: http://snomed.info/sct | N75: 10239008 | O75: Rheumatoid factor, quantitative | P75: http://unitsofmeasure.org | Q75: [IU]/mL | R75: international unit per milliliter | X75: low | Z75: 14
A76: RA factor (Quantitative) | B76: ra-factor-quantitative | C76: Indicates recent streptococcal infection. | D76: laboratory | E76: active | F76: http://loinc.org | G76: 11572-5 | H76: Rheumatoid factor [Units/volume] in Serum or Plasma | I76: integer | M76: http://snomed.info/sct | N76: 10239008 | O76: Rheumatoid factor, quantitative | P76: http://unitsofmeasure.org | Q76: [IU]/mL | R76: international unit per milliliter | X76: normal | Y76: 14 | Z76: 60
A77: RA factor (Quantitative) | B77: ra-factor-quantitative | C77: Indicates recent streptococcal infection. | D77: laboratory | E77: active | F77: http://loinc.org | G77: 11572-5 | H77: Rheumatoid factor [Units/volume] in Serum or Plasma | I77: integer | M77: http://snomed.info/sct | N77: 10239008 | O77: Rheumatoid factor, quantitative | P77: http://unitsofmeasure.org | Q77: [IU]/mL | R77: international unit per milliliter | X77: high | Y77: 60
A78: CRP (including new born) | B78: crp-including-new-born | C78: Measures C-reactive protein levels in the blood, a marker of inflammation or infection. | D78: laboratory | E78: active | F78: http://loinc.org | G78: 30522-7 | H78: C reactive protein [Mass/volume] in Serum or Plasma by High sensitivity method | I78: integer | M78: http://snomed.info/sct | N78: 55235003 | O78: C-reactive protein measurement | P78: http://unitsofmeasure.org | Q78: mg/L | R78: milligram per deciliter | X78: low | Z78: 6
A79: CRP (including new born) | B79: crp-including-new-born | C79: Measures C-reactive protein levels in the blood, a marker of inflammation or infection. | D79: laboratory | E79: active | F79: http://loinc.org | G79: 30522-7 | H79: C reactive protein [Mass/volume] in Serum or Plasma by High sensitivity method | I79: integer | M79: http://snomed.info/sct | N79: 55235003 | O79: C-reactive protein measurement | P79: http://unitsofmeasure.org | Q79: mg/L | R79: milligram per deciliter | X79: normal | Y79: 6 | Z79: 100
A80: CRP (including new born) | B80: crp-including-new-born | C80: Measures C-reactive protein levels in the blood, a marker of inflammation or infection. | D80: laboratory | E80: active | F80: http://loinc.org | G80: 30522-7 | H80: C reactive protein [Mass/volume] in Serum or Plasma by High sensitivity method | I80: integer | M80: http://snomed.info/sct | N80: 55235003 | O80: C-reactive protein measurement | P80: http://unitsofmeasure.org | Q80: mg/L | R80: milligram per deciliter | X80: high | Y80: 100
A81: RPR/VDRL test for Syphilis | B81: rprvdrl-test-for-syphili | C81: A screening test that detects antibodies produced in response to syphilis infection. | D81: laboratory | E81: active | F81: http://loinc.org | G81: 20507-0 | H81: Reagin Ab [Presence] in Serum by RPR | I81: string | M81: http://snomed.info/sct | N81: 19869000 | O81: Rapid Plasma Reagin (RPR) test | P81: http://unitsofmeasure.org
A82: RPR/VDRL test for Syphilis | B82: rprvdrl-test-for-syphili | C82: A screening test that detects antibodies produced in response to syphilis infection. | D82: laboratory | E82: active | F82: http://loinc.org | G82: 20507-0 | H82: Reagin Ab [Presence] in Serum by RPR | I82: string | M82: http://snomed.info/sct | N82: 19869000 | O82: Rapid Plasma Reagin (RPR) test | P82: http://unitsofmeasure.org
A83: RPR/VDRL test for Syphilis | B83: rprvdrl-test-for-syphili | C83: A screening test that detects antibodies produced in response to syphilis infection. | D83: laboratory | E83: active | F83: http://loinc.org | G83: 20507-0 | H83: Reagin Ab [Presence] in Serum by RPR | I83: string | M83: http://snomed.info/sct | N83: 19869000 | O83: Rapid Plasma Reagin (RPR) test | P83: http://unitsofmeasure.org
A84: ELISA ANA | B84: elisa-ana | C84: Measure antinuclear antibodies (ANA) in serum using ELISA. Helps screen for autoimmune diseases. | D84: laboratory | E84: active | F84: http://loinc.org | G84: 47383-5 | H84: Nuclear Ab [Presence ] in serum by immunoassay | I84: string | M84: http://snomed.info/sct | N84: 76978006 | O84: Enzyme-linked immunosorbent assay (procedure) | P84: http://unitsofmeasure.org | X84: low | Z84: 1
A85: ELISA ANA | B85: elisa-ana | C85: Measure antinuclear antibodies (ANA) in serum using ELISA. Helps screen for autoimmune diseases. | D85: laboratory | E85: active | F85: http://loinc.org | G85: 47383-5 | H85: Nuclear Ab [Presence ] in serum by immunoassay | I85: string | M85: http://snomed.info/sct | N85: 76978006 | O85: Enzyme-linked immunosorbent assay (procedure) | P85: http://unitsofmeasure.org | X85: normal | Y85: 1 | Z85: 1.5
A86: ELISA ANA | B86: elisa-ana | C86: Measure antinuclear antibodies (ANA) in serum using ELISA. Helps screen for autoimmune diseases. | D86: laboratory | E86: active | F86: http://loinc.org | G86: 47383-5 | H86: Nuclear Ab [Presence ] in serum by immunoassay | I86: string | M86: http://snomed.info/sct | N86: 76978006 | O86: Enzyme-linked immunosorbent assay (procedure) | P86: http://unitsofmeasure.org | X86: high | Y86: 1.5
A87: Dengue Test | B87: dengue-test | C87: Detects dengue virus infection using antigen or antibody-based methods. | D87: laboratory | E87: active | F87: http://loinc.org | G87: 104595-4 | H87: Dengue virus Ab.IgG and IgM and NS1 Ag panel - Serum or Plasma | I87: boolean | M87: http://snomed.info/sct | N87: 399302007 | O87: Polymerase chain reaction test for Dengue virus | P87: http://unitsofmeasure.org
A88: Test for Dengue ELISA | B88: test-for-dengue-elisa | C88: Detects dengue virus infection using antigen or antibody-based methods. | D88: laboratory | E88: active | F88: http://loinc.org | G88: 104595-4 | H88: Dengue virus Ab.IgG and IgM and NS1 Ag panel - Serum or Plasma | I88: boolean | M88: http://snomed.info/sct | N88: 399302007 | O88: Polymerase chain reaction test for Dengue virus | P88: http://unitsofmeasure.org
A89: SARS COV-19 PCR test | B89: sars-cov-19-pcr-test | C89: Detects SARS-CoV-2 RNA using real-time PCR. Used for diagnosis of COVID-19. | D89: laboratory | E89: active | F89: http://loinc.org | G89: 96895-8 | H89: SARS-CoV-2 (COVID-19) lineage [Identifier] in Specimen by Molecular genetics method | I89: boolean | M89: http://snomed.info/sct | N89: 399150003 | O89: Polymerase chain reaction test for severe acute respiratory syndrome | P89: http://unitsofmeasure.org
A90: Scrub typhus Test - ELISA | B90: scrub-typhus-test-elisa | C90: Detects antibodies or antigens associated with Orientia tsutsugamushi, the organism causing scrub typhus. | D90: laboratory | E90: active | F90: http://loinc.org | G90: 33897-0 | H90: Orientia tsutsugamushi IgM Ab [Presence] in Serum or Plasma | I90: boolean | M90: http://snomed.info/sct | N90: 104273003 | O90: Febrile agglutinins measurement, Brucella, Francisella, Murine typhus, Q fever, Rocky Mountain Spotted Fever, scrub typhus | P90: http://unitsofmeasure.org
A91: Respiratory Panels (RT PCR) | B91: respiratory-panels-rt-pcr | C91: Multiplex RT-PCR panel detecting common respiratory pathogens. Used in acute respiratory infections. | D91: laboratory | E91: active | F91: http://loinc.org | G91: 92143-7 | H91: Respiratory pathogens DNA and RNA panel - Respiratory system specimen by NAA with probe detection | I91: boolean | M91: http://snomed.info/sct | N91: 115252004 | O91: Microbiological identification method (procedure) | P91: http://unitsofmeasure.org
A92: Typhoid IgM | B92: typhoid-igm | C92: Detects IgM antibodies specific to Salmonella typhi, indicating recent typhoid infection. | D92: laboratory | E92: active | F92: http://loinc.org | G92: 9674-3 | H92: Salmonella sp IgM Ab | I92: boolean | M92: http://snomed.info/sct | N92: 414464004 | O92: Immunoassay method (procedure) | P92: http://unitsofmeasure.org
A93: Influenza A and B virus with subtypes | B93: influenza-a-and-b-virus-w | C93: Molecular detection of Influenza A and B viral RNA. Used in influenza diagnosis. | D93: laboratory | E93: active | F93: http://loinc.org | G93: 81233-9 | H93: Influenza virus types A and B and subtypes RNA panel - Respiratory system specimen by NAA with probe detection | I93: boolean | M93: http://snomed.info/sct | N93: 118089005 | O93: Influenza A virus and Influenza B virus antigen assay (procedure) | P93: http://unitsofmeasure.org
A94: Respiratory Syncytial Virus (RSV) A and B | B94: respiratory-syncytial | C94: PCR-based detection of RSV subtypes. Used in pediatric and adult respiratory infections. | D94: laboratory | E94: active | F94: http://loinc.org | G94: 72885-7 | H94: Respiratory syncytial virus Ag [Presence] in Nasopharynx by Rapid immunoassay | I94: boolean | M94: http://snomed.info/sct | N94: 122274003 | O94: Respiratory syncytial virus culture (procedure) | P94: http://unitsofmeasure.org
A95: Human Meta Pneumo Virus (HMPV) | B95: human-meta-pneumo-virus | C95: Human metapneumovirus RNA [Presence] in Respiratory system specimen by NAA with probe detection | D95: laboratory | E95: active | F95: http://loinc.org | G95: 92134-6 | H95: Human metapneumovirus RNA [Presence] in Respiratory system specimen by NAA with probe detection | I95: boolean | M95: http://snomed.info/sct | N95: 115252004 | O95: Microbiological identification method (procedure) | P95: http://unitsofmeasure.org
A96: Para influenza virus 1 to 4 | B96: para-influenza-virus-1-to | C96: PCR detection of Parainfluenza virus types 1 to 4. Used in respiratory infection evaluation. | D96: laboratory | E96: active | F96: http://loinc.org | G96: 88890-9 | H96: Parainfluenza virus 1+2+3+4 RNA [Presence] in Nasopharynx by NAA with non-probe detection | I96: boolean | M96: http://snomed.info/sct | N96: 391431008 | O96: Parainfluenza virus antibody level (procedure) | P96: http://unitsofmeasure.org
A97: HPV PCR test | B97: hpv-pcr-test | C97: Detects Human Papillomavirus DNA in clinical specimens using polymerase chain reaction. Used in cervical cancer screening and diagnosis of HPV infection. | D97: laboratory | E97: active | F97: http://loinc.org | G97: 6516-9 | H97: Human papilloma virus rRNA [Presence] in Specimen by NAA with probe detection | I97: boolean | M97: http://snomed.info/sct | N97: 122416008 | O97: Papillomavirus ribosomal ribonucleic acid assay (procedure) | P97: http://unitsofmeasure.org
A98: Herpes Simplex Virus (HSV) 1 and 2 ELISA | B98: herpes-simplex-virus-hsv | C98: Detects antibodies against HSV type 1 and 2. Used in evaluation of HSV exposure or infection. | D98: laboratory | E98: active | F98: http://loinc.org | G98: 81621-5 | H98: Herpes simplex virus 1 and 2 IgG panel - Serum or Plasma | I98: boolean | M98: http://snomed.info/sct | N98: 117736004 | O98: Measurement of Human herpesvirus 1 antibody and Human herpesvirus 2 antibody (procedure) | P98: http://unitsofmeasure.org
... A102: HIV test (Antibodies 1 and 2) | B102: hiv-test-antibodies-1-and | C102: HIV test (Antibodies 1 and 2) | D102: laboratory | E102: active | F102: http://loinc.org | G102: 85037-0 | H102: (HIV 1 and 2 Ab and HIV 1 p24 Ag panel - Serum or Plasma by Immunoassay) | I102: boolean | M102: http://snomed.info/sct | N102: 50806003 | O102: Human immunodeficiency virus type 1 antibody confirmatory test | P102: http://unitsofmeasure.org
A103: CD4 count | B103: cd4-count | C103: Measures the number of CD4+ T-lymphocytes in the blood, an important marker of immune function. | D103: laboratory | E103: active | F103: http://loinc.org | G103: 24467-3 | H103: CD3+CD4+ (T4 helper) cells [#/volume] in Blood | I103: integer | M103: http://snomed.info/sct | N103: 313660005 | O103: Absolute CD4 count procedure | P103: http://unitsofmeasure.org | Q103: {cells}/uL | R103: cells per microliter | X103: low | Z103: 200
...

Sheet observation_definition
A1: Title | B1: slug_value | C1: description | D1: category | E1: status | F1: code_system | G1: code_value | H1: code_display | I1: permitted_data_type | J1: body_site_system | K1: body_site_code | L1: body_site_display | M1: method_system | N1: method_code | O1: method_display | P1: permitted_unit_system | Q1: permitted_unit_code | R1: permitted_unit_display | S1: derived_from_uri
A2: Random Blood Sugar (RBS) | B2: random-blood-sugar-rbs | C2: Measures the level of glucose in the blood | D2: laboratory | E2: active | F2: http://loinc.org | G2: 74774-1 | H2: Glucose [Mass/volume] in Serum, Plasma or Blood | I2: integer | M2: http://snomed.info/sct | N2: 36048009 | O2: Glucose measurement | P2: http://unitsofmeasure.org | Q2: mg/dL | R2: milligram per deciliter
A3: Fasting Blood Sugar (FBS) | B3: fasting-blood-sugar-fbs | C3: Measures the level of glucose in the blood in the fasting state | D3: laboratory | E3: active | F3: http://loinc.org | G3: 1557-8 | H3: Fasting glucose [Mass/volume] in Venous blood | I3: integer | M3: http://snomed.info/sct | N3: 36048009 | O3: Glucose measurement | P3: http://unitsofmeasure.org | Q3: mg/dL | R3: milligram per deciliter
A4: Post Prandial Blood Sugar (PPBS) | B4: post-prandial-blood-sugar | C4: Measures the level of glucose in the blood after a meal, used to assess how the body processes sugar and to monitor diabetes control | D4: laboratory | E4: active | F4: http://loinc.org | G4: 87422-2 | H4: Glucose [Mass/volume] in Blood – Post meal | I4: integer | M4: http://snomed.info/sct | N4: 302788006 | O4: Post-prandial blood glucose measurement | P4: http://unitsofmeasure.org | Q4: mg/dL | R4: milligram per deciliter
A5: Glucose Tolerance test (GTT) | B5: glucose-tolerance-test-gt | C5: Ordered to assess how the body processes glucose and to help diagnose diabetes or gestational diabetes | D5: laboratory | E5: active | F5: http://loinc.org | G5: 21004-7 | H5: Glucose tolerance [Interpretation] in Serum or Plasma | I5: integer | M5: http://snomed.info/sct | N5: 113076002 | O5: Glucose tolerance test (procedure) | P5: http://unitsofmeasure.org | Q5: mg/dL | R5: milligram per deciliter
A6: Glucose Tolerance test (GTT)-2hrs | B6: glucose-tolerance-test-th | C6: Ordered to assess how the body processes glucose and to help diagnose diabetes or gestational diabetes | D6: laboratory | E6: active | F6: http://loinc.org | G6: 21004-7 | H6: Glucose tolerance [Interpretation] in Serum or Plasma | I6: integer | M6: http://snomed.info/sct | N6: 113076002 | O6: Glucose tolerance test (procedure) | P6: http://unitsofmeasure.org | Q6: mg/dL | R6: milligram per deciliter
A7: Serum Uric acid | B7: serum-uric-acid | C7: Measures uric acid levels in the blood, reflecting purine metabolism | D7: laboratory | E7: active | F7: http://loinc.org | G7: 3084-1 | H7: Urate [Measurement] in Serum or Plasma | I7: decimal | M7: http://snomed.info/sct | N7: 275740009 | O7: Serum Uric acid measurement | P7: http://unitsofmeasure.org | Q7: mg/dL | R7: milligram per deciliter
A8: Serum Calcium | B8: serum-calcium | C8: Measures total calcium in the blood, essential for bone health, nerve signals, and muscle function | D8: laboratory | E8: active | F8: http://loinc.org | G8: 17861-6 | H8: Calcium [Mass/volume] in Serum or Plasma | I8: decimal | M8: http://snomed.info/sct | N8: 271240001 | O8: Serum Calcium measurement | P8: http://unitsofmeasure.org | Q8: mg/dL | R8: milligram per deciliter
A9: Serum Amylase | B9: serum-amylase | C9: Measures the level of amylase enzyme in the blood, mainly from the pancreas and salivary glands. | D9: laboratory | E9: active | F9: http://loinc.org | G9: 1798-8 | H9: Amylase [Enzymatic activity/volume] in Serum or Plasma | I9: integer | M9: http://snomed.info/sct | N9: 89659001 | O9: Amylase measurement, serum | P9: http://unitsofmeasure.org | Q9: U/L | R9: enzyme unit per liter
A10: Serum Lipase | B10: serum-lipase | C10: Measures the level of lipase enzyme in the serum, which is primarily produced by the pancreas to break down fats. | D10: laboratory | E10: active | F10: http://loinc.org | G10: 3040-3 | H10: Lipase [Enzymatic activity/volume] in Serum or Plasma | I10: integer | M10: http://snomed.info/sct | N10: 271232007 | O10: Serum Lipase Measurement | P10: http://unitsofmeasure.org | Q10: U/L | R10: enzyme unit per liter
A11: Serum LDH | B11: serum-ldh | C11: Measures LDH enzyme levels, which increase with tissue damage in many organs. | D11: laboratory | E11: active | F11: http://loinc.org | G11: 14804-9 | H11: Lactate dehydrogenase [Enzymatic activity/volume] in Serum or Plasma by Lactate to pyruvate reaction | I11: integer | M11: http://snomed.info/sct | N11: 313854008 | O11: Serum Lactate dehydrogenase measurement | P11: http://unitsofmeasure.org | Q11: U/L | R11: enzyme unit per liter
A12: Serum Phosphorus | B12: serum-phosphorus | C12: Measures the level of phosphorus (phosphate) in the serum, which plays a key role in bone formation, energy production, and maintaining acid–base balance in the body. | D12: laboratory | E12: active | F12: http://loinc.org | G12: 2777-1 | H12: Phosphate [Mass/volume] in Serum or Plasma | I12: decimal | M12: http://snomed.info/sct | N12: 271241002 | O12: Serum inorganic phosphate measurement (procedure) | P12: http://unitsofmeasure.org | Q12: mg/dL | R12: milligram per deciliter
A13: Serum Bicarbonate | B13: serum-bicarbonate | C13: Measures serum bicarbonate level for acid–base balance. | D13: laboratory | E13: active | F13: http://loinc.org | G13: 1963-8 | H13: Bicarbonate [Moles/volume] in Serum or Plasma | I13: integer | M13: http://snomed.info/sct | N13: 271239003 | O13: Serum bicarbonate measurement (procedure) | P13: http://unitsofmeasure.org | Q13: mmol/L | R13: millimole per liter
... A21: Troponin - I | B21: troponin-i | C21: Measures cardiac-specific proteins released into the blood when heart muscle is damaged. | D21: laboratory | E21: active | F21: http://loinc.org | G21: 10839-9 | H21: Troponin I.cardiac [Mass/volume] in Serum or Plasma | I21: decimal | M21: http://snomed.info/sct | N21: 121870001 | O21: Troponin I measurement | P21: http://unitsofmeasure.org | Q21: ng/mL | R21: nanograms per milliliter
A22: Serum HBsAg | B22: serum-hbsag | C22: Detects the presence of Hepatitis B surface antigen in the blood. | D22: laboratory | E22: active | F22: http://loinc.org | G22: 5195-3 | H22: Hepatitis B virus surface Ag [Presence] in Serum | I22: boolean | M22: http://snomed.info/sct | N22: 47758006 | O22: Hepatitis B surface antigen measurement | P22: http://unitsofmeasure.org
A23: HCV Antibody Test (Anti HCV) | B23: hcv-antibody-test-anti-hc1 | C23: Screens for antibodies produced in response to Hepatitis C virus infection. | D23: laboratory | E23: active | F23: http://loinc.org | G23: 16128-1 | H23: Hepatitis C virus Ab [Presence] in Serum | I23: boolean | M23: http://snomed.info/sct | N23: 64411004 | O23: Hepatitis C antibody measurement | P23: http://unitsofmeasure.org
A24: Hepatitis A virus Ab (HAV)-Rapid | B24: hepatitis-a-virus-ab-hav | C24: Detects IgM antibodies against Hepatitis A virus, indicating recent or acute infection. | D24: laboratory | E24: active | F24: http://loinc.org | G24: 22314-9 | H24: Hepatitis A virus IgM Ab [Presence] in Serum | I24: boolean | M24: http://snomed.info/sct | N24: 88159009 | O24: Hepatitis A virus antibody, immunoglobulin M type | P24: http://unitsofmeasure.org
A25: Hepatitis E Ab (HEV)-Rapid | B25: hepatitis-e-ab-hev-rapid | C25: Detects IgM antibodies to hepatitis E virus (HEV) in blood using a rapid test method. | D25: laboratory | E25: active | F25: http://loinc.org | G25: 14212-5 | H25: Hepatitis E virus IgM Ab [Presence] in Serum | I25: boolean | M25: http://snomed.info/sct | N25: 401242000 | O25: Hepatitis E immunoglobulin M level | P25: http://unitsofmeasure.org
A26: Widal test | B26: widal-test | C26: Indicates recent or acute hepatitis E infection. | D26: laboratory | E26: active | F26: http://loinc.org | G26: 98211-6 | H26: Salmonella species antibody panel- Serum by agglutination | I26: string | M26: http://snomed.info/sct | N26: 165828002 | O26: Widal test (procedure) | P26: http://unitsofmeasure.org
A27: ASO {titer} | B27: aso-titer | C27: Detects antistreptolysin O (ASO) antibodies. | D27: laboratory | E27: active | F27: http://loinc.org | G27: 5370-2 | H27: Streptolysin O Ab [Units/volume] in Serum or Plasma | I27: integer | M27: http://snomed.info/sct | N27: 82703001 | O27: Antistreptolysin O {titer} (procedure) | P27: http://unitsofmeasure.org | Q27: [IU]/mL | R27: international unit per milliliter
A28: RA factor (Quantitative) | B28: ra-factor-quantitative | C28: Indicates recent streptococcal infection. | D28: laboratory | E28: active | F28: http://loinc.org | G28: 11572-5 | H28: Rheumatoid factor [Units/volume] in Serum or Plasma | I28: integer | M28: http://snomed.info/sct | N28: 10239008 | O28: Rheumatoid factor, quantitative | P28: http://unitsofmeasure.org | Q28: [IU]/mL | R28: international unit per milliliter
A29: CRP (including new born) | B29: crp-including-new-born | C29: Measures C-reactive protein levels in the blood, a marker of inflammation or infection. | D29: laboratory | E29: active | F29: http://loinc.org | G29: 30522-7 | H29: C reactive protein [Mass/volume] in Serum or Plasma by High sensitivity method | I29: integer | M29: http://snomed.info/sct | N29: 55235003 | O29: C-reactive protein measurement | P29: http://unitsofmeasure.org | Q29: mg/L | R29: milligram per deciliter
A30: RPR/VDRL test for Syphilis | B30: rprvdrl-test-for-syphili | C30: A screening test that detects antibodies produced in response to syphilis infection. | D30: laboratory | E30: active | F30: http://loinc.org | G30: 20507-0 | H30: Reagin Ab [Presence] in Serum by RPR | I30: string | M30: http://snomed.info/sct | N30: 19869000 | O30: Rapid Plasma Reagin (RPR) test | P30: http://unitsofmeasure.org
A31: ELISA ANA | B31: elisa-ana | C31: Measure antinuclear antibodies (ANA) in serum using ELISA. Helps screen for autoimmune diseases. | D31: laboratory | E31: active | F31: http://loinc.org | G31: 47383-5 | H31: Nuclear Ab [Presence ] in serum by immunoassay | I31: string | M31: http://snomed.info/sct | N31: 76978006 | O31: Enzyme-linked immunosorbent assay (procedure) | P31: http://unitsofmeasure.org
A32: Dengue Test | B32: dengue-test | C32: Detects dengue virus infection using antigen or antibody-based methods. | D32: laboratory | E32: active | F32: http://loinc.org | G32: 104595-4 | H32: Dengue virus Ab.IgG and IgM and NS1 Ag panel - Serum or Plasma | I32: boolean | M32: http://snomed.info/sct | N32: 399302007 | O32: Polymerase chain reaction test for Dengue virus | P32: http://unitsofmeasure.org
A33: Test for Dengue ELISA | B33: test-for-dengue-elisa | C33: Detects dengue virus infection using antigen or antibody-based methods. | D33: laboratory | E33: active | F33: http://loinc.org | G33: 104595-4 | H33: Dengue virus Ab.IgG and IgM and NS1 Ag panel - Serum or Plasma | I33: boolean | M33: http://snomed.info/sct | N33: 399302007 | O33: Polymerase chain reaction test for Dengue virus | P33: http://unitsofmeasure.org
A34: SARS COV-19 PCR test | B34: sars-cov-19-pcr-test | C34: Detects SARS-CoV-2 RNA using real-time PCR. Used for diagnosis of COVID-19. | D34: laboratory | E34: active | F34: http://loinc.org | G34: 96895-8 | H34: SARS-CoV-2 (COVID-19) lineage [Identifier] in Specimen by Molecular genetics method | I34: boolean | M34: http://snomed.info/sct | N34: 399150003 | O34: Polymerase chain reaction test for severe acute respiratory syndrome | P34: http://unitsofmeasure.org
A35: Scrub typhus Test - ELISA | B35: scrub-typhus-test-elisa | C35: Detects antibodies or antigens associated with Orientia tsutsugamushi, the organism causing scrub typhus. | D35: laboratory | E35: active | F35: http://loinc.org | G35: 33897-0 | H35: Orientia tsutsugamushi IgM Ab [Presence] in Serum or Plasma | I35: boolean | M35: http://snomed.info/sct | N35: 104273003 | O35: Febrile agglutinins measurement, Brucella, Francisella, Murine typhus, Q fever, Rocky Mountain Spotted Fever, scrub typhus | P35: http://unitsofmeasure.org
A36: Respiratory Panels (RT PCR) | B36: respiratory-panels-rt-pcr | C36: Multiplex RT-PCR panel detecting common respiratory pathogens. Used in acute respiratory infections. | D36: laboratory | E36: active | F36: http://loinc.org | G36: 92143-7 | H36: Respiratory pathogens DNA and RNA panel - Respiratory system specimen by NAA with probe detection | I36: boolean | M36: http://snomed.info/sct | N36: 115252004 | O36: Microbiological identification method (procedure) | P36: http://unitsofmeasure.org
A37: Typhoid IgM | B37: typhoid-igm | C37: Detects IgM antibodies specific to Salmonella typhi, indicating recent typhoid infection. | D37: laboratory | E37: active | F37: http://loinc.org | G37: 9674-3 | H37: Salmonella sp IgM Ab | I37: boolean | M37: http://snomed.info/sct | N37: 414464004 | O37: Immunoassay method (procedure) | P37: http://unitsofmeasure.org
A38: Influenza A and B virus with subtypes | B38: influenza-a-and-b-virus-w | C38: Molecular detection of Influenza A and B viral RNA. Used in influenza diagnosis. | D38: laboratory | E38: active | F38: http://loinc.org | G38: 81233-9 | H38: Influenza virus types A and B and subtypes RNA panel - Respiratory system specimen by NAA with probe detection | I38: boolean | M38: http://snomed.info/sct | N38: 118089005 | O38: Influenza A virus and Influenza B virus antigen assay (procedure) | P38: http://unitsofmeasure.org
A39: Respiratory Syncytial Virus (RSV) A and B | B39: respiratory-syncytial | C39: PCR-based detection of RSV subtypes. Used in pediatric and adult respiratory infections. | D39: laboratory | E39: active | F39: http://loinc.org | G39: 72885-7 | H39: Respiratory syncytial virus Ag [Presence] in Nasopharynx by Rapid immunoassay | I39: boolean | M39: http://snomed.info/sct | N39: 122274003 | O39: Respiratory syncytial virus culture (procedure) | P39: http://unitsofmeasure.org
A40: Human Meta Pneumo Virus (HMPV) | B40: human-meta-pneumo-virus | C40: Human metapneumovirus RNA [Presence] in Respiratory system specimen by NAA with probe detection | D40: laboratory | E40: active | F40: http://loinc.org | G40: 92134-6 | H40: Human metapneumovirus RNA [Presence] in Respiratory system specimen by NAA with probe detection | I40: boolean | M40: http://snomed.info/sct | N40: 115252004 | O40: Microbiological identification method (procedure) | P40: http://unitsofmeasure.org
A41: Para influenza virus 1 to 4 | B41: para-influenza-virus-1-to | C41: PCR detection of Parainfluenza virus types 1 to 4. Used in respiratory infection evaluation. | D41: laboratory | E41: active | F41: http://loinc.org | G41: 88890-9 | H41: Parainfluenza virus 1+2+3+4 RNA [Presence] in Nasopharynx by NAA with non-probe detection | I41: boolean | M41: http://snomed.info/sct | N41: 391431008 | O41: Parainfluenza virus antibody level (procedure) | P41: http://unitsofmeasure.org
... A47: HIV test (Antibodies 1 and 2) | B47: hiv-test-antibodies-1-and | C47: HIV test (Antibodies 1 and 2) | D47: laboratory | E47: active | F47: http://loinc.org | G47: 85037-0 | H47: (HIV 1 and 2 Ab and HIV 1 p24 Ag panel - Serum or Plasma by Immunoassay) | I47: boolean | M47: http://snomed.info/sct | N47: 50806003 | O47: Human immunodeficiency virus type 1 antibody confirmatory test | P47: http://unitsofmeasure.org
A48: CD4 count | B48: cd4-count | C48: Measures the number of CD4+ T-lymphocytes in the blood, an important marker of immune function. | D48: laboratory | E48: active | F48: http://loinc.org | G48: 24467-3 | H48: CD3+CD4+ (T4 helper) cells [#/volume] in Blood | I48: integer | M48: http://snomed.info/sct | N48: 313660005 | O48: Absolute CD4 count procedure | P48: http://unitsofmeasure.org | Q48: {cells}/uL | R48: cells per microliter
A49: HCV Antibody Test (Anti HCV) | B49: hcv-antibody-test-anti-hc2 | C49: Screens for antibodies produced in response to Hepatitis C virus infection. | D49: laboratory | E49: active | F49: http://loinc.org | G49: 13955-0 | H49: Hepatitis C virus Ab [Presence] in Serum | I49: boolean | M49: http://snomed.info/sct | N49: 64411004 | O49: Hepatitis C antibody measurement | P49: http://unitsofmeasure.org
A50: Japanese Encephalitis IgM | B50: japanese-encephalitis-igm | C50: Detects IgM antibodies against Japanese Encephalitis virus in blood or cerebrospinal fluid for confirmatory diagnosis. | D50: laboratory | E50: active | F50: http://loinc.org | G50: 60532-9 | H50: Japanese encephalitis virus IgM Ab [{titer}] in Cerebral spinal fluid | I50: boolean | M50: http://snomed.info/sct | N50: 122015000 | O50: Measurement of Japanese encephalitis virus antibody | P50: http://unitsofmeasure.org
A51: IgM for Hepatitis A | B51: igm-for-hepatitis-a | C51: Detects IgM antibodies against Hepatitis A virus, indicating recent or acute infection. | D51: laboratory | E51: active | F51: http://loinc.org | G51: 22314-9 | H51: Hepatitis A virus IgM Ab [Presence] in Serum | I51: boolean | M51: http://snomed.info/sct | N51: 88159009 | O51: Hepatitis A virus antibody, immunoglobulin M type | P51: http://unitsofmeasure.org
A52: IgM for Hepatitis E | B52: igm-for-hepatitis-e | C52: Ordered to detect IgM antibodies against the Hepatitis E virus to confirm recent or acute Hepatitis E infection. | D52: laboratory | E52: active | F52: http://loinc.org | G52: 14212-5 | H52: Hepatitis E virus IgM Ab [Presence] in Serum | I52: boolean | M52: http://snomed.info/sct | N52: 401242000 | O52: Hepatitis E immunoglobulin M level | P52: http://unitsofmeasure.org
A53: TPHA | B53: tpha-sn | C53: Detects antibodies against Treponema pallidum. Used for confirmation of syphilis infection. | D53: laboratory | E53: active | F53: http://loinc.org | G53: 11597-2 | H53: Treponema pallidum Ab [Units/volume] in Serum | I53: boolean | M53: http://snomed.info/sct | N53: 104334001 | O53: Treponema pallidum antibody confirmatory test | P53: http://unitsofmeasure.org | Q53: [IU]/mL | R53: international unit per milliliter
A54: IgM Hepatitis E - ELISA | B54: igm-hepatitis-e-elisa | C54: Detects IgM antibodies against Hepatitis E virus. Used to diagnose acute Hepatitis E infection. | D54: laboratory | E54: active | F54: http://loinc.org | G54: 14212-5 | H54: Hepatitis E virus IgM Ab [Presence] in Serum | I54: boolean | M54: http://snomed.info/sct | N54: 401242000 | O54: Hepatitis E immunoglobulin M level | P54: http://unitsofmeasure.org
A55: HBsAg (Quantitative) | B55: hbsag-quantitative | C55: Measures concentration of Hepatitis B surface antigen in serum. Used for disease monitoring and treatment response. | D55: laboratory | E55: active | F55: http://loinc.org | G55: 58452-4 | H55: Hepatitis B virus surface Ag [Units/volume] in Serum | I55: decimal | M55: http://snomed.info/sct | N55: 47758006 | O55: Hepatitis B surface antigen measurement | P55: http://unitsofmeasure.org | Q55: [IU]/mL | R55: international unit per milliliter
A56: HBsAg (Qualitative) | B56: hbsag-qualitative | C56: Detects presence of Hepatitis B surface antigen. Used for screening and diagnosis of Hepatitis B infection. | D56: laboratory | E56: active | F56: http://loinc.org | G56: 1203535 | H56: Hepatitis B virus surface Ag [Presence] in Serum | I56: boolean | M56: http://snomed.info/sct | N56: 47758006 | O56: Hepatitis B surface antigen measurement | P56: http://unitsofmeasure.org
A57: Cryptococcal IgM - Rapid | B57: cryptococcal-igm-rapid | C57: Detects presence of IgM antibodies against Cryptococcus. Used for screening and early diagnosis of Cryptococcosis | D57: laboratory | E57: active | F57: http://loinc.org | G57: 70910-5 | H57: Cryptococcus sp Ag [Presence] in Serum by Rapid immunoassay | I57: boolean | M57: http://snomed.info/sct | N57: 121980003 | O57: Cryptococcus species antigen assay (procedure) | P57: http://unitsofmeasure.org
A58: Viral load count for HCV | B58: viral-load-count-for-hcv | C58: Measures the amount of Hepatitis C virus RNA in the blood. | D58: laboratory | E58: active | F58: http://loinc.org | G58: 75886-2 | H58: HCV antibody screening - Meaningful Use set | I58: integer | M58: http://snomed.info/sct | N58: 187033005 | O58: Hepatitis C virus measurement (procedure) | P58: http://unitsofmeasure.org
A59: Viral load count for HBV | B59: viral-load-count-for-hbv | C59: Measures the amount of Hepatitis B virus DNA in the blood to assess viral activity. | D59: laboratory | E59: active | F59: http://loinc.org | G59: 31845-1 | H59: Hepatitis B virus e Ag [Units/volume] in Serum | I59: integer | M59: http://snomed.info/sct | N59: 62889000 | O59: Hepatitis B virus measurement (procedure) | P59: http://unitsofmeasure.org | Q59: [arb'U]/mL | R59: Arbitrary Units per Milliliter.
A60: Mycobacterium Tb culture | B60: mycobacterium-tb-culture | C60: Detects Mycobacterium tuberculosis or other mycobacteria in clinical samples and evaluates their susceptibility to anti-TB drugs. | D60: laboratory | E60: active | F60: http://loinc.org | G60: 543-9 | H60: Mycobacterium sp identified in Specimen by Organism specific culture | I60: boolean | M60: http://snomed.info/sct | N60: 4737000 | O60: Mycobacteria culture (procedure) | P60: http://unitsofmeasure.org
A61: Gram staining for Clinical specimen | B61: gram-staining-for-clinica | C61: Microscopic examination of a clinical specimen using Gram staining to detect and classify bacteria as Gram-positive or Gram-negative based on cell wall staining characteristics. | D61: laboratory | E61: active | F61: http://loinc.org | G61: 664-3 | H61: Microscopic observation [Identifier] in Specimen by Gram stain | I61: boolean | M61: http://snomed.info/sct | N61: 391245000 | O61: Gram stain microscopy (procedure | P61: http://unitsofmeasure.org
A62: AFB/ZN Stain for Extra pulmonary sample | B62: afbzn-stain-for-extra-pu | C62: Ziehl–Neelsen staining to detect acid-fast bacilli in non-sputum specimens. Used in extra-pulmonary tuberculosis diagnosis. | D62: laboratory | E62: active | F62: http://loinc.org | G62: 58944-0 | H62: Microscopic observation [Identifier] in Body fluid by Acid fast stain.Ziehl-Neelsen | I62: boolean | M62: http://snomed.info/sct | N62: 414788003 | O62: Mycobacterial microscopy (procedure) | P62: http://unitsofmeasure.org
A63: AFB examination -sputum | B63: afb-examination-sputum | C63: Microscopic examination to detect acid-fast bacilli, mainly used for diagnosing tuberculosis. | D63: laboratory | E63: active | F63: http://loinc.org | G63: 647-8 | H63: Microscopic observation [Identifier] in Sputum by Acid fast stain.Ziehl-Neelsen | I63: boolean | M63: http://snomed.info/sct | N63: 414788003 | O63: Mycobacterial microscopy (procedure) | P63: http://unitsofmeasure.org
A64: Albert stain for Corynebacterium diphtheria | B64: albert-stain-for-coryneba | C64: Special stain used to demonstrate metachromatic granules in Corynebacterium diphtheriae. | D64: laboratory | E64: active | F64: http://loinc.org | G64: 75222-0 | H64: Microscopic observation [Identifier] in Throat by Alberts stain | I64: boolean | M64: http://snomed.info/sct | N64: 608955007 | O64: Microscopic examination of bacterial smear of sputum specimen (procedure) | P64: http://unitsofmeasure.org
A65: Slit skin smear for Mycobacterium Leprae | B65: slit-skin-smear-for-mycob | C65: Detects acid-fast Mycobacterium leprae in skin or nasal smears to support the diagnosis of leprosy. | D65: laboratory | E65: active | F65: http://loinc.org | G65: 94542-8 | H65: Leprosy type | I65: integer | M65: http://snomed.info/sct | N65: 85558005 | O65: Skin test for leprosy (procedure) | P65: http://unitsofmeasure.org
A66: CBNAAT for TB | B66: cbnaat-for-tb | C66: Rapid molecular test that identifies Mycobacterium tuberculosis and detects rifampicin resistance directly from clinical samples | D66: laboratory | E66: active | F66: http://loinc.org | G66: 13956-8 | H66: Mycobacterium tuberculosis DNA [Presence] in Specimen by NAA with probe detection | I66: boolean | M66: http://snomed.info/sct | N66: 122384004 | O66: Mycobacterium tuberculosis deoxyribonucleic acid assay (procedure) | P66: http://unitsofmeasure.org
A67: Stool for hanging drop | B67: stool-for-hanging-drop | C67: A rapid microscopic test to detect motile Vibrio cholerae in fresh stool. | D67: laboratory | E67: active | F67: http://loinc.org | G67: 6470-9 | H67: Microscopic observation [Identifier] in Stool by Wet preparation | I67: boolean | M67: http://snomed.info/sct | N67: 88238009 | O67: Microbial smear, hanging drop technique (procedure) | P67: http://unitsofmeasure.org
A68: Other cultures -swab | B68: other-cultures-swab | C68: Used to detect and identify bacteria or fungi from infected sites to guide appropriate antimicrobial treatment. | D68: laboratory | E68: active | F68: http://loinc.org | G68: 11475-1 | H68: Microorganism identified in Specimen by Culture | I68: boolean | M68: http://snomed.info/sct | N68: 61594008 | O68: Microbial culture (procedure) | P68: http://unitsofmeasure.org
A69: Culture of stool specimen for Vibrio cholerae and other common bacterial enteropathogens | B69: culture-of-stool-specimen | C69: Identifies Vibrio cholerae and other bacteria causing diarrheal diseases through selective stool culture. | D69: laboratory | E69: active | F69: http://loinc.org | G69: 625-4 | H69: Bacteria identified in Stool by Culture | I69: boolean | M69: http://snomed.info/sct | N69: 122259000 | O69: Vibrio culture (procedure) | P69: http://unitsofmeasure.org
A70: Smear for STI/STD | B70: smear-for-stistd | C70: Ordered to detect infections related to reproductive tract or sexually transmitted diseases using microscopic examination. | D70: laboratory | E70: active | F70: http://loinc.org | G70: 48712-4 | H70: Microscopic observation [Identifier] in Genital specimen by Gram stain | I70: string | M70: http://snomed.info/sct | N70: 16314007 | O70: Microbial smear examination (procedure) | P70: http://unitsofmeasure.org
A71: Fungal Culture | B71: fungal-culture | C71: Detects and identifies fungal organisms from clinical specimens. | D71: laboratory | E71: active | F71: http://loinc.org | G71: 580-1 | H71: Fungus identified in Specimen by Culture | I71: boolean | M71: http://snomed.info/sct | N71: 121238005 | O71: Fungal blood culture (procedure) | P71: http://unitsofmeasure.org
A72: India ink for Cryptococcus | B72: india-ink-for-cryptococcu | C72: Direct microscopic examination using India ink to detect encapsulated Cryptococcus species. Commonly performed on cerebrospinal fluid in suspected cryptococcal meningitis. | D72: laboratory | E72: active | F72: http://loinc.org | G72: 1740779 | H72: Microscopic observation [Identifier] in Tissue by India ink prep | I72: boolean | M72: http://snomed.info/sct | N72: 395213003 | O72: Fungal microscopy (procedure) | P72: http://unitsofmeasure.org
A73: Pneumocystis jerovicii stain (PCP) | B73: pneumocystis-jerovicii-st | C73: Detects Pneumocystis jirovecii in clinical samples using special staining methods to diagnose Pneumocystis pneumonia (PCP) | D73: laboratory | E73: active | F73: http://loinc.org | G73: 10712-8 | H73: Pneumocystis sp identified in Lung tissue | I73: boolean | M73: http://snomed.info/sct | N73: 443069002 | O73: Pneumocystis jirovecii deoxyribonucleic acid assay (procedure) | P73: http://unitsofmeasure.org
A74: KOH for fungal elements (any sample) | B74: koh-for-fungal-elements-a | C74: Direct microscopic examination using potassium hydroxide to identify fungal hyphae or yeast in clinical specimens. | D74: laboratory | E74: active | F74: http://loinc.org | G74: 106049-0 | H74: Fungus [Presence] in Tissue by KOH preparation | I74: boolean | M74: http://snomed.info/sct | N74: 395213003 | O74: Fungal microscopy (procedure) | P74: http://unitsofmeasure.org
A75: Stool/Sputum for Paragonimus | B75: stoolsputum-for-paragoni | C75: Microscopic examination of stool or sputum for ova of Paragonimus species. Used in suspected paragonimiasis. | D75: laboratory | E75: active | F75: http://loinc.org | G75: 41421-9 | H75: Paragonimus sp Ab [Presence] in Serum by Immunoblot | I75: boolean | M75: http://snomed.info/sct | N75: 122064008 | O75: Measurement of Paragonimus species antibody (procedure) | P75: http://unitsofmeasure.org
A76: Modified ZN for Coccidian parasites | B76: modified-zn-for-coccidian | C76: Modified Ziehl–Neelsen staining to detect coccidian parasites such as Cryptosporidium, Cyclospora, and Isospora species. | D76: laboratory | E76: active | F76: http://loinc.org | G76: 10853-0 | H76: Isospora belli [Presence] in Specimen by Acid fast stain.Kinyoun modified | I76: boolean | M76: http://snomed.info/sct | N76: 122039005 | O76: Microscopic examination for parasites (procedure) | P76: http://unitsofmeasure.org
A77: Erythrocyte Sedimentation Rate (ESR) | B77: erythrocyte-sedimentation | C77: Measures how quickly red blood cells settle in a tube, reflecting inflammation in the body. | D77: laboratory | E77: active | F77: http://loinc.org | G77: 30341-2 | H77: Erythrocyte [Sedimentation Rate] in Blood | I77: integer | M77: http://snomed.info/sct | N77: 416838001 | O77: Erythrocyte sedimentation rate measurement (procedure) | P77: http://unitsofmeasure.org | Q77: mm/h | R77: millimeter per hour
A78: General blood picture | B78: general-blood-picture | C78: Microscopic examination of peripheral blood smear to assess red cells, white cells, and platelets. Used to identify morphological abnormalities. | D78: laboratory | E78: active | F78: http://loinc.org | G78: 58410-2 | H78: CBC panel - Blood by Automated count | I78: string | M78: http://snomed.info/sct | N78: 26604007 | O78: Complete blood count (procedure) | P78: http://unitsofmeasure.org
A79: Platelet morphology | B79: platelet-morphology | C79: Microscopic evaluation of platelet size, shape, and distribution to assess platelet abnormalities | D79: laboratory | E79: active | F79: http://loinc.org | G79: 11125-2 | H79: Platelet morphology finding [Identifier] in Blood | I79: string | M79: http://snomed.info/sct | N79: 73623007 | O79: Platelet morphology (procedure) | P79: http://unitsofmeasure.org
A80: Absolute eosinophil count | B80: absolute-eosinophil-count | C80: Measures the total number of eosinophils in the blood. | D80: laboratory | E80: active | F80: http://loinc.org | G80: 711-2 | H80: Eosinophils [#/volume] in Blood by Automated count | I80: integer | M80: http://snomed.info/sct | N80: 71960002 | O80: Eosinophil count (procedure) | P80: http://unitsofmeasure.org | Q80: {cells}/uL | R80: cell per micro liter
A81: Total Lymphocyte count | B81: total-lymphocyte-count | C81: Quantifies lymphocytes in peripheral blood. Used to assess immune status and hematological disorders. | D81: laboratory | E81: active | F81: http://loinc.org | G81: 731-0 | H81: Lymphocytes [#/volume] in Blood by Automated count | I81: integer | M81: http://snomed.info/sct | N81: 446325007 | O81: Total lymphocyte count (procedure) | P81: http://unitsofmeasure.org | Q81: {cells}/uL | R81: cells per microliter
A82: Total neutrophil count | B82: total-neutrophil-count | C82: Measures the number of neutrophils in the blood, helping assess immune response and detect infections or inflammatory conditions. | D82: laboratory | E82: active | F82: http://loinc.org | G82: 751-8 | H82: Neutrophils [#/volume] in Blood by Automated count | I82: integer | M82: http://snomed.info/sct | N82: 30630007 | O82: Enumeration of neutrophils in peripheral blood | P82: http://unitsofmeasure.org | Q82: /mm3 | R82: per cubic millimeter
A83: Reticulocyte count | B83: reticulocyte-count | C83: Measures the number or percent of immature red blood cells (reticulocytes) in the bloodstream. | D83: laboratory | E83: active | F83: http://loinc.org | G83: 14196-0 | H83: Reticulocytes [#/volume] in Blood | I83: decimal | M83: http://snomed.info/sct | N83: 45995003 | O83: Reticulocyte count (procedure) | P83: http://unitsofmeasure.org | Q83: % | R83: percent
A84: Blood for parasite-Malaria(slide) | B84: blood-for-parasite-malari | C84: Tests used to detect malaria parasites in the blood through microscopic examination or rapid antigen detection. | D84: laboratory | E84: active | F84: http://loinc.org | G84: 32206-5 | H84: Plasmodium sp identified in Blood by Light microscopy | I84: boolean | M84: http://snomed.info/sct | N84: 117023006 | O84: Thick film peripheral blood smear | P84: http://unitsofmeasure.org
A85: Rapid malaria test for Plasmodium sp. | B85: rapid-malaria-test-for-pl | C85: Tests used to detect malaria parasites in the blood through microscopic examination or rapid antigen detection. | D85: laboratory | E85: active | F85: http://loinc.org | G85: 70569-9 | H85: Plasmodium sp Ag [Identifier] in Blood by Rapid immunoassay | I85: boolean | M85: http://snomed.info/sct | N85: 391513009 | O85: Immunochromatographic malaria screening test (procedure) | P85: http://unitsofmeasure.org
A86: Rapid malaria test for PF | B86: rapid-malaria-test-for-pf | C86: Rapid antigen test to detect Plasmodium falciparum infection using immunochromatographic methods. | D86: laboratory | E86: active | F86: http://loinc.org | G86: 76772-3 | H86: Plasmodium falciparum Ag [Presence] in Blood by Rapid immunoassay | I86: boolean | M86: http://snomed.info/sct | N86: 391513009 | O86: Immunochromatographic malaria screening test (procedure) | P86: http://unitsofmeasure.org
A87: Rapid malaria test for PV | B87: rapid-malaria-test-for-pv | C87: Rapid antigen test to detect Plasmodium vivax infection using immunochromatographic methods. | D87: laboratory | E87: active | F87: http://loinc.org | G87: 70569-9 | H87: Plasmodium sp Ag [Identifier] in Blood by Rapid immunoassay | I87: boolean | M87: http://snomed.info/sct | N87: 391513009 | O87: Immunochromatographic malaria screening test (procedure) | P87: http://unitsofmeasure.org
A88: Blood for microfilaria | B88: blood-for-microfilaria | C88: Microscopic examination of a blood smear to detect microfilariae (filarial parasites). | D88: laboratory | E88: active | F88: http://loinc.org | G88: 10662-5 | H88: Filaria identified in Blood by Concentration | I88: boolean | M88: http://snomed.info/sct | N88: 121904005 | O88: Filaria identification | P88: http://unitsofmeasure.org
A89: Sickling Slide Test - Finger prick* | B89: sickling-slide-test-fin | C89: A rapid screening test used to detect the presence of Haemoglobin S (HbS). Helps quickly identify individuals with sickle cell trait or sickle cell disease. Positive results require confirmation with Hb electrophoresis or HPLC. | D89: laboratory | E89: active | F89: http://loinc.org | G89: 4621-9 | H89: Hemoglobin S [Presence] in Blood | I89: boolean | M89: http://snomed.info/sct | N89: 271510004 | O89: Hemoglobin S measurement (procedure) | P89: http://unitsofmeasure.org
A90: Sickling Slide Test - Venipuncture | B90: sickling-slide-test-ven | C90: Screens for the presence of sickle-shaped red blood cells caused by abnormal haemoglobin (HbS). Helps identify suspected sickle cell anaemia or sickle cell trait, and is often used as an initial screening test before confirmatory testing like Hb electrophoresis. | D90: laboratory | E90: active | F90: http://loinc.org | G90: 801-1 | H90: Sickle cells [Presence] in Blood by Light microscopy | I90: boolean | M90: http://snomed.info/sct | N90: 252289009 | O90: Sickling test | P90: http://unitsofmeasure.org
A91: Lupus Erythematosus cell | B91: lupus-erythematosus-cell | C91: Detects LE cells formed by phagocytosis of antibody-coated nuclear material. Historically used in systemic lupus erythematosus evaluation. | D91: laboratory | E91: active | F91: http://loinc.org | G91: 13507-9 | H91: Lupus erythematosus cells [Presence] in Blood | I91: boolean | M91: http://snomed.info/sct | N91: 37954002 | O91: Lupus erythematosus cell preparation (procedure) | P91: http://unitsofmeasure.org
A92: Coombs test direct with titre | B92: coombs-test-direct-with-t | C92: Detects antibodies or complement attached to the surface of red blood cells. | D92: laboratory | E92: active | F92: http://loinc.org | G92: 51006-5 | H92: Direct antiglobulin test.unspecified reagent [Presence] on Red Blood Cells | I92: boolean | M92: http://snomed.info/sct | N92: 77020008 | O92: Direct Coombs test | P92: http://unitsofmeasure.org | Q92: {titer} | R92: titer
A93: Coombs test indirect with titre | B93: coombs-test-indirect-with | C93: Detects free antibodies in the patient’s serum that may react with red blood cells. | D93: laboratory | E93: active | F93: http://loinc.org | G93: 56886-5 | H93: Indirect antiglobulin test.unspecified reagent [{titer}] in Serum or Plasma | I93: boolean | M93: http://snomed.info/sct | N93: 16742006 | O93: Indirect Coombs test | P93: http://unitsofmeasure.org | Q93: {titer} | R93: titer
A94: Bleeding time (Duke's method) | B94: bleeding-time-d | C94: Measures time required for bleeding to stop after a small skin puncture. | D94: laboratory | E94: active | F94: http://loinc.org | G94: 3178-1 | H94: Bleeding time by Duke method | I94: integer | M94: http://snomed.info/sct | N94: 26769008 | O94: Bleeding time, Duke | P94: http://unitsofmeasure.org | Q94: min | R94: minute
A95: Bleeding time (Ivy's method) | B95: bleeding-time-i | C95: Measures time required for bleeding to stop after a small skin puncture. | D95: laboratory | E95: active | F95: http://loinc.org | G95: 3179-9 | H95: Bleeding time by Ivy method | I95: integer | M95: http://snomed.info/sct | N95: 16132001 | O95: Bleeding time, Ivy | P95: http://unitsofmeasure.org | Q95: min | R95: minute
A96: Clotting time (Duke's method) | B96: clotting-time-d | C96: Measures time taken for blood clot formation. | D96: laboratory | E96: active | F96: http://loinc.org | G96: 81638-9 | H96: Clotting time of Capillary blood by Sukharev method | I96: integer | M96: http://snomed.info/sct | N96: 165566005 | O96: Whole blood clotting time procedure (procedure) | P96: http://unitsofmeasure.org | Q96: min | R96: minute
A97: Clotting time (Ivy's method) | B97: clotting-time-i | C97: Measures time taken for blood clot formation. | D97: laboratory | E97: active | F97: http://loinc.org | G97: 81638-9 | H97: Clotting time of Capillary blood by Sukharev method | I97: integer | M97: http://snomed.info/sct | N97: 165566005 | O97: Whole blood clotting time procedure (procedure) | P97: http://unitsofmeasure.org | Q97: min | R97: minute
A98: Coagulation Time | B98: coagulation-time | C98: Time taken for blood to clot under standard conditions. | D98: laboratory | E98: active | F98: http://loinc.org | G98: 3184-9 | H98: Clotting time of Capillary blood by Sukharev method | I98: integer | M98: http://snomed.info/sct | N98: 165566005 | O98: Whole blood clotting time procedure (procedure) | P98: http://unitsofmeasure.org | Q98: min | R98: minute
A99: Prothrombin Time (PT) | B99: prothrombin-time-pt | C99: ime taken for blood to clot via the extrinsic pathway. | D99: laboratory | E99: active | F99: http://loinc.org | G99: 5902-2 | H99: Prothrombin time (PT) | I99: integer | M99: http://snomed.info/sct | N99: 396451008 | O99: Prothrombin time | P99: http://unitsofmeasure.org | Q99: s | R99: second
A100: International Normalized Ratio (INR) | B100: international-normalized | C100: Standardized ratio of prothrombin time used to monitor blood coagulation. | D100: laboratory | E100: active | F100: http://loinc.org | G100: 6301-6 | H100: INR in Platelet poor plasma by Coagulation assay | I100: decimal | M100: http://snomed.info/sct | N100: 440685005 | O100: Calculation of international normalized ratio (procedure) | P100: http://unitsofmeasure.org
A101: Cytochemical stain of slides | B101: cytochemical-stain-of-sli | C101: Applies specific chemical stains on blood or marrow smears to identify cellular enzymes or constituents. Commonly used in leukemia classification. | D101: laboratory | E101: active | F101: http://loinc.org | G101: 74225-4 | H101: Cytochemical stains in Bone marrow Narrative | I101: boolean | M101: http://snomed.info/sct | N101: 52744009 | O101: Cytochemical test (procedure) | P101: http://unitsofmeasure.org
A102: Red Blood Cell Count (RBC) | B102: red-blood-cell-count-rbc | C102: The number of red blood cells present in a given volume of blood. | D102: laboratory | E102: active | F102: http://loinc.org | G102: 789-8 | H102: Erythrocytes [#/volume] in Blood by Automated count | I102: integer | M102: http://snomed.info/sct | N102: 14089001 | O102: Red blood cell count | P102: http://unitsofmeasure.org | Q102: {cells}/uL | R102: cells per microliter
A103: Bone marrow aspiration | B103: bone-marrow-aspiration | C103: Microscopic evaluation of bone marrow aspirate and/or biopsy to assess blood cell production, marrow cellularity, and detect hematological disorders. | D103: laboratory | E103: active | F103: http://loinc.org | G103: 48807-2 | H103: Bone marrow aspiration report | I103: string | M103: http://snomed.info/sct | N103: 167907006 | O103: Bone marrow examination | P103: http://unitsofmeasure.org
A104: Hemoglobin- Finger Prick | B104: hemoglobin-finger-prick | C104: Measures the concentration of hemoglobin in blood to assess anemia, polycythemia, and overall oxygen-carrying capacity. | D104: laboratory | E104: active | F104: http://loinc.org | G104: 718-7 | H104: Hemoglobin [Mass/volume] in Blood | I104: integer | M104: http://snomed.info/sct | N104: 271026005 | O104: Hb estimation procedure | P104: http://unitsofmeasure.org | Q104: g/dL | R104: gram per deciliter
A105: Hemoglobin- venipuncture | B105: hemoglobin-venipuncture | C105: Measures the concentration of hemoglobin in blood to assess anemia, polycythemia, and overall oxygen-carrying capacity. | D105: laboratory | E105: active | F105: http://loinc.org | G105: 718-7 | H105: Hemoglobin [Mass/volume] in Blood | I105: integer | M105: http://snomed.info/sct | N105: 271026005 | O105: Hb estimation procedure | P105: http://unitsofmeasure.org | Q105: g/dL | R105: gram per deciliter
A106: Packed Cell Volume (PCV) | B106: packed-cell-volume-pcv | C106: The percent of blood made up of red blood cells. | D106: laboratory | E106: active | F106: http://loinc.org | G106: 4544-3 | H106: Hematocrit [Volume Fraction] of Blood by Automated count | I106: decimal | M106: http://snomed.info/sct | N106: 28317006 | O106: Hematocrit determination | P106: http://unitsofmeasure.org | Q106: % | R106: percent
A107: Bone marrow trephine biopsy | B107: bone-marrow-trephine-biop | C107: Microscopic evaluation of bone marrow aspirate and/or biopsy to assess blood cell production, marrow cellularity, and detect hematological disorders. | D107: laboratory | E107: active | F107: http://loinc.org | G107: 33721-2 | H107: Bone marrow Pathology biopsy report | I107: string | M107: http://snomed.info/sct | N107: 167907006 | O107: Bone marrow examination | P107: http://unitsofmeasure.org
A108: Platelet count | B108: platelet-count | C108: Measures the number of platelets in the blood, which help in clotting. | D108: laboratory | E108: active | F108: http://loinc.org | G108: 777-3 | H108: Platelets [#/volume] in Blood by Automated count | I108: decimal | M108: http://snomed.info/sct | N108: 61928009 | O108: Platelet count (procedure) | P108: http://unitsofmeasure.org | Q108: {cells}/uL | R108: cells per microliter
A109: Differential leucocyte count (DLC) | B109: differential-leucocyte-co | C109: Breaks down the different types of white blood cells present in the blood. | D109: laboratory | E109: active | F109: http://loinc.org | G109: 57021-8 | H109: CBC W Auto Differential panel - Blood | I109: decimal | M109: http://snomed.info/sct | N109: 165511009 | O109: Differential white cell count estimation procedure | P109: http://unitsofmeasure.org | Q109: % | R109: percent
A110: DLC Neutrophil | B110: dlc-neutrophil | C110: Measures the percentage of neutrophils among total white blood cells in blood. It helps assess bacterial infections, inflammation, and overall immune response. | D110: laboratory | E110: active | F110: http://loinc.org | G110: 770-8 | H110: Neutrophils/Leukocytes in Blood by Automated count | I110: integer | M110: http://snomed.info/sct | N110: 30630007 | O110: Neutrophil count (procedure) | P110: http://unitsofmeasure.org | Q110: % | R110: percent
A111: DLC Lymphocyte | B111: dlc-lymphocyte | C111: Measures the percentage of lymphocytes among total white blood cells as part of the differential leukocyte count (DLC). | D111: laboratory | E111: active | F111: http://loinc.org | G111: 736-9 | H111: Lymphocytes/Leukocytes in Blood by Automated count | I111: decimal | M111: http://snomed.info/sct | N111: 271036002 | O111: Lymphocyte percent differential coun | P111: http://unitsofmeasure.org | Q111: % | R111: percent
A112: DLC Monocyte | B112: dlc-monocyte | C112: Measures the percentage of monocytes among total white blood cells in the blood, used to assess immune and inflammatory conditions. | D112: laboratory | E112: active | F112: http://loinc.org | G112: 26485-3 | H112: Monocytes/Leukocytes in Blood | I112: decimal | M112: http://snomed.info/sct | N112: 271037006 | O112: Monocyte percent differential count (procedure) | P112: http://unitsofmeasure.org | Q112: % | R112: percent
...

Sheet observation_components
A1: observation_slug | B1: code_system | C1: code_value | D1: code_display | E1: permitted_data_type | F1: unit_system | G1: unit_code | H1: unit_display | I1: age_min | J1: age_max | K1: age_op | L1: gender | M1: range_display | N1: range_min | O1: range_max
A2: random-blood-sugar-rbs | B2: http://loinc.org | C2: 74774-1 | D2: Glucose [Mass/volume] in Serum, Plasma or Blood | E2: integer | F2: http://unitsofmeasure.org | G2: mg/dL | H2: milligram per deciliter | M2: low | O2: 0
A3: random-blood-sugar-rbs | B3: http://loinc.org | C3: 74774-1 | D3: Glucose [Mass/volume] in Serum, Plasma or Blood | E3: integer | F3: http://unitsofmeasure.org | G3: mg/dL | H3: milligram per deciliter | M3: normal | N3: 0 | O3: 200
A4: random-blood-sugar-rbs | B4: http://loinc.org | C4: 74774-1 | D4: Glucose [Mass/volume] in Serum, Plasma or Blood | E4: integer | F4: http://unitsofmeasure.org | G4: mg/dL | H4: milligram per deciliter | M4: high | N4: 200
A5: fasting-blood-sugar-fbs | B5: http://loinc.org | C5: 1557-8 | D5: Fasting Blood Sugar (FBS) | E5: integer | F5: http://unitsofmeasure.org | G5: mg/dL | H5: milligram per deciliter | M5: low | O5: 70
A6: fasting-blood-sugar-fbs | B6: http://loinc.org | C6: 1557-8 | D6: Fasting Blood Sugar (FBS) | E6: integer | F6: http://unitsofmeasure.org | G6: mg/dL | H6: milligram per deciliter | M6: normal | N6: 70 | O6: 110
A7: fasting-blood-sugar-fbs | B7: http://loinc.org | C7: 1557-8 | D7: Fasting Blood Sugar (FBS) | E7: integer | F7: http://unitsofmeasure.org | G7: mg/dL | H7: milligram per deciliter | M7: high | N7: 110
A8: post-prandial-blood-sugar | B8: http://loinc.org | C8: 87422-2 | D8: Post Prandial Blood Sugar (PPBS) | E8: integer | F8: http://unitsofmeasure.org | G8: mg/dL | H8: milligram per deciliter | M8: low | O8: 0
A9: post-prandial-blood-sugar | B9: http://loinc.org | C9: 87422-2 | D9: Post Prandial Blood Sugar (PPBS) | E9: integer | F9: http://unitsofmeasure.org | G9: mg/dL | H9: milligram per deciliter | M9: normal | N9: 0 | O9: 200
A10: post-prandial-blood-sugar | B10: http://loinc.org | C10: 87422-2 | D10: Post Prandial Blood Sugar (PPBS) | E10: integer | F10: http://unitsofmeasure.org | G10: mg/dL | H10: milligram per deciliter | M10: high | N10: 200
A11: glucose-tolerance-test-gt | B11: http://loinc.org | C11: 21004-7 | D11: Glucose Tolerance test (GTT) fasting | E11: integer | F11: http://unitsofmeasure.org | G11: mg/dL | H11: milligram per deciliter | M11: low | O11: 0
A12: glucose-tolerance-test-gt | B12: http://loinc.org | C12: 21004-7 | D12: Glucose Tolerance test (GTT) fasting | E12: integer | F12: http://unitsofmeasure.org | G12: mg/dL | H12: milligram per deciliter | M12: normal | N12: 0 | O12: 100
A13: glucose-tolerance-test-gt | B13: http://loinc.org | C13: 21004-7 | D13: Glucose Tolerance test (GTT) fasting | E13: integer | F13: http://unitsofmeasure.org | G13: mg/dL | H13: milligram per deciliter | M13: high | N13: 100
A14: glucose-tolerance-test-th | B14: http://loinc.org | C14: 21004-7 | D14: Glucose Tolerance test (GTT)-2hrs | E14: integer | F14: http://unitsofmeasure.org | G14: mg/dL | H14: milligram per deciliter | M14: low | O14: 0
A15: glucose-tolerance-test-th | B15: http://loinc.org | C15: 21004-7 | D15: Glucose Tolerance test (GTT)-2hrs | E15: integer | F15: http://unitsofmeasure.org | G15: mg/dL | H15: milligram per deciliter | M15: normal | N15: 0 | O15: 140
A16: glucose-tolerance-test-th | B16: http://loinc.org | C16: 21004-7 | D16: Glucose Tolerance test (GTT)-2hrs | E16: integer | F16: http://unitsofmeasure.org | G16: mg/dL | H16: milligram per deciliter | M16: high | N16: 140
A17: serum-uric-acid | B17: http://loinc.org | C17: 3084-1 | D17: Serum Uric acid | E17: decimal | F17: http://unitsofmeasure.org | G17: mg/dL | H17: milligram per deciliter | M17: low | O17: 2.5
A18: serum-uric-acid | B18: http://loinc.org | C18: 3084-1 | D18: Serum Uric acid | E18: decimal | F18: http://unitsofmeasure.org | G18: mg/dL | H18: milligram per deciliter | M18: normal | N18: 2.5 | O18: 7.5
A19: serum-uric-acid | B19: http://loinc.org | C19: 3084-1 | D19: Serum Uric acid | E19: decimal | F19: http://unitsofmeasure.org | G19: mg/dL | H19: milligram per deciliter | M19: high | N19: 7.5
A20: serum-calcium | B20: http://loinc.org | C20: 17861-6 | D20: Serum Calcium | E20: decimal | F20: http://unitsofmeasure.org | G20: mg/dL | H20: milligram per deciliter | M20: low | O20: 8.4
A21: serum-calcium | B21: http://loinc.org | C21: 17861-6 | D21: Serum Calcium | E21: decimal | F21: http://unitsofmeasure.org | G21: mg/dL | H21: milligram per deciliter | M21: normal | N21: 8.4 | O21: 10.2
A22: serum-calcium | B22: http://loinc.org | C22: 17861-6 | D22: Serum Calcium | E22: decimal | F22: http://unitsofmeasure.org | G22: mg/dL | H22: milligram per deciliter | M22: high | N22: 10.2
A23: serum-amylase | B23: http://loinc.org | C23: 1798-8 | D23: Serum Amylase | E23: integer | F23: http://unitsofmeasure.org | G23: U/L | H23: enzyme unit per liter | M23: low | O23: 30
A24: serum-amylase | B24: http://loinc.org | C24: 1798-8 | D24: Serum Amylase | E24: integer | F24: http://unitsofmeasure.org | G24: U/L | H24: enzyme unit per liter | M24: normal | N24: 30 | O24: 110
A25: serum-amylase | B25: http://loinc.org | C25: 1798-8 | D25: Serum Amylase | E25: integer | F25: http://unitsofmeasure.org | G25: U/L | H25: enzyme unit per liter | M25: high | N25: 110
A26: serum-lipase | B26: http://loinc.org | C26: 3040-3 | D26: Serum Lipase | E26: integer | F26: http://unitsofmeasure.org | G26: U/L | H26: enzyme unit per liter | M26: low | O26: 10
A27: serum-lipase | B27: http://loinc.org | C27: 3040-3 | D27: Serum Lipase | E27: integer | F27: http://unitsofmeasure.org | G27: U/L | H27: enzyme unit per liter | M27: normal | N27: 10 | O27: 140
A28: serum-lipase | B28: http://loinc.org | C28: 3040-3 | D28: Serum Lipase | E28: integer | F28: http://unitsofmeasure.org | G28: U/L | H28: enzyme unit per liter | M28: high | N28: 140
A29: serum-ldh | B29: http://loinc.org | C29: 14804-9 | D29: Serum LDH | E29: integer | F29: http://unitsofmeasure.org | G29: U/L | H29: enzyme unit per liter | M29: low | O29: 140
A30: serum-ldh | B30: http://loinc.org | C30: 14804-9 | D30: Serum LDH | E30: integer | F30: http://unitsofmeasure.org | G30: U/L | H30: enzyme unit per liter | M30: normal | N30: 140 | O30: 280
A31: serum-ldh | B31: http://loinc.org | C31: 14804-9 | D31: Serum LDH | E31: integer | F31: http://unitsofmeasure.org | G31: U/L | H31: enzyme unit per liter | M31: high | N31: 280
A32: serum-phosphorus | B32: http://loinc.org | C32: 2777-1 | D32: Serum Phosphorus | E32: decimal | F32: http://unitsofmeasure.org | G32: mg/dL | H32: milligram per deciliter | M32: low | O32: 2.5
A33: serum-phosphorus | B33: http://loinc.org | C33: 2777-1 | D33: Serum Phosphorus | E33: decimal | F33: http://unitsofmeasure.org | G33: mg/dL | H33: milligram per deciliter | M33: normal | N33: 2.5 | O33: 4.5
A34: serum-phosphorus | B34: http://loinc.org | C34: 2777-1 | D34: Serum Phosphorus | E34: decimal | F34: http://unitsofmeasure.org | G34: mg/dL | H34: milligram per deciliter | M34: high | N34: 4.5
A35: serum-bicarbonate | B35: http://loinc.org | C35: 1963-8 | D35: Serum Bicarbonate | E35: integer | F35: http://unitsofmeasure.org | G35: mmol/L | H35: millimole per liter | M35: low | O35: 20
A36: serum-bicarbonate | B36: http://loinc.org | C36: 1963-8 | D36: Serum Bicarbonate | E36: integer | F36: http://unitsofmeasure.org | G36: mmol/L | H36: millimole per liter | M36: normal | N36: 20 | O36: 30
A37: serum-bicarbonate | B37: http://loinc.org | C37: 1963-8 | D37: Serum Bicarbonate | E37: integer | F37: http://unitsofmeasure.org | G37: mmol/L | H37: millimole per liter | M37: high | N37: 30
A38: blood-urea | B38: http://loinc.org | C38: 20977-5 | D38: Blood Urea | E38: integer | F38: http://unitsofmeasure.org | G38: mg/dL | H38: milligram per deciliter | M38: low | O38: 15
A39: blood-urea | B39: http://loinc.org | C39: 20977-5 | D39: Blood Urea | E39: integer | F39: http://unitsofmeasure.org | G39: mg/dL | H39: milligram per deciliter | M39: normal | N39: 15 | O39: 45
A40: blood-urea | B40: http://loinc.org | C40: 20977-5 | D40: Blood Urea | E40: integer | F40: http://unitsofmeasure.org | G40: mg/dL | H40: milligram per deciliter | M40: high | N40: 45
A41: serum-creatinine | B41: http://loinc.org | C41: 2160-0 | D41: Serum Creatinine | E41: decimal | F41: http://unitsofmeasure.org | G41: mg/dL | H41: milligram per deciliter | L41: male | M41: low | O41: 0.6
A42: serum-creatinine | B42: http://loinc.org | C42: 2160-0 | D42: Serum Creatinine | E42: decimal | F42: http://unitsofmeasure.org | G42: mg/dL | H42: milligram per deciliter | L42: male | M42: normal | N42: 0.6 | O42: 1.2
A43: serum-creatinine | B43: http://loinc.org | C43: 2160-0 | D43: Serum Creatinine | E43: decimal | F43: http://unitsofmeasure.org | G43: mg/dL | H43: milligram per deciliter | L43: male | M43: high | N43: 1.2
A44: serum-creatinine | B44: http://loinc.org | C44: 2160-0 | D44: Serum Creatinine | E44: decimal | F44: http://unitsofmeasure.org | G44: mg/dL | H44: milligram per deciliter | L44: female | M44: low | O44: 0.5
A45: serum-creatinine | B45: http://loinc.org | C45: 2160-0 | D45: Serum Creatinine | E45: decimal | F45: http://unitsofmeasure.org | G45: mg/dL | H45: milligram per deciliter | L45: female | M45: normal | N45: 0.5 | O45: 0.9
A46: serum-creatinine | B46: http://loinc.org | C46: 2160-0 | D46: Serum Creatinine | E46: decimal | F46: http://unitsofmeasure.org | G46: mg/dL | H46: milligram per deciliter | L46: female | M46: high | N46: 0.9
A47: serum-total-protein | B47: http://loinc.org | C47: 2885-2 | D47: Serum Total Protein | E47: decimal | F47: http://unitsofmeasure.org | G47: mg/dL | H47: milligram per deciliter | M47: low | O47: 6.3
A48: serum-total-protein | B48: http://loinc.org | C48: 2885-2 | D48: Serum Total Protein | E48: decimal | F48: http://unitsofmeasure.org | G48: mg/dL | H48: milligram per deciliter | M48: normal | N48: 6.3 | O48: 8.2
A49: serum-total-protein | B49: http://loinc.org | C49: 2885-2 | D49: Serum Total Protein | E49: decimal | F49: http://unitsofmeasure.org | G49: mg/dL | H49: milligram per deciliter | M49: high | N49: 8.2
A50: serum-albumin | B50: http://loinc.org | C50: 1751-7 | D50: Serum Albumin | E50: decimal | F50: http://unitsofmeasure.org | G50: mg/dL | H50: milligram per deciliter | M50: low | O50: 3.5
A51: serum-albumin | B51: http://loinc.org | C51: 1751-7 | D51: Serum Albumin | E51: decimal | F51: http://unitsofmeasure.org | G51: mg/dL | H51: milligram per deciliter | M51: normal | N51: 3.5 | O51: 5
A52: serum-albumin | B52: http://loinc.org | C52: 1751-7 | D52: Serum Albumin | E52: decimal | F52: http://unitsofmeasure.org | G52: mg/dL | H52: milligram per deciliter | M52: high | N52: 5
A53: s-tsh-test | B53: http://loinc.org | C53: 3016-3 | D53: S.TSH | E53: decimal | F53: http://unitsofmeasure.org | G53: ug/mL | H53: microgram per milliliter | M53: low | O53: 0.2
A54: s-tsh-test | B54: http://loinc.org | C54: 3016-3 | D54: S.TSH | E54: decimal | F54: http://unitsofmeasure.org | G54: ug/mL | H54: microgram per milliliter | M54: normal | N54: 0.2 | O54: 4.2
A55: s-tsh-test | B55: http://loinc.org | C55: 3016-3 | D55: S.TSH | E55: decimal | F55: http://unitsofmeasure.org | G55: ug/mL | H55: microgram per milliliter | M55: high | N55: 4.2
A56: s-trio-sn | B56: http://loinc.org | C56: 3053-6 | D56: S.T3 | E56: decimal | F56: http://unitsofmeasure.org | G56: ng/mL | H56: nanograms per milliliter | M56: low | O56: 0.75
A57: s-trio-sn | B57: http://loinc.org | C57: 3053-6 | D57: S.T3 | E57: decimal | F57: http://unitsofmeasure.org | G57: ng/mL | H57: nanograms per milliliter | M57: normal | N57: 0.75 | O57: 2.1
A58: s-trio-sn | B58: http://loinc.org | C58: 3053-6 | D58: S.T3 | E58: decimal | F58: http://unitsofmeasure.org | G58: ng/mL | H58: nanograms per milliliter | M58: high | N58: 2.1
A59: s-thy-sn | B59: http://loinc.org | C59: 3026-2 | D59: S.T4 | E59: integer | F59: http://unitsofmeasure.org | G59: ug/dL | H59: micrograms per deciliter | M59: low | O59: 5
A60: s-thy-sn | B60: http://loinc.org | C60: 3026-2 | D60: S.T4 | E60: integer | F60: http://unitsofmeasure.org | G60: ug/dL | H60: micrograms per deciliter | M60: normal | N60: 5 | O60: 13
A61: s-thy-sn | B61: http://loinc.org | C61: 3026-2 | D61: S.T4 | E61: integer | F61: http://unitsofmeasure.org | G61: ug/dL | H61: micrograms per deciliter | M61: high | N61: 13
A62: troponin-i | B62: http://loinc.org | C62: 10839-9 | D62: Troponin - I | E62: decimal | F62: http://unitsofmeasure.org | G62: ng/mL | H62: nanograms per milliliter | M62: low | O62: 0
A63: troponin-i | B63: http://loinc.org | C63: 10839-9 | D63: Troponin - I | E63: decimal | F63: http://unitsofmeasure.org | G63: ng/mL | H63: nanograms per milliliter | M63: normal | N63: 0 | O63: 0.3
A64: troponin-i | B64: http://loinc.org | C64: 10839-9 | D64: Troponin - I | E64: decimal | F64: http://unitsofmeasure.org | G64: ng/mL | H64: nanograms per milliliter | M64: high | N64: 0.3
A65: serum-hbsag | B65: http://loinc.org | C65: 5195-3 | D65: Serum HBsAg | E65: boolean | F65: http://unitsofmeasure.org
A66: hcv-antibody-test-anti-hc1 | B66: http://loinc.org | C66: 16128-1 | D66: HCV Antibody Test (Anti HCV) | E66: boolean | F66: http://unitsofmeasure.org
A67: hepatitis-a-virus-ab-hav | B67: http://loinc.org | C67: 22314-9 | D67: Hepatitis A virus Ab (HAV)-Rapid | E67: boolean | F67: http://unitsofmeasure.org
A68: hepatitis-e-ab-hev-rapid | B68: http://loinc.org | C68: 14212-5 | D68: Hepatitis E Ab (HEV)-Rapid | E68: boolean | F68: http://unitsofmeasure.org
A69: widal-test | B69: http://loinc.org | C69: 98211-6 | D69: Widal test | E69: string | F69: http://unitsofmeasure.org
A70: widal-test | B70: http://loinc.org | C70: 98211-6 | D70: Widal test | E70: string | F70: http://unitsofmeasure.org
A71: widal-test | B71: http://loinc.org | C71: 98211-6 | D71: Widal test | E71: string | F71: http://unitsofmeasure.org
A72: aso-titer | B72: http://loinc.org | C72: 5370-2 | D72: ASO {titer} | E72: integer | F72: http://unitsofmeasure.org | G72: [IU]/mL | H72: international unit per milliliter | M72: low | O72: 0
A73: aso-titer | B73: http://loinc.org | C73: 5370-2 | D73: ASO {titer} | E73: integer | F73: http://unitsofmeasure.org | G73: [IU]/mL | H73: international unit per milliliter | M73: normal | N73: 200 | O73: 400
A74: aso-titer | B74: http://loinc.org | C74: 5370-2 | D74: ASO {titer} | E74: integer | F74: http://unitsofmeasure.org | G74: [IU]/mL | H74: international unit per milliliter | M74: high | N74: 400
A75: ra-factor-quantitative | B75: http://loinc.org | C75: 11572-5 | D75: RA factor (Quantitative) | E75: integer | F75: http://unitsofmeasure.org | G75: [IU]/mL | H75: international unit per milliliter | M75: low | O75: 14
A76: ra-factor-quantitative | B76: http://loinc.org | C76: 11572-5 | D76: RA factor (Quantitative) | E76: integer | F76: http://unitsofmeasure.org | G76: [IU]/mL | H76: international unit per milliliter | M76: normal | N76: 14 | O76: 60
A77: ra-factor-quantitative | B77: http://loinc.org | C77: 11572-5 | D77: RA factor (Quantitative) | E77: integer | F77: http://unitsofmeasure.org | G77: [IU]/mL | H77: international unit per milliliter | M77: high | N77: 60
A78: crp-including-new-born | B78: http://loinc.org | C78: 30522-7 | D78: CRP (including new born) | E78: integer | F78: http://unitsofmeasure.org | G78: mg/L | H78: milligram per deciliter | M78: low | O78: 6
A79: crp-including-new-born | B79: http://loinc.org | C79: 30522-7 | D79: CRP (including new born) | E79: integer | F79: http://unitsofmeasure.org | G79: mg/L | H79: milligram per deciliter | M79: normal | N79: 6 | O79: 100
A80: crp-including-new-born | B80: http://loinc.org | C80: 30522-7 | D80: CRP (including new born) | E80: integer | F80: http://unitsofmeasure.org | G80: mg/L | H80: milligram per deciliter | M80: high | N80: 100
A81: rprvdrl-test-for-syphili | B81: http://loinc.org | C81: 20507-0 | D81: RPR/VDRL test for Syphilis | E81: string | F81: http://unitsofmeasure.org
A82: rprvdrl-test-for-syphili | B82: http://loinc.org | C82: 20507-0 | D82: RPR/VDRL test for Syphilis | E82: string | F82: http://unitsofmeasure.org
A83: rprvdrl-test-for-syphili | B83: http://loinc.org | C83: 20507-0 | D83: RPR/VDRL test for Syphilis | E83: string | F83: http://unitsofmeasure.org
A84: elisa-ana | B84: http://loinc.org | C84: 47383-5 | D84: ELISA ANA | E84: string | F84: http://unitsofmeasure.org | M84: low | O84: 1
A85: elisa-ana | B85: http://loinc.org | C85: 47383-5 | D85: ELISA ANA | E85: string | F85: http://unitsofmeasure.org | M85: normal | N85: 1 | O85: 1.5
A86: elisa-ana | B86: http://loinc.org | C86: 47383-5 | D86: ELISA ANA | E86: string | F86: http://unitsofmeasure.org | M86: high | N86: 1.5
A87: dengue-test | B87: http://loinc.org | C87: 104595-4 | D87: Dengue Test | E87: boolean | F87: http://unitsofmeasure.org
A88: test-for-dengue-elisa | B88: http://loinc.org | C88: 104595-4 | D88: Test for Dengue ELISA | E88: boolean | F88: http://unitsofmeasure.org
A89: sars-cov-19-pcr-test | B89: http://loinc.org | C89: 96895-8 | D89: SARS COV-19 PCR test | E89: boolean | F89: http://unitsofmeasure.org
A90: scrub-typhus-test-elisa | B90: http://loinc.org | C90: 33897-0 | D90: Scrub typhus Test - ELISA | E90: boolean | F90: http://unitsofmeasure.org
A91: respiratory-panels-rt-pcr | B91: http://loinc.org | C91: 92143-7 | D91: Respiratory Panels (RT PCR) | E91: boolean | F91: http://unitsofmeasure.org
A92: typhoid-igm | B92: http://loinc.org | C92: 9674-3 | D92: Typhoid IgM | E92: boolean | F92: http://unitsofmeasure.org
A93: influenza-a-and-b-virus-w | B93: http://loinc.org | C93: 81233-9 | D93: Influenza A and B virus with subtypes | E93: boolean | F93: http://unitsofmeasure.org
A94: respiratory-syncytial | B94: http://loinc.org | C94: 72885-7 | D94: Respiratory Syncytial Virus (RSV) A and B | E94: boolean | F94: http://unitsofmeasure.org
A95: human-meta-pneumo-virus | B95: http://loinc.org | C95: 92134-6 | D95: Human Meta Pneumo Virus (HMPV) | E95: boolean | F95: http://unitsofmeasure.org
A96: para-influenza-virus-1-to | B96: http://loinc.org | C96: 88890-9 | D96: Para influenza virus 1 to 4 | E96: boolean | F96: http://unitsofmeasure.org
A97: hpv-pcr-test | B97: http://loinc.org | C97: 6516-9 | D97: HPV PCR test | E97: boolean | F97: http://unitsofmeasure.org
A98: herpes-simplex-virus-hsv | B98: http://loinc.org | C98: 81621-5 | D98: Herpes Simplex Virus (HSV) 1 and 2 ELISA | E98: boolean | F98: http://unitsofmeasure.org
... A102: hiv-test-antibodies-1-and | B102: http://loinc.org | C102: 85037-0 | D102: HIV test (Antibodies 1 and 2) | E102: boolean | F102: http://unitsofmeasure.org
A103: cd4-count | B103: http://loinc.org | C103: 24467-3 | D103: CD4 count | E103: integer | F103: http://unitsofmeasure.org | G103: {cells}/uL | H103: cells per microliter | M103: low | O103: 200
...

Sheet all_charge_item_definition
A1: title | D1: slug_value | E1: description | F1: purpose | G1: price | H1: category
A2: Random Blood Sugar (RBS) | B2: =IF(A2=all_activity_definition!A2,"🟢Match","🔴Mismatch") -> 🟢Match | C2: =IFERROR( IF(ROW()=MATCH(A2,all_activity_definition!A:A,0), "🟢 A"&ROW()&" = A"&MATCH(A2,all_activity_definition!A:A,0), "🔴 A"&ROW()&" = A"&MATCH(A2,all_activity_definition!A:A,0) ), "No Match" ) -> 🟢 A2 = A2 | D2: rbs-charge | E2: Measures the level of glucose in the blood. | F2: Used for diabetes screening. | G2: 0 | H2: Biochemistry
A3: Fasting Blood Sugar (FBS) | B3: =IF(A3=all_activity_definition!A3,"🟢Match","🔴Mismatch") -> 🟢Match | C3: =IFERROR( IF(ROW()=MATCH(A3,all_activity_definition!A:A,0), "🟢 A"&ROW()&" = A"&MATCH(A3,all_activity_definition!A:A,0), "🔴 A"&ROW()&" = A"&MATCH(A3,all_activity_definition!A:A,0) ), "No Match" ) -> 🟢 A3 = A3 | D3: fbs-charge | E3: Measures the level of glucose in the blood in the fasting state | F3: Used to diagnose diabetes mellitus. | G3: 0 | H3: Biochemistry
A4: Post Prandial Blood Sugar (PPBS) | B4: =IF(A4=all_activity_definition!A4,"🟢Match","🔴Mismatch") -> 🟢Match | C4: =IFERROR( IF(ROW()=MATCH(A4,all_activity_definition!A:A,0), "🟢 A"&ROW()&" = A"&MATCH(A4,all_activity_definition!A:A,0), "🔴 A"&ROW()&" = A"&MATCH(A4,all_activity_definition!A:A,0) ), "No Match" ) -> 🟢 A4 = A4 | D4: ppbs-charge | E4: Measures the level of glucose in the blood after a meal, used to assess how the body processes sugar and to monitor diabetes control | F4: Used to monitor diabetes control. | G4: 0 | H4: Biochemistry
A5: Glucose Tolerance test (GTT) | B5: =IF(A5=all_activity_definition!A5,"🟢Match","🔴Mismatch") -> 🟢Match | C5: =IFERROR( IF(ROW()=MATCH(A5,all_activity_definition!A:A,0), "🟢 A"&ROW()&" = A"&MATCH(A5,all_activity_definition!A:A,0), "🔴 A"&ROW()&" = A"&MATCH(A5,all_activity_definition!A:A,0) ), "No Match" ) -> 🟢 A5 = A5 | D5: gtt-charge | E5: Ordered to assess how the body processes glucose and to help diagnose diabetes or gestational diabetes. | F5: Used to diagnose diabetes mellitus. | G5: 0 | H5: Biochemistry
A6: Liver function Test (LFT) | B6: =IF(A6=all_activity_definition!A6,"🟢Match","🔴Mismatch") -> 🟢Match | C6: =IFERROR( IF(ROW()=MATCH(A6,all_activity_definition!A:A,0), "🟢 A"&ROW()&" = A"&MATCH(A6,all_activity_definition!A:A,0), "🔴 A"&ROW()&" = A"&MATCH(A6,all_activity_definition!A:A,0) ), "No Match" ) -> 🟢 A6 = A6 | D6: lft-charge | E6: A panel of tests measuring enzymes, bilirubin, and proteins produced by the liver. | F6: A panel of tests measuring enzymes, bilirubin, and proteins produced by the liver. | G6: 0 | H6: Biochemistry
A7: Total serum bilirubin (TSB) | B7: =IF(A7=all_activity_definition!A7,"🟢Match","🔴Mismatch") -> 🟢Match | C7: =IFERROR( IF(ROW()=MATCH(A7,all_activity_definition!A:A,0), "🟢 A"&ROW()&" = A"&MATCH(A7,all_activity_definition!A:A,0), "🔴 A"&ROW()&" = A"&MATCH(A7,all_activity_definition!A:A,0) ), "No Match" ) -> 🟢 A7 = A7 | D7: tsb-charge | E7: Measurement of total serum bilirubin to assess liver function and hemolytic conditions. | F7: Used for evaluation of jaundice, hepatobiliary disorders, and neonatal hyperbilirubinemia. | G7: 0 | H7: Biochemistry
A8: Serum Glutamic Pyruvic Transaminase (SGPT)/ Alanine Aminotransferase (ALT) | B8: =IF(A8=all_activity_definition!A8,"🟢Match","🔴Mismatch") -> 🟢Match | C8: =IFERROR( IF(ROW()=MATCH(A8,all_activity_definition!A:A,0), "🟢 A"&ROW()&" = A"&MATCH(A8,all_activity_definition!A:A,0), "🔴 A"&ROW()&" = A"&MATCH(A8,all_activity_definition!A:A,0) ), "No Match" ) -> 🟢 A8 = A8 | D8: sgpt-charge | E8: Measures alanine aminotransferase, an enzyme released when liver cells are damaged. | F8: Used to detect liver injury. | G8: 0 | H8: Biochemistry
A9: Kidney Function Test (KFT) | B9: =IF(A9=all_activity_definition!A9,"🟢Match","🔴Mismatch") -> 🟢Match | C9: =IFERROR( IF(ROW()=MATCH(A9,all_activity_definition!A:A,0), "🟢 A"&ROW()&" = A"&MATCH(A9,all_activity_definition!A:A,0), "🔴 A"&ROW()&" = A"&MATCH(A9,all_activity_definition!A:A,0) ), "No Match" ) -> 🟢 A9 = A9 | D9: kft-charge | E9: Kidney Function Test panel measuring urea, creatinine and electrolytes to evaluate renal function. | F9: Used to assess renal function, monitor chronic kidney disease, and evaluate electrolyte balance. | G9: 0 | H9: Biochemistry
A10: Serum Electrolyte | B10: =IF(A10=all_activity_definition!A10,"🟢Match","🔴Mismatch") -> 🟢Match | C10: =IFERROR( IF(ROW()=MATCH(A10,all_activity_definition!A:A,0), "🟢 A"&ROW()&" = A"&MATCH(A10,all_activity_definition!A:A,0), "🔴 A"&ROW()&" = A"&MATCH(A10,all_activity_definition!A:A,0) ), "No Match" ) -> 🟢 A10 = A10 | D10: se-charge | E10: Quantitative measurement of sodium, potassium and chloride in serum. | F10: Used to evaluate electrolyte imbalance, dehydration, and acid-base disorders. | G10: 0 | H10: Biochemistry
A11: Lipid profile | B11: =IF(A11=all_activity_definition!A11,"🟢Match","🔴Mismatch") -> 🟢Match | C11: =IFERROR( IF(ROW()=MATCH(A11,all_activity_definition!A:A,0), "🟢 A"&ROW()&" = A"&MATCH(A11,all_activity_definition!A:A,0), "🔴 A"&ROW()&" = A"&MATCH(A11,all_activity_definition!A:A,0) ), "No Match" ) -> 🟢 A11 = A11 | D11: lipid-charge | E11: Measures cholesterol (Total, HDL, LDL) and triglycerides in the blood. | F11: Used to assess cardiovascular risk and monitor lipid-lowering therapy. | G11: 0 | H11: Biochemistry
A12: Serum Uric acid | B12: =IF(A12=all_activity_definition!A12,"🟢Match","🔴Mismatch") -> 🟢Match | C12: =IFERROR( IF(ROW()=MATCH(A12,all_activity_definition!A:A,0), "🟢 A"&ROW()&" = A"&MATCH(A12,all_activity_definition!A:A,0), "🔴 A"&ROW()&" = A"&MATCH(A12,all_activity_definition!A:A,0) ), "No Match" ) -> 🟢 A12 = A12 | D12: uric-charge | E12: Measures uric acid levels formed from purine metabolism. | F12: Used to diagnose gout and kidney disorders. | G12: 0 | H12: Biochemistry
A13: Serum Calcium | B13: =IF(A13=all_activity_definition!A13,"🟢Match","🔴Mismatch") -> 🟢Match | C13: =IFERROR( IF(ROW()=MATCH(A13,all_activity_definition!A:A,0), "🟢 A"&ROW()&" = A"&MATCH(A13,all_activity_definition!A:A,0), "🔴 A"&ROW()&" = A"&MATCH(A13,all_activity_definition!A:A,0) ), "No Match" ) -> 🟢 A13 = A13 | D13: ca-charge | E13: Measures total calcium in the blood, essential for bone health, nerve signals, and muscle function. | F13: Used to evaluate bone metabolism and parathyroid function. | G13: 0 | H13: Biochemistry
... A225: Dengue virus(Patho) | B225: =IF(A225=all_activity_definition!A225,"🟢Match","🔴Mismatch") -> 🟢Match | C225: =IFERROR( IF(ROW()=MATCH(A225,all_activity_definition!A:A,0), "🟢 A"&ROW()&" = A"&MATCH(A225,all_activity_definition!A:A,0), "🔴 A"&ROW()&" = A"&MATCH(A225,all_activity_definition!A:A,0) ), "No Match" ) -> 🟢 A225 = A225 | D225: dengue-virus-charge1 | E225: Detection of dengue virus antigen (NS1), nucleic acid, or antibodies (IgM/IgG) to diagnose dengue infection. | F225: Used in diagnosis of Dengue infection in acute febrile illness | G225: 0 | H225: Pathology
A226: Dressing | B226: =IF(A226=procedure_activity_definition!A2,"🟢Match","🔴Mismatch") -> 🟢Match | C226: =IFERROR( IF(ROW()=MATCH(A226,procedure_activity_definition!A:A,0), "A"&ROW()&" = A"&MATCH(A226,procedure_activity_definition!A:A,0), "A"&ROW()&" = A"&MATCH(A226,procedure_activity_definition!A:A,0) ), "No Match" ) -> A226 = A2 | D226: dressing-charge | E226: Application of dressing to wound using appropriate sterile materials with assessment of wound status | F226: Application of dressing to wound using appropriate sterile materials with assessment of wound status | G226: 0 | H226: Procedures
A227: Injection (I/M) | B227: =IF(A227=procedure_activity_definition!A3,"🟢Match","🔴Mismatch") -> 🟢Match | C227: =IFERROR( IF(ROW()=MATCH(A227,procedure_activity_definition!A:A,0), "A"&ROW()&" = A"&MATCH(A227,procedure_activity_definition!A:A,0), "A"&ROW()&" = A"&MATCH(A227,procedure_activity_definition!A:A,0) ), "No Match" ) -> A227 = A3 | D227: injection-im-charge | E227: Administration of medication into the body via intramuscular route using aseptic technique | F227: Administration of medication into the body via intramuscular route using aseptic technique | G227: 0 | H227: Procedures
A228: Injection (subcutaneous ) | B228: =IF(A228=procedure_activity_definition!A4,"🟢Match","🔴Mismatch") -> 🟢Match | C228: =IFERROR( IF(ROW()=MATCH(A228,procedure_activity_definition!A:A,0), "A"&ROW()&" = A"&MATCH(A228,procedure_activity_definition!A:A,0), "A"&ROW()&" = A"&MATCH(A228,procedure_activity_definition!A:A,0) ), "No Match" ) -> A228 = A4 | D228: injection-sc-charge | E228: Administration of medication into the body via subcutaneous route using aseptic technique | F228: Administration of medication into the body via subcutaneous route using aseptic technique | G228: 0 | H228: Procedures
A229: Injection (I/V) | B229: =IF(A229=procedure_activity_definition!A5,"🟢Match","🔴Mismatch") -> 🟢Match | C229: =IFERROR( IF(ROW()=MATCH(A229,procedure_activity_definition!A:A,0), "A"&ROW()&" = A"&MATCH(A229,procedure_activity_definition!A:A,0), "A"&ROW()&" = A"&MATCH(A229,procedure_activity_definition!A:A,0) ), "No Match" ) -> A229 = A5 | D229: injection-iv-charge | E229: Administration of medication into the body via intravenous route using aseptic technique | F229: Administration of medication into the body via intravenous route using aseptic technique | G229: 0 | H229: Procedures
A230: Nebulisation | B230: =IF(A230=procedure_activity_definition!A6,"🟢Match","🔴Mismatch") -> 🟢Match | C230: =IFERROR( IF(ROW()=MATCH(A230,procedure_activity_definition!A:A,0), "A"&ROW()&" = A"&MATCH(A230,procedure_activity_definition!A:A,0), "A"&ROW()&" = A"&MATCH(A230,procedure_activity_definition!A:A,0) ), "No Match" ) -> A230 = A6 | D230: nebulization-charge | E230: Administration of medication in aerosol form by inhalation using a nebulizer. | F230: Administration of medication in aerosol form by inhalation using a nebulizer. | G230: 0 | H230: Procedures
A231: Enema | B231: =IF(A231=procedure_activity_definition!A7,"🟢Match","🔴Mismatch") -> 🟢Match | C231: =IFERROR( IF(ROW()=MATCH(A231,procedure_activity_definition!A:A,0), "A"&ROW()&" = A"&MATCH(A231,procedure_activity_definition!A:A,0), "A"&ROW()&" = A"&MATCH(A231,procedure_activity_definition!A:A,0) ), "No Match" ) -> A231 = A7 | D231: enema-charge | E231: Administration of fluid or medication into the rectum for bowel evacuation or therapeutic purpose. | F231: Administration of fluid or medication into the rectum for bowel evacuation or therapeutic purpose. | G231: 0 | H231: Procedures
A232: Cast application | B232: =IF(A232=procedure_activity_definition!A8,"🟢Match","🔴Mismatch") -> 🟢Match | C232: =IFERROR( IF(ROW()=MATCH(A232,procedure_activity_definition!A:A,0), "A"&ROW()&" = A"&MATCH(A232,procedure_activity_definition!A:A,0), "A"&ROW()&" = A"&MATCH(A232,procedure_activity_definition!A:A,0) ), "No Match" ) -> A232 = A8 | D232: cast-applicatio-charge | E232: Application of a rigid cast to immobilize a limb or body part for fracture management or support during healing | F232: Application of a rigid cast to immobilize a limb or body part for fracture management or support during healing | G232: 0 | H232: Procedures
A233: NG tube insertion | B233: =IF(A233=procedure_activity_definition!A9,"🟢Match","🔴Mismatch") -> 🟢Match | C233: =IFERROR( IF(ROW()=MATCH(A233,procedure_activity_definition!A:A,0), "A"&ROW()&" = A"&MATCH(A233,procedure_activity_definition!A:A,0), "A"&ROW()&" = A"&MATCH(A233,procedure_activity_definition!A:A,0) ), "No Match" ) -> A233 = A9 | D233: ng-tube-inserti-charge | E233: Insertion of a nasogastric tube through the nose into the stomach for feeding, medication, or gastric decompression | F233: Insertion of a nasogastric tube through the nose into the stomach for feeding, medication, or gastric decompression | G233: 0 | H233: Procedures
A234: Suture removal | B234: =IF(A234=procedure_activity_definition!A10,"🟢Match","🔴Mismatch") -> 🟢Match | C234: =IFERROR( IF(ROW()=MATCH(A234,procedure_activity_definition!A:A,0), "A"&ROW()&" = A"&MATCH(A234,procedure_activity_definition!A:A,0), "A"&ROW()&" = A"&MATCH(A234,procedure_activity_definition!A:A,0) ), "No Match" ) -> A234 = A10 | D234: suture-removal-charge | E234: Removal of sutures from a healed wound following adequate tissue repair. | F234: Removal of sutures from a healed wound following adequate tissue repair. | G234: 0 | H234: Procedures
A235: Skin scraping for fungus/AFB | B235: =IF(A235=procedure_activity_definition!A11,"🟢Match","🔴Mismatch") -> 🟢Match | C235: =IFERROR( IF(ROW()=MATCH(A235,procedure_activity_definition!A:A,0), "A"&ROW()&" = A"&MATCH(A235,procedure_activity_definition!A:A,0), "A"&ROW()&" = A"&MATCH(A235,procedure_activity_definition!A:A,0) ), "No Match" ) -> A235 = A11 | D235: skin-scraping-f-charge | E235: Collection of skin scrapings for microscopic examination to detect fungal elements or acid-fast bacilli. | F235: Collection of skin scrapings for microscopic examination to detect fungal elements or acid-fast bacilli. | G235: 0 | H235: Procedures
A236: Sitz bath | B236: =IF(A236=procedure_activity_definition!A12,"🟢Match","🔴Mismatch") -> 🟢Match | C236: =IFERROR( IF(ROW()=MATCH(A236,procedure_activity_definition!A:A,0), "A"&ROW()&" = A"&MATCH(A236,procedure_activity_definition!A:A,0), "A"&ROW()&" = A"&MATCH(A236,procedure_activity_definition!A:A,0) ), "No Match" ) -> A236 = A12 | D236: sitz-bath-charge | E236: Soaking of the perineal and anal region in warm water for hygiene, pain relief, or local therapeutic care | F236: Soaking of the perineal and anal region in warm water for hygiene, pain relief, or local therapeutic care | G236: 0 | H236: Procedures
A237: Catheterization | B237: =IF(A237=procedure_activity_definition!A13,"🟢Match","🔴Mismatch") -> 🟢Match | C237: =IFERROR( IF(ROW()=MATCH(A237,procedure_activity_definition!A:A,0), "A"&ROW()&" = A"&MATCH(A237,procedure_activity_definition!A:A,0), "A"&ROW()&" = A"&MATCH(A237,procedure_activity_definition!A:A,0) ), "No Match" ) -> A237 = A13 | D237: catheterization-charge | E237: Insertion of a catheter into a specific organ, duct, cavity, or vessel for diagnostic, therapeutic, or drainage purposes | F237: Insertion of a catheter into a specific organ, duct, cavity, or vessel for diagnostic, therapeutic, or drainage purposes | G237: 0 | H237: Procedures
... A750: Videokymography | B750: =IF(A750=procedure_activity_definition!A526,"🟢Match","🔴Mismatch") -> 🟢Match | C750: =IFERROR( IF(ROW()=MATCH(A750,procedure_activity_definition!A:A,0), "A"&ROW()&" = A"&MATCH(A750,procedure_activity_definition!A:A,0), "A"&ROW()&" = A"&MATCH(A750,procedure_activity_definition!A:A,0) ), "No Match" ) -> A750 = A526 | D750: videokymography-charge | E750: A high-speed laryngeal imaging technique that records and analyzes vocal fold vibration along a single horizontal line to assess phonatory dynamics and voice disorders | F750: A high-speed laryngeal imaging technique that records and analyzes vocal fold vibration along a single horizontal line to assess phonatory dynamics and voice disorders | G750: 0 | H750: Procedures
A751: X-Ray Chest PA View | B751: =IF(A751=all_activity_definition!A226,"🟢Match","🔴Mismatch") -> 🟢Match | C751: =IFERROR( IF(ROW()=MATCH(A751,all_activity_definition!A:A,0), "🟢 A"&ROW()&" = A"&MATCH(A751,all_activity_definition!A:A,0), "🔴 A"&ROW()&" = A"&MATCH(A751,all_activity_definition!A:A,0) ), "No Match" ) -> 🔴 A751 = A226 | D751: x-ray-chest-pa-v-charge | E751: Posteroanterior radiograph of the chest with X-ray beam entering from posterior and exiting anterior, patient standing with chest against detector. | F751: Routine chest evaluation for lung parenchyma, cardiac silhouette, mediastinum, pleura, diaphragm, and bony thorax assessment. | G751: 0 | H751: Radiodiagnosis
A752: X-Ray Cervical Spine AP View | B752: =IF(A752=all_activity_definition!A227,"🟢Match","🔴Mismatch") -> 🟢Match | C752: =IFERROR( IF(ROW()=MATCH(A752,all_activity_definition!A:A,0), "🟢 A"&ROW()&" = A"&MATCH(A752,all_activity_definition!A:A,0), "🔴 A"&ROW()&" = A"&MATCH(A752,all_activity_definition!A:A,0) ), "No Match" ) -> 🔴 A752 = A227 | D752: x-ray-cervical-s-charge | E752: Anteroposterior radiographic imaging of the cervical spine to visualize vertebral alignment, intervertebral spaces, and bony integrity. | F752: Used to evaluate cervical spine trauma, degenerative changes, congenital anomalies, infections, tumors, and neck pain. | G752: 0 | H752: Radiodiagnosis
A753: Ultrasound Scan Upper Abdomen | B753: =IF(A753=all_activity_definition!A228,"🟢Match","🔴Mismatch") -> 🟢Match | C753: =IFERROR( IF(ROW()=MATCH(A753,all_activity_definition!A:A,0), "🟢 A"&ROW()&" = A"&MATCH(A753,all_activity_definition!A:A,0), "🔴 A"&ROW()&" = A"&MATCH(A753,all_activity_definition!A:A,0) ), "No Match" ) -> 🔴 A753 = A228 | D753: ultrasound-scan-charge | E753: Ultrasonographic imaging of upper abdominal organs including liver, gallbladder, pancreas, spleen, kidneys, and upper abdominal vessels. | F753: Used to assess abdominal pain, hepatobiliary disease, gallstones, liver pathology, pancreatitis, splenomegaly, and renal abnormalities. | G753: 0 | H753: Radiodiagnosis
A754: X-Ray Sacroiliac Joint AP & Lateral Views | B754: =IF(A754=all_activity_definition!A229,"🟢Match","🔴Mismatch") -> 🟢Match | C754: =IFERROR( IF(ROW()=MATCH(A754,all_activity_definition!A:A,0), "🟢 A"&ROW()&" = A"&MATCH(A754,all_activity_definition!A:A,0), "🔴 A"&ROW()&" = A"&MATCH(A754,all_activity_definition!A:A,0) ), "No Match" ) -> 🔴 A754 = A229 | D754: x-ray-sacroiliac-charge | E754: Plain radiographic examination of the pelvis with focused visualization of the sacroiliac joints using anteroposterior and lateral views. | F754: Used to assess sacroiliac joints for inflammatory, degenerative, traumatic, or structural abnormalities. | G754: 0 | H754: Radiodiagnosis
A755: Ultrasound Lower Abdomen | B755: =IF(A755=all_activity_definition!A230,"🟢Match","🔴Mismatch") -> 🟢Match | C755: =IFERROR( IF(ROW()=MATCH(A755,all_activity_definition!A:A,0), "🟢 A"&ROW()&" = A"&MATCH(A755,all_activity_definition!A:A,0), "🔴 A"&ROW()&" = A"&MATCH(A755,all_activity_definition!A:A,0) ), "No Match" ) -> 🔴 A755 = A230 | D755: ultrasound-lower-charge | E755: Ultrasonographic examination of the lower abdomen to visualize pelvic and lower abdominal organs. | F755: Used to evaluate pelvic organs and lower abdominal structures for masses, fluid collections, inflammation, or other pathology. | G755: 0 | H755: Radiodiagnosis
A756: X-Ray Lumbar Spine | B756: =IF(A756=all_activity_definition!A231,"🟢Match","🔴Mismatch") -> 🟢Match | C756: =IFERROR( IF(ROW()=MATCH(A756,all_activity_definition!A:A,0), "🟢 A"&ROW()&" = A"&MATCH(A756,all_activity_definition!A:A,0), "🔴 A"&ROW()&" = A"&MATCH(A756,all_activity_definition!A:A,0) ), "No Match" ) -> 🔴 A756 = A231 | D756: x-ray-lumbar-spi-charge | E756: Radiographic imaging of the lumbar spine to visualize vertebrae, intervertebral spaces, and alignment. | F756: Used to assess low back pain, trauma, degenerative disc disease, spondylosis, infections, and spinal deformities. | G756: 0 | H756: Radiodiagnosis
A757: X-Ray Right Knee AP & Lateral Views | B757: =IF(A757=all_activity_definition!A232,"🟢Match","🔴Mismatch") -> 🟢Match | C757: =IFERROR( IF(ROW()=MATCH(A757,all_activity_definition!A:A,0), "🟢 A"&ROW()&" = A"&MATCH(A757,all_activity_definition!A:A,0), "🔴 A"&ROW()&" = A"&MATCH(A757,all_activity_definition!A:A,0) ), "No Match" ) -> 🔴 A757 = A232 | D757: x-ray-right-knee-charge | E757: Radiographic imaging of the right knee in anteroposterior and lateral views. | F757: Used to evaluate trauma, arthritis, fractures, joint space narrowing, and degenerative changes. | G757: 0 | H757: Radiodiagnosis
A758: X-Ray Left Knee AP & Lateral Views | B758: =IF(A758=all_activity_definition!A233,"🟢Match","🔴Mismatch") -> 🟢Match | C758: =IFERROR( IF(ROW()=MATCH(A758,all_activity_definition!A:A,0), "🟢 A"&ROW()&" = A"&MATCH(A758,all_activity_definition!A:A,0), "🔴 A"&ROW()&" = A"&MATCH(A758,all_activity_definition!A:A,0) ), "No Match" ) -> 🔴 A758 = A233 | D758: x-ray-left-knee-charge | E758: Radiographic imaging of the left knee in anteroposterior and lateral views. | F758: Used for assessment of pain, injury, arthritis, fractures, and joint abnormalities. | G758: 0 | H758: Radiodiagnosis
A759: X-Ray Left Knee AP View | B759: =IF(A759=all_activity_definition!A234,"🟢Match","🔴Mismatch") -> 🟢Match | C759: =IFERROR( IF(ROW()=MATCH(A759,all_activity_definition!A:A,0), "🟢 A"&ROW()&" = A"&MATCH(A759,all_activity_definition!A:A,0), "🔴 A"&ROW()&" = A"&MATCH(A759,all_activity_definition!A:A,0) ), "No Match" ) -> 🔴 A759 = A234 | D759: x-ray-left-knee-charge1 | E759: Anteroposterior radiographic imaging of the left knee joint. | F759: Used to assess alignment, fractures, arthritis, and joint space abnormalities. | G759: 0 | H759: Radiodiagnosis
A760: X-Ray Left Knee Lateral View | B760: =IF(A760=all_activity_definition!A235,"🟢Match","🔴Mismatch") -> 🟢Match | C760: =IFERROR( IF(ROW()=MATCH(A760,all_activity_definition!A:A,0), "🟢 A"&ROW()&" = A"&MATCH(A760,all_activity_definition!A:A,0), "🔴 A"&ROW()&" = A"&MATCH(A760,all_activity_definition!A:A,0) ), "No Match" ) -> 🔴 A760 = A235 | D760: x-ray-left-knee-charge2 | E760: Lateral view radiographic imaging of the left knee joint. | F760: Used to detect fractures, effusion, patellar position, and degenerative changes. | G760: 0 | H760: Radiodiagnosis
A761: X-Ray Right Knee AP View | B761: =IF(A761=all_activity_definition!A236,"🟢Match","🔴Mismatch") -> 🟢Match | C761: =IFERROR( IF(ROW()=MATCH(A761,all_activity_definition!A:A,0), "🟢 A"&ROW()&" = A"&MATCH(A761,all_activity_definition!A:A,0), "🔴 A"&ROW()&" = A"&MATCH(A761,all_activity_definition!A:A,0) ), "No Match" ) -> 🔴 A761 = A236 | D761: x-ray-right-knee-charge1 | E761: Anteroposterior radiographic imaging of the right knee joint. | F761: Used to evaluate fractures, arthritis, and joint alignment. | G761: 0 | H761: Radiodiagnosis
A762: X-Ray Right Knee Lateral View | B762: =IF(A762=all_activity_definition!A237,"🟢Match","🔴Mismatch") -> 🟢Match | C762: =IFERROR( IF(ROW()=MATCH(A762,all_activity_definition!A:A,0), "🟢 A"&ROW()&" = A"&MATCH(A762,all_activity_definition!A:A,0), "🔴 A"&ROW()&" = A"&MATCH(A762,all_activity_definition!A:A,0) ), "No Match" ) -> 🔴 A762 = A237 | D762: x-ray-right-knee-charge2 | E762: Lateral view radiographic imaging of the right knee joint. | F762: Used for trauma assessment, effusion detection, and degenerative joint disease. | G762: 0 | H762: Radiodiagnosis
... A1997: DOPPLER LT. FOOT ARTERIAL | B1997: =IF(A1997=all_activity_definition!A1472,"🟢Match","🔴Mismatch") -> 🟢Match | C1997: =IFERROR( IF(ROW()=MATCH(A1997,all_activity_definition!A:A,0), "🟢 A"&ROW()&" = A"&MATCH(A1997,all_activity_definition!A:A,0), "🔴 A"&ROW()&" = A"&MATCH(A1997,all_activity_definition!A:A,0) ), "No Match" ) -> 🔴 A1997 = A1472 | D1997: doppler-lt-foot-charge1 | E1997: Doppler ultrasound imaging of the arterial systems of the left foot to assess vascular patency, flow dynamics, and hemodynamic abnormalities. | F1997: Doppler ultrasound imaging of the arterial systems of the left foot to assess vascular patency, flow dynamics, and hemodynamic abnormalities. | G1997: 250 | H1997: Radiodiagnosis
A1998: MRI CE BRAIN-IPD | B1998: =IF(A1998=all_activity_definition!A1473,"🟢Match","🔴Mismatch") -> 🟢Match | C1998: =IFERROR( IF(ROW()=MATCH(A1998,all_activity_definition!A:A,0), "🟢 A"&ROW()&" = A"&MATCH(A1998,all_activity_definition!A:A,0), "🔴 A"&ROW()&" = A"&MATCH(A1998,all_activity_definition!A:A,0) ), "No Match" ) -> 🔴 A1998 = A1473 | D1998: mri-brain-charge | E1998: Contrast-enhanced magnetic resonance imaging of the brain performed to obtain high-resolution multiplanar images of intracranial structures with intravenous contrast to assess lesion enhancement and vascularity. | F1998: Used to detect, characterize, and stage tumors, infections, inflammatory lesions, vascular abnormalities, and postoperative or demyelinating brain pathology. | G1998: 3000
A1999: MRI CE BRAIN-OPD | B1999: =IF(A1999=all_activity_definition!A1474,"🟢Match","🔴Mismatch") -> 🟢Match | C1999: =IFERROR( IF(ROW()=MATCH(A1999,all_activity_definition!A:A,0), "🟢 A"&ROW()&" = A"&MATCH(A1999,all_activity_definition!A:A,0), "🔴 A"&ROW()&" = A"&MATCH(A1999,all_activity_definition!A:A,0) ), "No Match" ) -> 🔴 A1999 = A1474 | D1999: mri-brain-charge1 | E1999: Contrast-enhanced magnetic resonance imaging of the brain performed to obtain high-resolution multiplanar images of intracranial structures with intravenous contrast to assess lesion enhancement and vascularity. | F1999: Used to detect, characterize, and stage tumors, infections, inflammatory lesions, vascular abnormalities, and postoperative or demyelinating brain pathology. | G1999: 3500
A2000: USG ANOMALY SCAN LEVEL 2 | B2000: =IF(A2000=all_activity_definition!A1475,"🟢Match","🔴Mismatch") -> 🟢Match | C2000: =IFERROR( IF(ROW()=MATCH(A2000,all_activity_definition!A:A,0), "🟢 A"&ROW()&" = A"&MATCH(A2000,all_activity_definition!A:A,0), "🔴 A"&ROW()&" = A"&MATCH(A2000,all_activity_definition!A:A,0) ), "No Match" ) -> 🔴 A2000 = A1475 | D2000: usg-anomaly-scan-charge | E2000: Detailed ultrasound examination performed during pregnancy to assess fetal anatomy and development. | F2000: Used for detection of fetal structural abnormalities and assessment of fetal well-being. | G2000: 0 | H2000: Radiodiagnosis
A2001: MRI CE OF UPPER ABDOMEN-IPD | B2001: =IF(A2001=all_activity_definition!A1476,"🟢Match","🔴Mismatch") -> 🟢Match | C2001: =IFERROR( IF(ROW()=MATCH(A2001,all_activity_definition!A:A,0), "🟢 A"&ROW()&" = A"&MATCH(A2001,all_activity_definition!A:A,0), "🔴 A"&ROW()&" = A"&MATCH(A2001,all_activity_definition!A:A,0) ), "No Match" ) -> 🔴 A2001 = A1476 | D2001: mri-ce-of-upper-charge | E2001: Contrast-enhanced magnetic resonance imaging of the upper abdomen performed to obtain high-resolution multiplanar images of the liver, biliary system, pancreas, spleen, upper kidneys, and adjacent vascular structures. | F2001: Used to detect, characterize, and stage focal lesions, inflammatory conditions, vascular abnormalities, and neoplastic processes of the upper abdominal organs. | G2001: 3000 | H2001: Radiodiagnosis
A2002: MRI CE OF UPPER ABDOMEN-OPD | B2002: =IF(A2002=all_activity_definition!A1477,"🟢Match","🔴Mismatch") -> 🟢Match | C2002: =IFERROR( IF(ROW()=MATCH(A2002,all_activity_definition!A:A,0), "🟢 A"&ROW()&" = A"&MATCH(A2002,all_activity_definition!A:A,0), "🔴 A"&ROW()&" = A"&MATCH(A2002,all_activity_definition!A:A,0) ), "No Match" ) -> 🔴 A2002 = A1477 | D2002: mri-ce-of-upper-charge1 | E2002: Contrast-enhanced magnetic resonance imaging of the upper abdomen performed to obtain high-resolution multiplanar images of the liver, biliary system, pancreas, spleen, upper kidneys, and adjacent vascular structures. | F2002: Used to detect, characterize, and stage focal lesions, inflammatory conditions, vascular abnormalities, and neoplastic processes of the upper abdominal organs. | G2002: 3500 | H2002: Radiodiagnosis
A2003: MRI LEG-IPD | B2003: =IF(A2003=all_activity_definition!A1478,"🟢Match","🔴Mismatch") -> 🟢Match | C2003: =IFERROR( IF(ROW()=MATCH(A2003,all_activity_definition!A:A,0), "🟢 A"&ROW()&" = A"&MATCH(A2003,all_activity_definition!A:A,0), "🔴 A"&ROW()&" = A"&MATCH(A2003,all_activity_definition!A:A,0) ), "No Match" ) -> 🔴 A2003 = A1478 | D2003: mri-leg-ipd-charge | E2003: Magnetic resonance imaging of the leg performed to obtain high-resolution multiplanar images of bones, muscles, tendons, vessels, and other soft tissues of the lower limb. | F2003: Used to evaluate soft-tissue masses, muscle and tendon injuries, infection, trauma, vascular abnormalities, and neoplastic or inflammatory conditions of the leg. | G2003: 3000 | H2003: Radiodiagnosis
A2004: MRI LEG-OPD | B2004: =IF(A2004=all_activity_definition!A1479,"🟢Match","🔴Mismatch") -> 🟢Match | C2004: =IFERROR( IF(ROW()=MATCH(A2004,all_activity_definition!A:A,0), "🟢 A"&ROW()&" = A"&MATCH(A2004,all_activity_definition!A:A,0), "🔴 A"&ROW()&" = A"&MATCH(A2004,all_activity_definition!A:A,0) ), "No Match" ) -> 🔴 A2004 = A1479 | D2004: mri-leg-opd-charge | E2004: Magnetic resonance imaging of the leg performed to obtain high-resolution multiplanar images of bones, muscles, tendons, vessels, and other soft tissues of the lower limb. | F2004: Used to evaluate soft-tissue masses, muscle and tendon injuries, infection, trauma, vascular abnormalities, and neoplastic or inflammatory conditions of the leg. | G2004: 3500 | H2004: Radiodiagnosis
A2005: MRI ABDOMEN-IPD | B2005: =IF(A2005=all_activity_definition!A1480,"🟢Match","🔴Mismatch") -> 🟢Match | C2005: =IFERROR( IF(ROW()=MATCH(A2005,all_activity_definition!A:A,0), "🟢 A"&ROW()&" = A"&MATCH(A2005,all_activity_definition!A:A,0), "🔴 A"&ROW()&" = A"&MATCH(A2005,all_activity_definition!A:A,0) ), "No Match" ) -> 🔴 A2005 = A1480 | D2005: mri-abdomen-ipd-charge | E2005: Contrast-enhanced magnetic resonance imaging of the abdomen to visualize abdominal organs, soft tissues, and vascular structures in detail. | F2005: Used to evaluate abdominal organs for tumors, inflammation, infection, vascular abnormalities, and other diseases. | G2005: 3000 | H2005: Radiodiagnosis
A2006: MRI ABDOMEN-OPD | B2006: =IF(A2006=all_activity_definition!A1481,"🟢Match","🔴Mismatch") -> 🟢Match | C2006: =IFERROR( IF(ROW()=MATCH(A2006,all_activity_definition!A:A,0), "🟢 A"&ROW()&" = A"&MATCH(A2006,all_activity_definition!A:A,0), "🔴 A"&ROW()&" = A"&MATCH(A2006,all_activity_definition!A:A,0) ), "No Match" ) -> 🔴 A2006 = A1481 | D2006: mri-abdomen-opd-charge | E2006: Contrast-enhanced magnetic resonance imaging of the abdomen to visualize abdominal organs, soft tissues, and vascular structures in detail. | F2006: Used to evaluate abdominal organs for tumors, inflammation, infection, vascular abnormalities, and other diseases. | G2006: 3500 | H2006: Radiodiagnosis
A2007: MRI NECK-IPD | B2007: =IF(A2007=all_activity_definition!A1482,"🟢Match","🔴Mismatch") -> 🟢Match | C2007: =IFERROR( IF(ROW()=MATCH(A2007,all_activity_definition!A:A,0), "🟢 A"&ROW()&" = A"&MATCH(A2007,all_activity_definition!A:A,0), "🔴 A"&ROW()&" = A"&MATCH(A2007,all_activity_definition!A:A,0) ), "No Match" ) -> 🔴 A2007 = A1482 | D2007: mri-neck-ipd-charge | E2007: Magnetic resonance imaging of the neck performed to obtain high-resolution multiplanar images of the soft tissues, cervical spaces, lymph nodes, salivary glands, airway, and neurovascular structures. | F2007: Used to evaluate neck masses, lymphadenopathy, infections, inflammatory conditions, congenital anomalies, vascular lesions, and neoplastic processes of the neck. | G2007: 3000 | H2007: Radiodiagnosis
A2008: MRI NECK-OPD | B2008: =IF(A2008=all_activity_definition!A1483,"🟢Match","🔴Mismatch") -> 🟢Match | C2008: =IFERROR( IF(ROW()=MATCH(A2008,all_activity_definition!A:A,0), "🟢 A"&ROW()&" = A"&MATCH(A2008,all_activity_definition!A:A,0), "🔴 A"&ROW()&" = A"&MATCH(A2008,all_activity_definition!A:A,0) ), "No Match" ) -> 🔴 A2008 = A1483 | D2008: mri-neck-opd-charge | E2008: Magnetic resonance imaging of the neck performed to obtain high-resolution multiplanar images of the soft tissues, cervical spaces, lymph nodes, salivary glands, airway, and neurovascular structures. | F2008: Used to evaluate neck masses, lymphadenopathy, infections, inflammatory conditions, congenital anomalies, vascular lesions, and neoplastic processes of the neck. | G2008: 3500 | H2008: Radiodiagnosis
A2009: MRCP-IPD | B2009: =IF(A2009=all_activity_definition!A1484,"🟢Match","🔴Mismatch") -> 🟢Match | C2009: =IFERROR( IF(ROW()=MATCH(A2009,all_activity_definition!A:A,0), "🟢 A"&ROW()&" = A"&MATCH(A2009,all_activity_definition!A:A,0), "🔴 A"&ROW()&" = A"&MATCH(A2009,all_activity_definition!A:A,0) ), "No Match" ) -> 🔴 A2009 = A1484 | D2009: mrcp-ipd-charge | E2009: Magnetic resonance cholangiopancreatography using heavily T2-weighted MRI sequences to noninvasively visualize the biliary tree and pancreatic ductal system. | F2009: Used to evaluate biliary and pancreatic duct obstruction, stones, strictures, congenital anomalies, and pancreatitis without ionizing radiation. | G2009: 3000 | H2009: Radiodiagnosis
A2010: MRCP-OPD | B2010: =IF(A2010=all_activity_definition!A1485,"🟢Match","🔴Mismatch") -> 🟢Match | C2010: =IFERROR( IF(ROW()=MATCH(A2010,all_activity_definition!A:A,0), "🟢 A"&ROW()&" = A"&MATCH(A2010,all_activity_definition!A:A,0), "🔴 A"&ROW()&" = A"&MATCH(A2010,all_activity_definition!A:A,0) ), "No Match" ) -> 🔴 A2010 = A1485 | D2010: mrcp-opd-charge | E2010: Magnetic resonance cholangiopancreatography using heavily T2-weighted MRI sequences to noninvasively visualize the biliary tree and pancreatic ductal system. | F2010: Used to evaluate biliary and pancreatic duct obstruction, stones, strictures, congenital anomalies, and pancreatitis without ionizing radiation. | G2010: 3500 | H2010: Radiodiagnosis
A2011: USG DOPPLER RT.LEG | B2011: =IF(A2011=all_activity_definition!A1486,"🟢Match","🔴Mismatch") -> 🟢Match | C2011: =IFERROR( IF(ROW()=MATCH(A2011,all_activity_definition!A:A,0), "🟢 A"&ROW()&" = A"&MATCH(A2011,all_activity_definition!A:A,0), "🔴 A"&ROW()&" = A"&MATCH(A2011,all_activity_definition!A:A,0) ), "No Match" ) -> 🔴 A2011 = A1486 | D2011: usg-doppler-rt-l-charge | E2011: Doppler ultrasound of the right lower limb performed to assess arterial and/or venous blood flow, vessel patency, and hemodynamics. | F2011: Used to evaluate deep vein thrombosis, venous insufficiency, arterial occlusive disease, varicosities, and other vascular abnormalities of the right leg. | G2011: 250 | H2011: Radiodiagnosis
... A2013: MRI ANGIO BRAIN-OPD | B2013: =IF(A2013=all_activity_definition!A1488,"🟢Match","🔴Mismatch") -> 🟢Match | C2013: =IFERROR( IF(ROW()=MATCH(A2013,all_activity_definition!A:A,0), "🟢 A"&ROW()&" = A"&MATCH(A2013,all_activity_definition!A:A,0), "🔴 A"&ROW()&" = A"&MATCH(A2013,all_activity_definition!A:A,0) ), "No Match" ) -> 🔴 A2013 = A1488 | D2013: mri-angio-brain-charge1 | E2013: Magnetic resonance angiography of the brain performed to visualize intracranial arterial and/or venous vasculature using non-invasive MR techniques, with or without contrast. | F2013: Used to evaluate intracranial vascular abnormalities such as aneurysms, arteriovenous malformations, stenosis, occlusion, vasculitis, and stroke-related vascular pathology. | G2013: 3500 | H2013: Radiodiagnosis
A2014: MRI PELVIS-IPD | B2014: =IF(A2014=#REF!,"🟢Match","🔴Mismatch") -> #REF! | C2014: =IFERROR( IF(ROW()=MATCH(A2014,all_activity_definition!A:A,0), "🟢 A"&ROW()&" = A"&MATCH(A2014,all_activity_definition!A:A,0), "🔴 A"&ROW()&" = A"&MATCH(A2014,all_activity_definition!A:A,0) ), "No Match" ) -> No Match | D2014: mri-pelvis-ipd-charge1 | E2014: Magnetic resonance imaging of the pelvis performed to obtain high-resolution multiplanar images of pelvic organs, bones, soft tissues, and neurovascular structures. | F2014: Used to evaluate pelvic pain, masses, inflammatory or infective conditions, congenital anomalies, trauma, and neoplastic processes of pelvic organs and structures. | G2014: 3000 | H2014: Radiodiagnosis
A2015: MRI PELVIS-OPD | B2015: =IF(A2015=#REF!,"🟢Match","🔴Mismatch") -> #REF! | C2015: =IFERROR( IF(ROW()=MATCH(A2015,all_activity_definition!A:A,0), "🟢 A"&ROW()&" = A"&MATCH(A2015,all_activity_definition!A:A,0), "🔴 A"&ROW()&" = A"&MATCH(A2015,all_activity_definition!A:A,0) ), "No Match" ) -> No Match | D2015: mri-pelvis-opd-charge1 | E2015: Magnetic resonance imaging of the pelvis performed to obtain high-resolution multiplanar images of pelvic organs, bones, soft tissues, and neurovascular structures. | F2015: Used to evaluate pelvic pain, masses, inflammatory or infective conditions, congenital anomalies, trauma, and neoplastic processes of pelvic organs and structures. | G2015: 3500 | H2015: Radiodiagnosis
A2016: MRI LEUBO SCAN SPINE-IPD | B2016: =IF(A2016=all_activity_definition!A1489,"🟢Match","🔴Mismatch") -> 🟢Match | C2016: =IFERROR( IF(ROW()=MATCH(A2016,all_activity_definition!A:A,0), "🟢 A"&ROW()&" = A"&MATCH(A2016,all_activity_definition!A:A,0), "🔴 A"&ROW()&" = A"&MATCH(A2016,all_activity_definition!A:A,0) ), "No Match" ) -> 🔴 A2016 = A1489 | D2016: mri-leubo-scan-s-charge | E2016: Magnetic resonance imaging of the lumbosacral spine performed to obtain high-resolution multiplanar images of lumbar vertebrae, intervertebral discs, spinal canal, nerve roots, and adjacent soft tissues. | F2016: Used to evaluate low back pain, disc herniation, spinal stenosis, nerve root compression, infection, trauma, and degenerative or neoplastic conditions of the lumbar spine. | G2016: 3000 | H2016: Radiodiagnosis
A2017: MRI LEUBO SCAN SPINE-OPD | B2017: =IF(A2017=all_activity_definition!A1490,"🟢Match","🔴Mismatch") -> 🟢Match | C2017: =IFERROR( IF(ROW()=MATCH(A2017,all_activity_definition!A:A,0), "🟢 A"&ROW()&" = A"&MATCH(A2017,all_activity_definition!A:A,0), "🔴 A"&ROW()&" = A"&MATCH(A2017,all_activity_definition!A:A,0) ), "No Match" ) -> 🔴 A2017 = A1490 | D2017: mri-leubo-scan-s-charge1 | E2017: Magnetic resonance imaging of the lumbosacral spine performed to obtain high-resolution multiplanar images of lumbar vertebrae, intervertebral discs, spinal canal, nerve roots, and adjacent soft tissues. | F2017: Used to evaluate low back pain, disc herniation, spinal stenosis, nerve root compression, infection, trauma, and degenerative or neoplastic conditions of the lumbar spine. | G2017: 3500 | H2017: Radiodiagnosis
A2018: MRI INNER EAR-IPD | B2018: =IF(A2018=all_activity_definition!A1491,"🟢Match","🔴Mismatch") -> 🟢Match | C2018: =IFERROR( IF(ROW()=MATCH(A2018,all_activity_definition!A:A,0), "🟢 A"&ROW()&" = A"&MATCH(A2018,all_activity_definition!A:A,0), "🔴 A"&ROW()&" = A"&MATCH(A2018,all_activity_definition!A:A,0) ), "No Match" ) -> 🔴 A2018 = A1491 | D2018: mri-inner-ear-ip-charge | E2018: Magnetic resonance imaging of the inner ear performed to obtain high-resolution images of the cochlea, vestibule, semicircular canals, internal auditory canals, and adjacent neural structures. | F2018: Used to evaluate sensorineural hearing loss, vertigo, vestibular disorders, congenital anomalies, inflammation, and neoplastic conditions such as vestibular schwannoma. | G2018: 3000 | H2018: Radiodiagnosis
A2019: MRI INNER EAR-OPD | B2019: =IF(A2019=all_activity_definition!A1492,"🟢Match","🔴Mismatch") -> 🟢Match | C2019: =IFERROR( IF(ROW()=MATCH(A2019,all_activity_definition!A:A,0), "🟢 A"&ROW()&" = A"&MATCH(A2019,all_activity_definition!A:A,0), "🔴 A"&ROW()&" = A"&MATCH(A2019,all_activity_definition!A:A,0) ), "No Match" ) -> 🔴 A2019 = A1492 | D2019: mri-inner-ear-op-charge | E2019: Magnetic resonance imaging of the inner ear performed to obtain high-resolution images of the cochlea, vestibule, semicircular canals, internal auditory canals, and adjacent neural structures. | F2019: Used to evaluate sensorineural hearing loss, vertigo, vestibular disorders, congenital anomalies, inflammation, and neoplastic conditions such as vestibular schwannoma. | G2019: 3500 | H2019: Radiodiagnosis
A2020: NCCT THORAX | B2020: =IF(A2020=all_activity_definition!A1493,"🟢Match","🔴Mismatch") -> 🟢Match | C2020: =IFERROR( IF(ROW()=MATCH(A2020,all_activity_definition!A:A,0), "🟢 A"&ROW()&" = A"&MATCH(A2020,all_activity_definition!A:A,0), "🔴 A"&ROW()&" = A"&MATCH(A2020,all_activity_definition!A:A,0) ), "No Match" ) -> 🔴 A2020 = A1493 | D2020: ncct-thorax-charge | E2020: Non-contrast computed tomography of the thorax performed to obtain detailed cross-sectional images of the lungs, mediastinum, pleura, chest wall, and bony thorax. | F2020: Used to evaluate pulmonary, pleural, and mediastinal conditions such as infection, interstitial lung disease, nodules, trauma, and hemorrhage without the use of intravenous contrast. | G2020: 0 | H2020: Radiodiagnosis
A2021: CT SCAN LEFT ORBIT | B2021: =IF(A2021=all_activity_definition!A1494,"🟢Match","🔴Mismatch") -> 🟢Match | C2021: =IFERROR( IF(ROW()=MATCH(A2021,all_activity_definition!A:A,0), "🟢 A"&ROW()&" = A"&MATCH(A2021,all_activity_definition!A:A,0), "🔴 A"&ROW()&" = A"&MATCH(A2021,all_activity_definition!A:A,0) ), "No Match" ) -> 🔴 A2021 = A1494 | D2021: ct-scan-left-orb-charge | E2021: Computed tomography of the left orbit performed to obtain detailed cross-sectional images of the globe, optic nerve, extraocular muscles, bony orbit, and adjacent structures. | F2021: Used to evaluate orbital trauma, fractures, infections, inflammatory conditions, masses, foreign bodies, and structural abnormalities of the left orbit. | G2021: 1100 | H2021: Radiodiagnosis
A2022: CT SCAN RIGHT ORBIT | B2022: =IF(A2022=all_activity_definition!A1495,"🟢Match","🔴Mismatch") -> 🟢Match | C2022: =IFERROR( IF(ROW()=MATCH(A2022,all_activity_definition!A:A,0), "🟢 A"&ROW()&" = A"&MATCH(A2022,all_activity_definition!A:A,0), "🔴 A"&ROW()&" = A"&MATCH(A2022,all_activity_definition!A:A,0) ), "No Match" ) -> 🔴 A2022 = A1495 | D2022: ct-scan-right-or-charge | E2022: Computed tomography of the right orbit performed to obtain detailed cross-sectional images of the globe, optic nerve, extraocular muscles, bony orbit, and adjacent structures. | F2022: Used to evaluate orbital trauma, fractures, infections, inflammatory conditions, masses, foreign bodies, and structural abnormalities of the right orbit. | G2022: 1100 | H2022: Radiodiagnosis
A2023: MR LEFT HAND-IPD | B2023: =IF(A2023=all_activity_definition!A1496,"🟢Match","🔴Mismatch") -> 🟢Match | C2023: =IFERROR( IF(ROW()=MATCH(A2023,all_activity_definition!A:A,0), "🟢 A"&ROW()&" = A"&MATCH(A2023,all_activity_definition!A:A,0), "🔴 A"&ROW()&" = A"&MATCH(A2023,all_activity_definition!A:A,0) ), "No Match" ) -> 🔴 A2023 = A1496 | D2023: mr-left-hand-ipd-charge | E2023: Magnetic resonance imaging of the left hand performed to obtain high-resolution multiplanar images of bones, joints, tendons, ligaments, muscles, and soft tissues. | F2023: Used to evaluate traumatic, inflammatory, infective, degenerative, or neoplastic conditions of the left hand and its soft-tissue and osseous structures. | G2023: 3000 | H2023: Radiodiagnosis
A2024: MRI LEFT HAND-OPD | B2024: =IF(A2024=all_activity_definition!A1497,"🟢Match","🔴Mismatch") -> 🟢Match | C2024: =IFERROR( IF(ROW()=MATCH(A2024,all_activity_definition!A:A,0), "🟢 A"&ROW()&" = A"&MATCH(A2024,all_activity_definition!A:A,0), "🔴 A"&ROW()&" = A"&MATCH(A2024,all_activity_definition!A:A,0) ), "No Match" ) -> 🔴 A2024 = A1497 | D2024: mri-left-hand-op-charge | E2024: Magnetic resonance imaging of the left hand to obtain detailed images of bones, joints, tendons, ligaments, muscles, nerves, and surrounding soft tissues. | F2024: Used for evaluation of trauma, fractures, ligament or tendon injuries, arthritis, infection, soft tissue swelling, congenital abnormalities, tumors, and other musculoskeletal disorders of the left hand. | G2024: 3500 | H2024: Radiodiagnosis
A2025: HAND SCALING | D2025: handscaling-charge | E2025: Hand scaling is a professional dental cleaning procedure in which specialized manual instruments are used to remove plaque, tartar (calculus), and stains from the surfaces of the teeth and along the gum line. | F2025: The procedure is performed to maintain oral hygiene, prevent and treat gum diseases such as gingivitis and periodontitis, reduce bad breath, and promote healthy gums and teeth by removing deposits that cannot be cleaned through regular brushing and flossing. | G2025: 100 | H2025: Dental
A2026: ULTRASONIC SCALING | D2026: ultrasonicscal-charge | E2026: Ultrasonic scaling is a professional dental cleaning procedure that uses an ultrasonic scaler device with high-frequency vibrations and water irrigation to remove plaque, tartar (calculus), stains, and bacterial deposits from the teeth and below the gum line. | F2026: The procedure is performed to maintain oral hygiene, prevent and treat gum diseases, remove hardened deposits more efficiently, reduce bad breath, and promote healthier gums and teeth by cleaning areas that are difficult to reach with regular brushing and flossing. | G2026: 300 | H2026: Dental
A2027: GIC | D2027: gic-charge | E2027: Glass Ionomer Cement (GIC) is a tooth-colored dental restorative material used for fillings, liners, bases, and cementation procedures. It chemically bonds to the tooth structure and releases fluoride, which helps protect the tooth from further decay. | F2027: The procedure is performed to restore decayed or damaged teeth, protect the tooth structure, prevent recurrent dental caries, and provide a durable restoration with fluoride-releasing properties, especially in pediatric, cervical, and low stress-bearing restorations. | G2027: 200 | H2027: Dental
A2028: OPG X-ray | D2028: opgx-ray-charge | E2028: An OPG X-ray is a panoramic dental radiograph that captures a single wide-view image of the upper and lower jaws, teeth, jaw joints, and surrounding facial structures using a rotating X-ray machine. It provides a comprehensive overview of the entire mouth and related structures in one image. | F2028: The procedure is performed to evaluate overall dental and jaw health, detect impacted teeth, infections, cysts, fractures, bone abnormalities, and other dental conditions, and to assist in treatment planning for procedures such as orthodontics, tooth extractions, dental implants, and oral surgery. | G2028: 200 | H2028: Dental
A2029: COMPLETE DENTURE (FULL) | D2029: completedentur-charge | E2029: A complete denture (full denture) is a removable dental prosthesis used to replace all missing teeth in the upper jaw, lower jaw, or both. It consists of artificial teeth attached to a gum-colored base designed to fit comfortably over the gums and restore oral function and appearance. | F2029: The procedure is performed to restore chewing ability, speech, facial appearance, and overall oral function in patients who have lost all natural teeth. It also helps support facial muscles, improve aesthetics, and enhance comfort and confidence in daily activities. | G2029: 2000 | H2029: Dental
A2030: COMPLETE DENTURE (HALF) | D2030: completedentur-charge1 | E2030: A complete denture (half) refers to a full removable dental prosthesis used to replace all missing teeth in either the upper jaw or the lower jaw only. It consists of artificial teeth attached to a gum-colored acrylic base designed to fit over the gums and restore oral function and appearance. | F2030: The procedure is performed to restore chewing ability, speech, facial support, and aesthetics in patients who have lost all teeth in a single jaw. It also helps improve oral function, comfort, and confidence in daily activities. | G2030: 1000 | H2030: Dental
A2031: MINOR OT | D2031: minorot-charge | E2031: Minor OT refers to minor surgical or dental procedures performed in a specially equipped operation theatre under sterile conditions, usually using local anesthesia. These procedures are generally simple, minimally invasive, and do not require major surgery or prolonged hospital stay. | F2031: The procedure is performed to safely carry out minor dental or oral surgical treatments such as tooth extractions, incision and drainage, biopsies, suturing, or other minor interventions while maintaining infection control, patient safety, and proper clinical care. | G2031: 500 | H2031: Dental
A2032: ROOT PLANNING | D2032: rootplanning-charge | E2032: Root planing is a deep dental cleaning procedure performed below the gum line to clean and smooth the root surfaces of the teeth by removing plaque, tartar, bacterial toxins, and infected deposits from the tooth roots. It is commonly performed along with scaling as part of periodontal treatment for gum disease. | F2032: The procedure is performed to treat gum disease, reduce periodontal pockets, promote reattachment of the gums to the teeth, prevent further buildup of bacteria and tartar, and help maintain healthy gums and supporting tooth structures. | G2032: 200 | H2032: Dental
A2033: ORTHODONTIC REMOVAL APPLIANCES | D2033: orthodonticrem-charge | E2033: Orthodontic removable appliances are custom-made dental devices that can be inserted and removed by the patient. These appliances are used to correct minor tooth irregularities, guide jaw growth, maintain space, or assist in orthodontic treatment by applying controlled pressure to the teeth and surrounding structures. | F2033: The procedure is performed to correct malocclusion, improve tooth alignment, guide proper jaw development, maintain or regain space for teeth, and support overall orthodontic treatment to improve oral function and dental appearance. | G2033: 400 | H2033: Dental
A2034: FLAP SURGERY PER QUADRANT | D2034: flapsurgeryper-charge | E2034: Flap surgery per quadrant is a periodontal surgical procedure performed on one section (quadrant) of the mouth in which the gums are gently lifted back to allow deep cleaning of the tooth roots and underlying bone. The procedure helps remove plaque, tartar, bacteria, and infected tissue from areas below the gum line that cannot be reached through routine cleaning methods. | F2034: The procedure is performed to treat advanced gum disease (periodontitis), reduce deep periodontal pockets, prevent further bone and tooth support loss, promote gum healing, and improve the overall health and stability of the teeth and surrounding tissues. | G2034: 500 | H2034: Dental
A2035: GINGIVECTOMY | D2035: gingivectomy-d-charge | E2035: Gingivectomy is a periodontal surgical procedure in which excess, diseased, or overgrown gum tissue is removed to reshape and improve the contour of the gums around the teeth. The procedure may be performed using surgical instruments, electrosurgery, or laser techniques. | F2035: The procedure is performed to treat gum disease, remove infected or enlarged gum tissue, reduce periodontal pockets, improve oral hygiene access, and enhance the appearance and health of the gums and supporting tooth structures. | G2035: 500 | H2035: Dental
A2036: ABSCESS DRAINAGE | D2036: abscessdrainag-charge | E2036: Abscess drainage is a dental surgical procedure in which pus and infected fluid are released from a dental or gum abscess through a small incision or opening to relieve pressure and remove the source of infection. | F2036: The procedure is performed to control and treat dental infection, reduce pain and swelling, promote healing, prevent the spread of infection, and restore oral health and comfort. | G2036: 200 | H2036: Dental
... A2139: Ipd Admission Charge | D2139: ipdadmissionch-charge | E2139: Charges applicable for inpatient department (IPD) admission. | F2139: Applied for admission processing, documentation, and inpatient administrative services. | G2139: 50 | H2139: Room

Sheet radio-charges
A1: title | B1: slug_value | C1: description | D1: purpose | E1: price | F1: category
A2: X-Ray Chest PA View | B2: x-ray-chest-pa-v-charge | C2: Posteroanterior radiograph of the chest with X-ray beam entering from posterior and exiting anterior, patient standing with chest against detector. | D2: Routine chest evaluation for lung parenchyma, cardiac silhouette, mediastinum, pleura, diaphragm, and bony thorax assessment. | E2: 0 | F2: Radiodiagnosis
A3: X-Ray Cervical Spine AP View | B3: x-ray-cervical-s-charge | C3: Anteroposterior radiographic imaging of the cervical spine to visualize vertebral alignment, intervertebral spaces, and bony integrity. | D3: Used to evaluate cervical spine trauma, degenerative changes, congenital anomalies, infections, tumors, and neck pain. | E3: 0 | F3: Radiodiagnosis
A4: Ultrasound Scan Upper Abdomen | B4: ultrasound-scan-charge | C4: Ultrasonographic imaging of upper abdominal organs including liver, gallbladder, pancreas, spleen, kidneys, and upper abdominal vessels. | D4: Used to assess abdominal pain, hepatobiliary disease, gallstones, liver pathology, pancreatitis, splenomegaly, and renal abnormalities. | E4: 0 | F4: Radiodiagnosis
A5: X-Ray Sacroiliac Joint AP & Lateral Views | B5: x-ray-sacroiliac-charge | C5: Plain radiographic examination of the pelvis with focused visualization of the sacroiliac joints using anteroposterior and lateral views. | D5: Used to assess sacroiliac joints for inflammatory, degenerative, traumatic, or structural abnormalities. | E5: 0 | F5: Radiodiagnosis
A6: Ultrasound Lower Abdomen | B6: ultrasound-lower-charge | C6: Ultrasonographic examination of the lower abdomen to visualize pelvic and lower abdominal organs. | D6: Used to evaluate pelvic organs and lower abdominal structures for masses, fluid collections, inflammation, or other pathology. | E6: 0 | F6: Radiodiagnosis
A7: X-Ray Lumbar Spine | B7: x-ray-lumbar-spi-charge | C7: Radiographic imaging of the lumbar spine to visualize vertebrae, intervertebral spaces, and alignment. | D7: Used to assess low back pain, trauma, degenerative disc disease, spondylosis, infections, and spinal deformities. | E7: 0 | F7: Radiodiagnosis
A8: X-Ray Right Knee AP & Lateral Views | B8: x-ray-right-knee-charge | C8: Radiographic imaging of the right knee in anteroposterior and lateral views. | D8: Used to evaluate trauma, arthritis, fractures, joint space narrowing, and degenerative changes. | E8: 0 | F8: Radiodiagnosis
A9: X-Ray Left Knee AP & Lateral Views | B9: x-ray-left-knee-charge | C9: Radiographic imaging of the left knee in anteroposterior and lateral views. | D9: Used for assessment of pain, injury, arthritis, fractures, and joint abnormalities. | E9: 0 | F9: Radiodiagnosis
A10: X-Ray Left Knee AP View | B10: x-ray-left-knee-charge1 | C10: Anteroposterior radiographic imaging of the left knee joint. | D10: Used to assess alignment, fractures, arthritis, and joint space abnormalities. | E10: 0 | F10: Radiodiagnosis
A11: X-Ray Left Knee Lateral View | B11: x-ray-left-knee-charge2 | C11: Lateral view radiographic imaging of the left knee joint. | D11: Used to detect fractures, effusion, patellar position, and degenerative changes. | E11: 0 | F11: Radiodiagnosis
A12: X-Ray Right Knee AP View | B12: x-ray-right-knee-charge1 | C12: Anteroposterior radiographic imaging of the right knee joint. | D12: Used to evaluate fractures, arthritis, and joint alignment. | E12: 0 | F12: Radiodiagnosis
A13: X-Ray Right Knee Lateral View | B13: x-ray-right-knee-charge2 | C13: Lateral view radiographic imaging of the right knee joint. | D13: Used for trauma assessment, effusion detection, and degenerative joint disease. | E13: 0 | F13: Radiodiagnosis
... A1248: DOPPLER LT. FOOT ARTERIAL | B1248: doppler-lt-foot-charge1 | C1248: Doppler ultrasound imaging of the arterial systems of the left foot to assess vascular patency, flow dynamics, and hemodynamic abnormalities. | D1248: Doppler ultrasound imaging of the arterial systems of the left foot to assess vascular patency, flow dynamics, and hemodynamic abnormalities. | E1248: 250 | F1248: Radiodiagnosis
